Workbook

Sheet Utilities Sector – Overview
B1: Utilities Sector – Business Model, Contract Structure & Risk Classification
B2: The Utilities sector includes companies engaged in generation, transmission, and distribution of essential services such as electricity, gas, LNG, and water. These services are critical for economic activity and daily consumption.
B4: • Power purchase agreements (PPAs)
B5: • Regulated tariffs approved by government bodies
B6: • Volume growth (electricity/gas demand)
B7: • Capacity addition and utilization
B8: • Industrial, commercial, and household consumption
B10: Company | C10: Segment | D10: Fuel / Business | E10: PPA / Contract | F10: Revenue Stability | G10: Key Risk | H10: SEB / Client Exposure | I10: Utility Type | J10: Remarks
B11: Adani Energy Solutions Limited | C11: Power Transmission | D11: Transmission | E11: Regulated | F11: Very High | G11: Minimal | H11: Low | I11: Core Utility | J11: Regulated returns
B12: Adani Green Energy Limited | C12: Renewable Power | D12: Solar/Wind | E12: PPAs | F12: High | G12: High valuation | H12: Medium | I12: Core Utility | J12: Renewable focused
B13: Adani Power Limited | C13: Power Generation | D13: Imported Coal | E13: PPAs | F13: Medium | G13: Fuel price risk | H13: Medium | I13: Core Utility | J13: Generation business
B14: Adani Total Gas Limited | C14: City Gas Distribution | D14: Natural Gas | E14: Regulated CGD | F14: High | G14: Valuation | H14: Low | I14: Core Utility | J14: Stable gas utility
B15: Agni Green Power Limited | C15: Renewable Power | D15: Solar | E15: PPAs | F15: Low | G15: Scale | H15: Medium | I15: Core Utility | J15: Renewable focused
B16: Apex Ecotech Limited | C16: Environmental Services | D16: Waste | E16: Project-based | F16: Low | G16: Execution risk | H16: Low | I16: EPC | J16: Non-core utility
B17: CESC Limited | C17: Power Distribution | D17: Coal | E17: PPAs | F17: High | G17: Regulatory | H17: Low | I17: Core Utility | J17: Non-core utility
B18: EKI Energy Services Limited | C18: Carbon Advisory | D18: Carbon credits | E18: Service contracts | F18: Medium | G18: Market volatility | H18: Medium | I18: Service | J18: Non-core utility
B19: Energy Development Company Limited | C19: Power Generation | D19: Renewable | E19: PPAs | F19: Medium | G19: Project scale | H19: Medium | I19: Core Utility | J19: Generation business
B20: GAIL (India) Limited | C20: Gas Transmission | D20: Natural Gas | E20: Long-term contracts | F20: High | G20: Gas policy | H20: Low | I20: Core Utility | J20: Stable gas utility
B21: Gita Renewable Energy Limited | C21: Renewable Power | D21: Solar/Wind | E21: PPAs | F21: Low | G21: Scale | H21: Medium | I21: Core Utility | J21: Renewable focused
... B69: Waaree Renewable Technologies Limited | C69: Renewable EPC | D69: Solar | E69: Project-based | F69: Medium | G69: Execution | H69: Medium | I69: EPC | J69: Renewable focused
B73: Source: Company Annual Reports, Investor Presentations, Regulatory Filings (PNGRB/CERC/SERC), Business Descriptions from Screener, Moneycontrol & Company Websites
B75: Segment | C75: Company business description (Annual Report / Screener)
B76: Fuel / Business | C76: Fuel mix disclosed in AR / Investor PPT
B77: PPA / Contract | C77: PPAs, CGD regulation, take-or-pay contracts
B78: Revenue Stability | C78: Derived from contract nature
B79: Key Risk | C79: Derived from sector + balance sheet reality
B80: SEB / Client Exposure | C80: Exposure to DISCOMs / Govt / private clients
B81: Utility Type | C81: Core vs Non-core based on essential utility definition
B82: Remarks | C82: Analyst conclusion (final takeaway)
B85: Below is the remark rule is used for the companies
B86: Condition | C86: Remark
B87: Regulated / PPAs / Essential service | C87: Stable utility
B88: Power generation under PPAs | C88: Generation business
B89: EPC / Trading / Infra | C89: Non-core utility
B90: Renewables + PPAs | C90: Renewable focused
B91: Execution-heavy infra | C91: Execution risk
B93: Examples:
B94: City Gas Distribution (Adani Total Gas, IGL, MGL, Gujarat Gas) | C94: Regulated CGD companies with predictable volumes and tariff protection. High revenue stability with low SEB exposure and gas price risk as key variable. Remarks logic:"Stable gas utility" because regulation + annuity-like cash flows.
B95: Gas Transmission (GAIL, GSPL, GSPC) | C95: Operate regulated pipelines with long-term contracts and assured returns. Minimal volume risk and high revenue visibility. Remarks: "Stable gas utility" / "Regulated returns".
B96: Hydro & PSU Generators (NHPC, SJVN, NTPC) | C96: Power sold under long-term PPAs with state utilities. Very high revenue stability but exposed to hydrology or SEB payment delays. Remkars: "Generation Business" (core utility)
B97: Thermal Power Generators (Adani Power, JSW Energy, RattanIndia) | C97: Coal-based power producers operating under PPAs. Exposed to fuel price volatility, leverage, and regulatory risk. Remarks: "Generation business" (risk varies by balance sheet).
B98: Renewable Power Producers (KPI, Waaree, Inox Green, Gita Renewable, NTPC Green) | C98: Solar/wind power producers operating under long-term PPAs ensuring predictable revenues. Key risks include policy changes, resource variability, DISCOM counterparty risk, and scaling constraints. Remarks: "Renewable focused"
B99: EPC / Infra / Trading Companies (Sugs Lloyd, Texmaco, PTC India, SG Mart) | C99: Project-based EPC or trading-led businesses with limited revenue visibility. Higher execution risk (for EPC), counterparty risk (for trading), and cyclicality compared to core utilities. Remarks: Non-core utility
B100: Non-Utility Industrials (Rajasthan Cylinders, Jayshree Chemicals) | C100: Manufacturing/industrial businesses not directly linked to utility services. Revenue depends on industrial demand cycles. Remarks: Non Utility

Sheet Industry Overview
B1: List of Companies Covered – Utilities Sector
B2: Coverage includes Power, Gas, LNG, Renewable Utilities
B4: Company Name | C4: Market cap | D4: Price | E4: Change % | F4: Volume | G4: Rel Volume | H4: P/E | I4: EPS dil | J4: EPS dil growth | K4: Div yield % | L4: Analyst Rating | M4: Symbol | N4: Price
B5: NTPCNTPC Limtied | C5: . | D5: 319.50 INR | E5: −1.18% | F5: 7.91 M | G5: 1.01 | H5: 13.04 | I5: 24.49 INR | J5: 0.076 | K5: 0.0266 | L5: Buy | M5: NTPCNTPC Limited | N5: 319.50 INR
B6: ADANIPOWERAdani Power Limited | C6: 2.77 T INR | D6: 139.04 INR | E6: −3.30% | F6: 14.99 M | G6: 1.39 | H6: 22.29 | I6: 6.24 INR | J6: −5.41% | K6: 0 | L6: Strong buy | M6: ADANIPOWERAdani Power Limited | N6: 139.04 INR
B7: POWERGRIDPower Grid Corporation of India Limited | C7: 2.51 T INR | D7: 265.20 INR | E7: −1.70% | F7: 10.2 M | G7: 0.76 | H7: 16.28 | I7: 16.29 INR | J7: −3.57% | K7: 0.0334 | L7: Buy | M7: POWERGRIDPower Grid Corporation of India Limited | N7: 265.20 INR
B8: ADANIGREENAdani Green Energy Limited | C8: 1.67 T INR | D8: 993.80 INR | E8: −2.35% | F8: 1.31 M | G8: 0.84 | H8: 79.59 | I8: 12.49 INR | J8: 0.8046 | K8: 0 | L8: Strong buy | M8: ADANIGREENAdani Green Energy Limited | N8: 993.80 INR
B9: TATAPOWERTata Power Company Limited | C9: 1.23 T INR | D9: 374.15 INR | E9: −2.69% | F9: 7.01 M | G9: 1.53 | H9: 29.5 | I9: 12.68 INR | J9: 0.0829 | K9: 0.0059 | L9: Neutral | M9: TATAPOWERTata Power Company Limited | N9: 374.15 INR
B10: ADANIENSOLAdani Energy Solutions Ltd | C10: 1.18 T INR | D10: 960.50 INR | E10: −1.87% | F10: 1.41 M | G10: 1.65 | H10: 51.16 | I10: 18.77 INR | J10: 3.2813 | K10: 0 | L10: Strong buy | M10: ADANIENSOLAdani Energy Solutions Ltd | N10: 960.50 INR
B11: GAILGAIL (India) Limited | C11: 1.12 T INR | D11: 166.81 INR | E11: −1.86% | F11: 10.88 M | G11: 0.75 | H11: 10.05 | I11: 16.60 INR | J11: −5.42% | K11: 0.0441 | L11: Buy | M11: GAILGAIL (India) Limited | N11: 166.81 INR
B12: ENRINSiemens Energy India Limited | C12: 1.1 T INR | D12: 2,953.80 INR | E12: −4.66% | F12: 518.82 K | G12: 0.24 | H12: — | I12: — | J12: — | K12: 0 | L12: Neutral | M12: ENRINSiemens Energy India Limited | N12: 2,953.80 INR
B13: JSWENERGYJSW Energy Limited | C13: 806.42 B INR | D13: 453.85 INR | E13: −1.75% | F13: 3.06 M | G13: 1.04 | H13: 39.18 | I13: 11.58 INR | J13: 0.0145 | K13: 0.0043 | L13: Buy | M13: JSWENERGYJSW Energy Limited | N13: 453.85 INR
B14: NHPCNHPC Limited | C14: 774.47 B INR | D14: 76.43 INR | E14: −0.83% | F14: 9.18 M | G14: 0.91 | H14: 24.21 | I14: 3.16 INR | J14: 0.0645 | K14: 0.0248 | L14: Neutral | M14: NHPCNHPC Limited | N14: 76.43 INR
B15: NTPCGREENNTPC Green Energy Limited | C15: 768.65 B INR | D15: 90.27 INR | E15: −1.03% | F15: 2.9 M | G15: 0.73 | H15: 124.96 | I15: 0.72 INR | J15: — | K15: 0 | L15: Neutral | M15: NTPCGREENNTPC Green Energy Limited | N15: 90.27 INR
B16: ATGLAdani Total Gas Ltd. | C16: 652.08 B INR | D16: 577.05 INR | E16: −2.71% | F16: 663.92 K | G16: 2.22 | H16: 101.43 | I16: 5.69 INR | J16: −10.87% | K16: 0.0004 | L16: Neutral | M16: ATGLAdani Total Gas Ltd. | N16: 577.05 INR
B17: TORNTPOWERTorrent Power Limited | C17: 647.26 B INR | D17: 1,255.10 INR | E17: −2.70% | F17: 316.75 K | G17: 0.93 | H17: 21.04 | I17: 59.66 INR | J17: 0.2783 | K17: 0.0148 | L17: Neutral | M17: TORNTPOWERTorrent Power Limited | N17: 1,255.10 INR
B18: PETRONETPetronet Lng Limited | C18: 412.28 B INR | D18: 270.80 INR | E18: −1.46% | F18: 1.51 M | G18: 0.5 | H18: 11.07 | I18: 24.46 INR | J18: −7.20% | K18: 0.0364 | L18: Neutral | M18: PETRONETPetronet Lng Limited | N18: 270.80 INR
B19: NLCINDIANLC India Limited | C19: 333.83 B INR | D19: 236.85 INR | E19: −1.07% | F19: 984.08 K | G19: 1.08 | H19: 12.57 | I19: 18.84 INR | J19: 0.4231 | K19: 0.0125 | L19: Strong buy | M19: NLCINDIANLC India Limited | N19: 236.85 INR
B20: SJVNSJVN Limited | C20: 291 B INR | D20: 71.24 INR | E20: −3.82% | F20: 4.69 M | G20: 1.88 | H20: 50.28 | I20: 1.42 INR | J20: −44.22% | K20: 0.0197 | L20: Neutral | M20: SJVNSJVN Limited | N20: 71.24 INR
B21: GUJGASLTDGujarat Gas Ltd. | C21: 279.83 B INR | D21: 400.40 INR | E21: −1.51% | F21: 257.03 K | G21: 0.56 | H21: 24.69 | I21: 16.22 INR | J21: −12.17% | K21: 0.0143 | L21: Neutral | M21: GUJGASLTDGujarat Gas Ltd. | N21: 400.40 INR
B22: IGLIndraprastha Gas Limited | C22: 268.31 B INR | D22: 185.02 INR | E22: −3.53% | F22: 1.34 M | G22: 0.48 | H22: 16.22 | I22: 11.41 INR | J22: −13.51% | K22: 0.0222 | L22: Buy | M22: IGLIndraprastha Gas Limited | N22: 185.02 INR
B23: CESCCESC Ltd | C23: 230.65 B INR | D23: 168.42 INR | E23: −3.21% | F23: 778.26 K | G23: 0.58 | H23: 15.4 | I23: 10.94 INR | J23: 0.0269 | K23: 0.0345 | L23: Strong buy | M23: CESCCESC Ltd | N23: 168.42 INR
B24: GSPLGujarat State Petronet Limited | C24: 165.54 B INR | D24: 290.45 INR | E24: −0.97% | F24: 272.79 K | G24: 0.09 | H24: 14.75 | I24: 19.69 INR | J24: −33.05% | K24: 0.017 | L24: Buy | M24: GSPLGujarat State Petronet Limited | N24: 290.45 INR
B25: RPOWERReliance Power Limited | C25: 155.88 B INR | D25: 35.40 INR | E25: −6.05% | F25: 47.51 M | G25: 1.34 | H25: 51.45 | I25: 0.69 INR | J25: −76.33% | K25: 0 | L25: Neutral | M25: RPOWERReliance Power Limited | N25: 35.40 INR
B26: NAVANava Limited | C26: 148.99 B INR | D26: 515.95 INR | E26: −1.99% | F26: 202.11 K | G26: 0.79 | H26: 15.94 | I26: 32.37 INR | J26: −17.68% | K26: 0.0171 | L26: Neutral | M26: NAVANava Limited | N26: 515.95 INR
B27: SWANCORPSwan Corp Limited | C27: 140.16 B INR | D27: 444.00 INR | E27: −0.65% | F27: 1.26 M | G27: 2.11 | H27: 23.98 | I27: 18.52 INR | J27: 0.6417 | K27: 0.0002 | L27: Neutral | M27: SWANCORPSwan Corp Limited | N27: 444.00 INR
B28: JPPOWERJaiprakash Power Ventures Limited | C28: 129.74 B INR | D28: 18.29 INR | E28: −3.33% | F28: 49.46 M | G28: 0.51 | H28: 22.86 | I28: 0.80 INR | J28: −50.89% | K28: 0 | L28: Neutral | M28: JPPOWERJaiprakash Power Ventures Limited | N28: 18.29 INR
B29: MGLMahanagar Gas Ltd | C29: 115.55 B INR | D29: 1,122.40 INR | E29: −4.07% | F29: 202.25 K | G29: 1.28 | H29: 11.34 | I29: 98.96 INR | J29: −14.38% | K29: 0.0256 | L29: Buy | M29: MGLMahanagar Gas Ltd | N29: 1,122.40 INR
B30: WAAREERTLWaaree Renewable Technologies Ltd | C30: 102.78 B INR | D30: 943.10 INR | E30: −4.26% | F30: 602.47 K | G30: 2.1 | H30: 28.15 | I30: 33.50 INR | J30: 0.7446 | K30: 0.002 | L30: Neutral | M30: WAAREERTLWaaree Renewable Technologies Ltd | N30: 943.10 INR
B31: KPIGREENKPI Green Energy Limited | C31: 83.51 B INR | D31: 395.10 INR | E31: −6.72% | F31: 1.93 M | G31: 2.32 | H31: 19.76 | I31: 19.99 INR | J31: 0.5821 | K31: 0.002 | L31: Strong buy | M31: KPIGREENKPI Green Energy Limited | N31: 395.10 INR
B32: INOXGREENInox Green Energy Services Ltd. | C32: 75.9 B INR | D32: 197.03 INR | E32: −4.53% | F32: 1.46 M | G32: 1.64 | H32: 121.31 | I32: 1.62 INR | J32: 0.6614 | K32: 0 | L32: Neutral | M32: INOXGREENInox Green Energy Services Ltd. | N32: 197.03 INR
B33: RELINFRAReliance Infrastructure Limited | C33: 63.19 B INR | D33: 146.97 INR | E33: −5.00% | F33: 1.01 M | G33: 0.93 | H33: 3.1 | I33: 47.47 INR | J33: −40.56% | K33: 0 | L33: Neutral | M33: RELINFRAReliance Infrastructure Limited | N33: 146.97 INR
B34: RTNPOWERRattanIndia Power Limited | C34: 52.09 B INR | D34: 9.34 INR | E34: −3.71% | F34: 12.71 M | G34: 1.27 | H34: 58.59 | I34: 0.16 INR | J34: −99.16% | K34: 0 | L34: Neutral | M34: RTNPOWERRattanIndia Power Limited | N34: 9.34 INR
B35: PTCPTC India Limited | C35: 46.31 B INR | D35: 152.57 INR | E35: −2.50% | F35: 790.51 K | G35: 1.23 | H35: 5.04 | I35: 30.25 INR | J35: 0.608 | K35: 0.0748 | L35: Strong buy | M35: PTCPTC India Limited | N35: 152.57 INR
B36: PACEDIGITKPace Digitek Limited | C36: 44.85 B INR | D36: 200.93 INR | E36: −3.28% | F36: 599.02 K | G36: 0.61 | H36: — | I36: — | J36: — | K36: 0 | L36: Strong buy | M36: PACEDIGITKPace Digitek Limited | N36: 200.93 INR
B37: SGMARTSG Mart Ltd | C37: 40.98 B INR | D37: 337.95 INR | E37: −1.63% | F37: 62.91 K | G37: 0.66 | H37: 33.61 | I37: 10.06 INR | J37: 0.1977 | K37: 0 | L37: Strong buy | M37: SGMARTSG Mart Ltd | N37: 337.95 INR
B38: RELTDRavindra Energy Ltd. | C38: 27.56 B INR | D38: 147.11 INR | E38: −4.21% | F38: 122.91 K | G38: 0.93 | H38: 38.28 | I38: 3.84 INR | J38: — | K38: 0 | L38: Neutral | M38: RELTDRavindra Energy Ltd. | N38: 147.11 INR
B39: GIPCLGujarat Industries Power Co. Ltd. | C39: 24.08 B INR | D39: 146.20 INR | E39: −5.84% | F39: 724.85 K | G39: 3.1 | H39: 12.02 | I39: 12.16 INR | J39: −14.58% | K39: 0.0264 | L39: Strong buy | M39: GIPCLGujarat Industries Power Co. Ltd. | N39: 146.20 INR
B40: KPELK.P. Energy Ltd. | C40: 23.6 B INR | D40: 339.05 INR | E40: −3.91% | F40: 353.62 K | G40: 1.67 | H40: 17.06 | I40: 19.87 INR | J40: 0.7168 | K40: 0.0024 | L40: Neutral | M40: KPELK.P. Energy Ltd. | N40: 339.05 INR
B41: UELUjaas Energy Limited | C41: 20.54 B INR | D41: 157.66 INR | E41: 0.0499 | F41: 2.85 K | G41: 0.16 | H41: 1554.83 | I41: 0.10 INR | J41: −81.92% | K41: 0 | L41: Neutral | M41: UELUjaas Energy Limited | N41: 157.66 INR
B42: GREENPOWEROrient Green Power Company Ltd | C42: 14.15 B INR | D42: 11.69 INR | E42: −2.99% | F42: 3.07 M | G42: 1.43 | H42: 19.71 | I42: 0.59 INR | J42: 1.0515 | K42: 0 | L42: Neutral | M42: GREENPOWEROrient Green Power Company Ltd | N42: 11.69 INR
B43: TEXINFRATexmaco Infrastructure & Holdings Limited | C43: 13.36 B INR | D43: 103.96 INR | E43: −0.99% | F43: 156.56 K | G43: 0.43 | H43: — | I43: −0.07 INR | J43: −114.96% | K43: 0.0014 | L43: Neutral | M43: TEXINFRATexmaco Infrastructure & Holdings Limited | N43: 103.96 INR
B44: JYOTISTRUCJyoti Structures Ltd. | C44: 13.05 B INR | D44: 10.36 INR | E44: −5.47% | F44: 9.5 M | G44: 1.94 | H44: 26.58 | I44: 0.39 INR | J44: 0.257 | K44: 0 | L44: Neutral | M44: JYOTISTRUCJyoti Structures Ltd. | N44: 10.36 INR
B45: DPSCLTDIndia Power Corp. Ltd. | C45: 9.96 B INR | D45: 10.48 INR | E45: 0.0244 | F45: 183.69 K | G45: 2.03 | H45: 134.19 | I45: 0.08 INR | J45: −57.25% | K45: 0.0049 | L45: Neutral | M45: DPSCLTDIndia Power Corp. Ltd. | N45: 10.48 INR
B46: RAJGASESRajasthan Gases Ltd. | C46: 3.31 B INR | D46: 43.75 INR | E46: 0.0174 | F46: 2.15 K | G46: 1.57 | H46: 6.6 | I46: 6.62 INR | J46: — | K46: 0 | L46: Neutral | M46: RAJGASESRajasthan Gases Ltd. | N46: 43.75 INR
B47: MADHAVIPLMadhav Infra Projects Ltd. | C47: 3.1 B INR | D47: 11.05 INR | E47: −4.00% | F47: 248.93 K | G47: 0.53 | H47: 8.56 | I47: 1.29 INR | J47: 1.0194 | K47: 0 | L47: Neutral | M47: MADHAVIPLMadhav Infra Projects Ltd. | N47: 11.05 INR
B48: EKIEKI Energy Services Ltd. | C48: 2.86 B INR | D48: 100.55 INR | E48: −2.90% | F48: 16.4 K | G48: 0.9 | H48: — | I48: −2.75 INR | J48: 0.8323 | K48: 0.0193 | L48: Neutral | M48: EKIEKI Energy Services Ltd. | N48: 100.55 INR
B49: SUGSLLOYDSugs Lloyd Limited | C49: 2.81 B INR | D49: 107.85 INR | E49: −10.98% | F49: 315 K | G49: 1.17 | H49: — | I49: — | J49: — | K49: 0 | L49: Neutral | M49: SUGSLLOYDSugs Lloyd Limited | N49: 107.85 INR
B50: INDOWINDIndowind Energy Limited | C50: 2.64 B INR | D50: 15.95 INR | E50: −2.74% | F50: 342.53 K | G50: 0.26 | H50: 90.88 | I50: 0.18 INR | J50: −67.65% | K50: 0 | L50: Neutral | M50: INDOWINDIndowind Energy Limited | N50: 15.95 INR
B51: APEXECOApex Ecotech Ltd. | C51: 1.72 B INR | D51: 128.95 INR | E51: −1.19% | F51: 5.6 K | G51: 0.52 | H51: 17.74 | I51: 7.27 INR | J51: — | K51: 0 | L51: Neutral | M51: APEXECOApex Ecotech Ltd. | N51: 128.95 INR
B52: POSITRONPositron Energy Limited | C52: 1.69 B INR | D52: 217.90 INR | E52: −2.05% | F52: 28.2 K | G52: 2.6 | H52: 8.47 | I52: 25.73 INR | J52: — | K52: 0 | L52: Neutral | M52: POSITRONPositron Energy Limited | N52: 217.90 INR
B53: ENERGYDEVEnergy Development Co. Ltd. | C53: 997.98 M INR | D53: 20.04 INR | E53: −2.15% | F53: 64.63 K | G53: 0.21 | H53: — | I53: −19.19 INR | J53: −3,615.56% | K53: 0 | L53: Neutral | M53: ENERGYDEVEnergy Development Co. Ltd. | N53: 20.04 INR
B54: KARMAENGKarma Energy Limited | C54: 651.62 M INR | D54: 49.23 INR | E54: −7.04% | F54: 5.75 K | G54: 2.62 | H54: 101.78 | I54: 0.48 INR | J54: — | K54: 0 | L54: Neutral | M54: KARMAENGKarma Energy Limited | N54: 49.23 INR
B55: WAAWaa Solar Ltd. | C55: 638.13 M INR | D55: 45.00 INR | E55: −6.44% | F55: 4.8 K | G55: 0.67 | H55: — | I55: — | J55: — | K55: — | L55: Neutral | M55: WAAWaa Solar Ltd. | N55: 45.00 INR
B56: CHIRAHARITChiraharit Limited | C56: 597.28 M INR | D56: 10.47 INR | E56: −3.94% | F56: 36 K | G56: 0.71 | H56: 57.28 | I56: 0.18 INR | J56: — | K56: 0 | L56: Neutral | M56: CHIRAHARITChiraharit Limited | N56: 10.47 INR
B57: RUDRAGASRudra Gas Enterprise Ltd. | C57: 582.41 M INR | D57: 68.10 INR | E57: −2.51% | F57: 2 K | G57: 0.65 | H57: 8.73 | I57: 7.80 INR | J57: 0.3959 | K57: 0 | L57: Neutral | M57: RUDRAGASRudra Gas Enterprise Ltd. | N57: 68.10 INR
B58: VENLONENTVenlon Enterprises Limited | C58: 353.68 M INR | D58: 6.77 INR | E58: 0 | F58: 62 | G58: 0.04 | H58: — | I58: −2.61 INR | J58: −615.88% | K58: 0 | L58: Neutral | M58: VENLONENTVenlon Enterprises Limited | N58: 6.77 INR
B59: JAYCHJayshree Chemicals Limited | C59: 183.58 M INR | D59: 6.15 INR | E59: −1.76% | F59: 14.26 K | G59: 1 | H59: — | I59: −0.07 INR | J59: 0.9413 | K59: 0 | L59: Neutral | M59: JAYCHJayshree Chemicals Limited | N59: 6.15 INR
B60: INDRENEWIND Renewable Energy Ltd | C60: 173.1 M INR | D60: 12.38 INR | E60: −0.40% | F60: 31.73 K | G60: 1.08 | H60: — | I60: −0.02 INR | J60: −110.21% | K60: 0 | L60: Neutral | M60: INDRENEWIND Renewable Energy Ltd | N60: 12.38 INR
B61: GITARENEWGita Renewable Energy Ltd | C61: — | D61: 90.64 INR | E61: −2.59% | F61: 997 | G61: 1.03 | H61: — | I61: — | J61: — | K61: — | L61: Neutral | M61: KKVAPOWKKV Agro Powers Ltd. | N61: 634.00 INR
B62: RCCLRajasthan Cylinders & Containers Ltd | C62: — | D62: 36.78 INR | E62: 0.0211 | F62: 49 | G62: 0.14 | H62: — | I62: — | J62: — | K62: — | L62: Neutral | M62: SRMENERGYSRM Energy Limited | N62: 22.46 INR
B63: SKILVENSkyline Ventures India Ltd | C63: — | D63: 22.00 INR | E63: −4.51% | F63: 1 | G63: 0.04 | H63: — | I63: — | J63: — | K63: — | L63: Neutral | M63: SKILVENSkyline Ventures India Ltd | N63: 22.00 INR
B64: SRMENERGYSRM Energy Limited | C64: — | D64: 22.46 INR | E64: −4.99% | F64: 406 | G64: 0.58 | H64: — | I64: — | J64: — | K64: — | L64: Neutral | M64: GITARENEWGita Renewable Energy Ltd | N64: 90.64 INR
B65: AGNIAgni Green Power Ltd. | C65: — | D65: 24.50 INR | E65: 0.0426 | F65: 15 K | G65: 1.94 | H65: 67.79 | I65: 0.36 INR | J65: 0.667 | K65: — | L65: Neutral | M65: AGNIAgni Green Power Ltd. | N65: 24.50 INR
B66: KKVAPOWKKV Agro Powers Ltd. | C66: — | D66: 634.00 INR | E66: 0.0497 | F66: 171 | G66: 0.83 | H66: — | I66: — | J66: — | K66: — | L66: Neutral | M66: RCCLRajasthan Cylinders & Containers Ltd | N66: 36.78 INR
B70: Utilities Sector Overview – India
B71: Prepared for Investment Research Purposes
B73: Industry | C73: Market cap | D73: Div yield % (indicated) | E73: Change % | F73: Volume | G73: Stocks | H73: Share
B74: Electric Utilities | C74: 15.01 T INR | D74: 0.0107 | E74: −2.36% | F74: 6.58 M | G74: 31 | H74: 0.618
B75: Alternative Power Generation | C75: 3.77 T INR | D75: 0.0223 | E75: −1.98% | F75: 9.44 M | G75: 9 | H75: 0.155
B76: Gas Distributors | C76: 3.01 T INR | D76: 0.0267 | E76: −2.14% | F76: 4.55 M | G76: 8 | H76: 0.227
B77: Water Utilities | C77: 1.72 B INR | D77: — | E77: −1.19% | F77: 5.6 K | G77: 1 | H77: ~0.0%
B79: • Electric Utilities – Power generation, transmission & distribution
B80: • Gas Utilities – City gas distribution, pipelines
B81: • LNG Utilities – Import, regasification, transmission
B82: • Renewable Utilities – Solar, wind, hybrid power producers
B83: • Water Utilities – Water supply & treatment (limited listed players)
B90: Electric Utilities – Company Snapshot
B91: Includes Generation, Transmission & Distribution Companies
B94: Symbol | C94: Market cap | D94: Price | E94: Change % | F94: Volume | G94: Rel Volume | H94: P/E | I94: EPS dil | J94: EPS dil growth | K94: Div yield % | L94: Sector | M94: Analyst Rating
B95: PTCPTC India Limited | C95: 46.31 B INR | D95: 152.57 INR | E95: −2.50% | F95: 790.51 K | G95: 1.23 | H95: 5.04 | I95: 30.25 INR | J95: 0.608 | K95: 0.0748 | L95: Utilities | M95: Strong buy
B96: PACEDIGITKPace Digitek Limited | C96: 44.85 B INR | D96: 200.93 INR | E96: −3.28% | F96: 599.02 K | G96: 0.61 | H96: — | I96: — | J96: — | K96: 0 | L96: Utilities | M96: Strong buy
B97: SGMARTSG Mart Ltd | C97: 40.98 B INR | D97: 337.95 INR | E97: −1.63% | F97: 62.91 K | G97: 0.66 | H97: 33.61 | I97: 10.06 INR | J97: 0.1977 | K97: 0 | L97: Utilities | M97: Strong buy
B98: NLCINDIANLC India Limited | C98: 333.83 B INR | D98: 236.85 INR | E98: −1.07% | F98: 984.08 K | G98: 1.08 | H98: 12.57 | I98: 18.84 INR | J98: 0.4231 | K98: 0.0125 | L98: Utilities | M98: Strong buy
B99: GIPCLGujarat Industries Power Co. Ltd. | C99: 24.08 B INR | D99: 146.20 INR | E99: −5.84% | F99: 724.85 K | G99: 3.1 | H99: 12.02 | I99: 12.16 INR | J99: −14.58% | K99: 0.0264 | L99: Utilities | M99: Strong buy
B100: CESCCESC Ltd | C100: 230.65 B INR | D100: 168.42 INR | E100: −3.21% | F100: 778.26 K | G100: 0.58 | H100: 15.4 | I100: 10.94 INR | J100: 0.0269 | K100: 0.0345 | L100: Utilities | M100: Strong buy
B101: ADANIPOWERAdani Power Limited | C101: 2.77 T INR | D101: 139.04 INR | E101: −3.30% | F101: 14.99 M | G101: 1.39 | H101: 22.29 | I101: 6.24 INR | J101: −5.41% | K101: 0 | L101: Utilities | M101: Strong buy
B102: ADANIGREENAdani Green Energy Limited | C102: 1.67 T INR | D102: 993.80 INR | E102: −2.35% | F102: 1.31 M | G102: 0.84 | H102: 79.59 | I102: 12.49 INR | J102: 0.8046 | K102: 0 | L102: Utilities | M102: Strong buy
B103: ADANIENSOLAdani Energy Solutions Ltd | C103: 1.18 T INR | D103: 960.50 INR | E103: −1.87% | F103: 1.41 M | G103: 1.65 | H103: 51.16 | I103: 18.77 INR | J103: 3.2813 | K103: 0 | L103: Utilities | M103: Strong buy
B104: JSWENERGYJSW Energy Limited | C104: 806.42 B INR | D104: 453.85 INR | E104: −1.75% | F104: 3.06 M | G104: 1.04 | H104: 39.18 | I104: 11.58 INR | J104: 0.0145 | K104: 0.0043 | L104: Utilities | M104: Buy
B105: NTPCNTPC Limited | C105: 3.14 T INR | D105: 319.50 INR | E105: −1.18% | F105: 7.91 M | G105: 1.01 | H105: 13.04 | I105: 24.49 INR | J105: 0.076 | K105: 0.0266 | L105: Utilities | M105: Buy
B106: ENERGYDEVEnergy Development Co. Ltd. | C106: 997.98 M INR | D106: 20.04 INR | E106: −2.15% | F106: 64.63 K | G106: 0.21 | H106: — | I106: −19.19 INR | J106: −3,615.56% | K106: 0 | L106: Utilities | M106: Neutral
B107: DPSCLTDIndia Power Corp. Ltd. | C107: 9.96 B INR | D107: 10.48 INR | E107: 0.0244 | F107: 183.69 K | G107: 2.03 | H107: 134.19 | I107: 0.08 INR | J107: −57.25% | K107: 0.0049 | L107: Utilities | M107: Neutral
B108: NHPCNHPC Limited | C108: 774.47 B INR | D108: 76.43 INR | E108: −0.83% | F108: 9.18 M | G108: 0.91 | H108: 24.21 | I108: 3.16 INR | J108: 0.0645 | K108: 0.0248 | L108: Utilities | M108: Neutral
B109: KARMAENGKarma Energy Limited | C109: 651.62 M INR | D109: 49.23 INR | E109: −7.04% | F109: 5.75 K | G109: 2.62 | H109: 101.78 | I109: 0.48 INR | J109: — | K109: 0 | L109: Utilities | M109: Neutral
B110: TORNTPOWERTorrent Power Limited | C110: 647.26 B INR | D110: 1,255.10 INR | E110: −2.70% | F110: 316.75 K | G110: 0.93 | H110: 21.04 | I110: 59.66 INR | J110: 0.2783 | K110: 0.0148 | L110: Utilities | M110: Neutral
B111: WAAWaa Solar Ltd. | C111: 638.13 M INR | D111: 45.00 INR | E111: −6.44% | F111: 4.8 K | G111: 0.67 | H111: — | I111: — | J111: — | K111: — | L111: Utilities | M111: Neutral
B112: RELINFRAReliance Infrastructure Limited | C112: 63.19 B INR | D112: 146.97 INR | E112: −5.00% | F112: 1.01 M | G112: 0.93 | H112: 3.1 | I112: 47.47 INR | J112: −40.56% | K112: 0 | L112: Utilities | M112: Neutral
B113: RTNPOWERRattanIndia Power Limited | C113: 52.09 B INR | D113: 9.34 INR | E113: −3.71% | F113: 12.71 M | G113: 1.27 | H113: 58.59 | I113: 0.16 INR | J113: −99.16% | K113: 0 | L113: Utilities | M113: Neutral
B114: MADHAVIPLMadhav Infra Projects Ltd. | C114: 3.1 B INR | D114: 11.05 INR | E114: −4.00% | F114: 248.93 K | G114: 0.53 | H114: 8.56 | I114: 1.29 INR | J114: 1.0194 | K114: 0 | L114: Utilities | M114: Neutral
...

Sheet Excluded Companies
A1: Excluded Companies – Screening Rationale
A3: Company Name | B3: Screening Category | C3: Reason for Not Shortlisted
A4: Reliance Power Limited | B4: Weak Financials | C4: Persistent losses, weak balance sheet, and lack of cash flow visibility
A5: RattanIndia Power Limited | B5: High Leverage | C5: High debt levels with volatile earnings and refinancing risk
A6: Adani Power Limited | B6: Fuel & Regulatory Risk | C6: High dependence on imported coal leading to margin and regulatory risk
A7: Jaiprakash Power Ventures Limited | B7: Financial Stress | C7: Stressed balance sheet with high leverage and weak profitability
A8: Reliance Infrastructure Limited | B8: Debt & Complexity | C8: Highly leveraged structure with complex and non-transparent operations
A9: Ujaas Energy Limited | B9: Weak Profitability | C9: Consistent losses and stressed financial position
A10: Sugs Lloyd Limited | B10: Non-Core Utility | C10: EPC-focused business with limited ownership of utility assets
A11: K.P. Energy Limited | B11: EPC-Driven Model | C11: Revenue dependent on project execution rather than long-term PPAs
A12: Waaree Renewable Technologies Limited | B12: Execution & Valuation Risk | C12: Earnings volatility due to execution-heavy growth and high valuation
A13: Orient Green Power Company Limited | B13: Weak Returns | C13: Low ROE and inconsistent profitability in renewable operations
A14: Indowind Energy Limited | B14: Small Scale | C14: Low operating scale with unstable margins
... A23: SRM Energy Limited | B23: Small Scale | C23: Limited size and inconsistent operating performance
A25: Note: Companies were excluded based on financial weakness, non-core utility business models, high execution or fuel risk, limited scale, or insufficient investment visibility.
A27: Initial Screening & Remaining Remaining Companies – Preliminary Screening
A29: Screening Category | B29: Approx. Number | C29: Key Reason
A30: Very Small / Illiquid Utilities | B30: ~12 | C30: Insufficient scale for investment
A31: Early-Stage Renewable Players | B31: ~8 | C31: Execution and earnings visibility risk
A32: Holding / Mixed Businesses | B32: ~6 | C32: Non-core utility exposure
A33: Limited Disclosure Companies | B33: ~4 | C33: Insufficient public financial data
A37: Company Name | B37: Screening Category | C37: Reason for Not Shortlisted
A38: Energy Development Company Limited | B38: Regional Utility | C38: Region-specific operations with limited scale and liquidity
A39: KKV Agro Powers Limited | B39: Micro Renewable Player | C39: Very small renewable capacity and limited financial visibility
A40: Pace Digitek Limited | B40: Non-Utility Business | C40: IT and digital services company, not part of utilities sector
A41: Jayshree Chemicals Limited | B41: Non-Utility Core | C41: Chemicals manufacturing business with no meaningful utility exposure
A42: Swan Corp Limited | B42: Mixed Business Model | C42: Diversified operations where utilities are not the main value driver
A43: Nava Limited | B43: Diversified Group | C43: Power business is a small part of a diversified group
... A66: Miscellaneous Energy Firms | B66: Non-Comparable | C66: Do not fit cleanly into utility investment framework
A68: Note: These companies were screened out at a preliminary stage due to limited scale, non-core utility exposure, early-stage operations, execution-driven earnings, or insufficient investment relevance.

Sheet Raw Data
A1: Raw Financial Data – Utilities Sector
A2: Financials: FY2025 or latest available , Market Data as on: 13 / 12 / 2025
A3: Currency: INR , Amounts in ₹ Crores , Shares in Crores
A4: Sources: Annual Reports , Screener , Moneycontrol , NSE/BSE
A6: Ticker | B6: Company | C6: Share Price | D6: Market Cap | E6: Total Debt | F6: Cash & Equivalents | G6: Net Debt (formula) | H6: EBITDA | I6: EBIT | J6: Net Profit | K6: Shares Outstanding | L6: EPS (formula) | M6: Equity | N6: Book Value per Share | O6: Revenue | P6: Operating Profit | Q6: Interest Expense | R6: Dividend per Share
A7: AGNI | B7: Agni Green Power Limited | C7: 24.008065 | D7: 443.58898 | E7: 103.14324 | F7: 5.2540688 | G7: =E7-F7 -> 97.889171 | H7: 28.694836 | I7: 25.966305 | J7: 6.5947356 | K7: 19.5348 | L7: =IF(K7=0, "", J7/K7) -> 0.3375891 | M7: 125.56006 | N7: 16.950391 | O7: 432.37371 | P7: =I7 -> 25.966305 | Q7: -20.602739 | R7: =J7/K7 -> 0.3375891
A8: KKVAPOW | B8: KKV Agro Powers Limited | C8: 634.21305 | D8: 395.47116 | E8: 86.270778 | F8: 6.3035521 | G8: =E8-F8 -> 79.967226 | H8: 116.62192 | I8: 96.484586 | J8: 55.480482 | K8: 0.627163 | L8: =IF(K8=0, "", J8/K8) -> 88.46262 | M8: 131.54968 | N8: 436.45882 | O8: 8813.4166 | P8: =I8 -> 96.484586 | Q8: -8.1463958 | R8: =J8/K8 -> 88.46262
A9: 523222 | B9: SRM Energy Limited | C9: 19.27 | D9: 174.5862 | E9: 484.48792 | F9: 0.10203559 | G9: =E9-F9 -> 484.38588 | H9: -4.0399801 | I9: -4.0353054 | J9: -4.0362943 | K9: 8.88 | L9: =IF(K9=0, "", J9/K9) -> -0.45453764 | M9: -584.31468 | N9: -53.785222 | O9: 0.01 | P9: =I9 -> -4.0353054 | Q9: -0.0010787904 | R9: =J9/K9 -> -0.45453764
A10: 539013 | B10: Gita Renewable Energy Limited | C10: 94 | D10: 386.55582 | E10: 0 | F10: 0.14168114 | G10: =E10-F10 -> -0.14168114 | H10: 0.1 | I10: -4.0344963 | J10: -2.796854 | K10: 4.027272 | L10: =IF(K10=0, "", J10/K10) -> -0.69447855 | M10: 89.459503 | N10: 32.54682 | O10: 0.14168114 | P10: =I10 -> -4.0344963 | Q10: -0.10859823 | R10: =J10/K10 -> -0.69447855
A11: 538919 | B11: Skyline Ventures India Limited | C11: 41.208776 | D11: 163.46153 | E11: 11.758546 | F11: 0.042072826 | G11: =E11-F11 -> 11.716473 | H11: -6.9199909 | I11: -7.0665266 | J11: -7.0622115 | K11: 3.790909 | L11: =IF(K11=0, "", J11/K11) -> -1.8629335 | M11: 0.2804855 | N11: 10.934544 | O11: 0.01 | P11: =I11 -> -7.0665266 | Q11: -0.0010787904 | R11: =J11/K11 -> -1.8629335
A12: 541445 | B12: Waa Solar Limited | C12: 46 | D12: 610.27114 | E12: 665.54068 | F12: 242.57969 | G12: =E12-F12 -> 422.96099 | H12: 64.113323 | I12: 5.112118 | J12: 17.709333 | K12: 13.031818 | L12: =IF(K12=0, "", J12/K12) -> 1.3589304 | M12: 850.68979 | N12: 148.06713 | O12: 187.0592 | P12: =I12 -> 5.112118 | Q12: -20.384014 | R12: =J12/K12 -> 1.3589304
A13: 533451 | B13: Karma Energy Limited | C13: 55.28 | D13: 636.87165 | E13: 17.591116 | F13: 2.7981126 | G13: =E13-F13 -> 14.793003 | H13: -0.25504403 | I13: -18.481657 | J13: 5.6640092 | K13: 11.512087 | L13: =IF(K13=0, "", J13/K13) -> 0.49200542 | M13: 305.40565 | N13: 36.580924 | O13: 96.835732 | P13: =I13 -> -18.481657 | Q13: -1.7335263 | R13: =J13/K13 -> 0.49200542
A14: 532219 | B14: Energy Development Company Limited | C14: 20.12 | D14: 955.7 | E14: 1449.7719 | F14: 211.72412 | G14: =E14-F14 -> 1238.0478 | H14: 229.40739 | I14: 129.26147 | J14: -922.33819 | K14: 47.599099 | L14: =IF(K14=0, "", J14/K14) -> -19.37722 | M14: -1260.1268 | N14: 3.4351208 | O14: 423.43512 | P14: =I14 -> 129.26147 | Q14: -95.006104 | R14: =J14/K14 -> -19.37722
A15: INDOWIND | B15: Indowind Energy Limited | C15: 14.57 | D15: 1897.8845 | E15: 182.42445 | F15: 10.84535 | G15: =E15-F15 -> 171.5791 | H15: 159.79475 | I15: 80.179658 | J15: 20.044195 | K15: 128.20541 | L15: =IF(K15=0, "", J15/K15) -> 0.15634439 | M15: -102.78643 | N15: 22.570635 | O15: 399.2267 | P15: =I15 -> 80.179658 | Q15: -35.708502 | R15: =J15/K15 -> 0.15634439
A16: 543284 | B16: EKI Energy Services Limited | C16: 100.95 | D16: 2790.6309 | E16: 8.1028846 | F16: 1182.7221 | G16: =E16-F16 -> -1174.6193 | H16: -71.329981 | I16: -281.36211 | J16: -91.570516 | K16: 16.243609 | L16: =IF(K16=0, "", J16/K16) -> -5.6373258 | M16: 3662.6252 | N16: 239.73105 | O16: 1366.533 | P16: =I16 -> -281.36211 | Q16: -1.8730498 | R16: =J16/K16 -> -5.6373258
A17: 539894 | B17: Madhav Infra Projects Limited | C17: 10.75 | D17: 2898.0018 | E17: 1917.3727 | F17: 881.07599 | G17: =E17-F17 -> 1036.2967 | H17: 678.28254 | I17: 582.52551 | J17: 352.98858 | K17: 272.64348 | L17: =IF(K17=0, "", J17/K17) -> 1.2946892 | M17: 1458.0865 | N17: 8.6330717 | O17: 6577.2449 | P17: =I17 -> 582.52551 | Q17: -203.03429 | R17: =J17/K17 -> 1.2946892
A18: DPSCLTD | B18: India Power Corporation Limited | C18: 10.33 | D18: 10059.247 | E18: 1640.0129 | F18: 44.30763 | G18: =E18-F18 -> 1595.7053 | H18: 25.031353 | I18: -369.99346 | J18: 73.208425 | K18: 973.78964 | L18: =IF(K18=0, "", J18/K18) -> 0.07517889 | M18: 10362.724 | N18: 9.5076143 | O18: 6421.7705 | P18: =I18 -> -369.99346 | Q18: -249.05504 | R18: =J18/K18 -> 0.07517889
... A65: GAIL | B65: GAIL (India) Limited | C65: 168.85 | D65: 1110202.2 | E65: 226463.41 | F65: 13860.531 | G65: =E65-F65 -> 212602.88 | H65: 154178.36 | I65: 111900.84 | J65: 122023.51 | K65: 6581.1111 | L65: =IF(K65=0, "", J65/K65) -> 18.541475 | M65: 702875.55 | N65: 135.57406 | O65: 1494101.6 | P65: =I65 -> 111900.84 | Q65: -7961.77 | R65: =J65/K65 -> 18.541475

Sheet Ratios
B1: Key Financial Ratios – Utilities Sector
B2: Derived from Raw Data - Financial Year: FY2025
B3: All ratios calculated using standard formulas
B4: Conditional formatting (Green = good, Red = bad)
A7: Company | B7: EV/EBITDA | C7: P/E | D7: P/B | E7: ROE | F7: ROCE | G7: Debt/Equity | H7: Interest Coverage | I7: Operating Margin | J7: Net Profit Margin | K7: Dividend Yield | L7: Valuation Score | M7: Profitability Score | N7: Risk Score | O7: Income Score | P7: Total Score
B8: Valuation vs operating earnings → Good: 8–15 | C8: Price paid per ₹1 profit → Good: 10–25 | D8: Price vs book value → Good: 1–3 | E8: Shareholder money efficiency → Good: >15% | F8: Capital efficiency (most important) → Good: >12% | G8: Debt dependence → Good: <1.5 | H8: Ability to pay interest → Good: >3 | I8: Core business profitability → Good: Positive & stable | J8: Final profitability → Good: >8% | K8: Cash return to shareholders → Good: 1–3% (sustainable) | L8: (cheap companies score higher) | M8: (higher ROE / ROCE / margins = better) | N8: (lower leverage + higher coverage) | O8: (dividend focus for utilities) | P8: Lower Total Score = Better Company
A9: ='Raw Data'!B7 -> Agni Green Power Limited | B9: =('Raw Data'!D7+'Raw Data'!E7-'Raw Data'!F7)/'Raw Data'!H7 -> 18.87023 | C9: ='Raw Data'!C7/'Raw Data'!L7 -> 71.116232 | D9: ='Raw Data'!C7/'Raw Data'!N7 -> 1.4163724 | E9: ='Raw Data'!J7/'Raw Data'!M7 -> 0.052522561 | F9: ='Raw Data'!I7/('Raw Data'!M7+'Raw Data'!E7) -> 0.11353708 | G9: ='Raw Data'!E7/'Raw Data'!M7 -> 0.82146539 | H9: ='Raw Data'!I7/'Raw Data'!Q7 -> -1.2603327 | I9: ='Raw Data'!I7/'Raw Data'!O7 -> 0.060055236 | J9: =IFERROR('Raw Data'!J7/'Raw Data'!O7, "") -> 0.015252397 | K9: ='Raw Data'!R7/'Raw Data'!C7 -> 0.014061487 | L9: =AVERAGE(_xlfn.RANK.EQ(B9,$B$9:$B$67,1), _xlfn.RANK.EQ(C9,$C$9:$C$67,1), _xlfn.RANK.EQ(D9,$D$9:$D$67,1) ) -> 37.333333 | M9: =AVERAGE( _xlfn.RANK.EQ(E9,$E$9:$E$67,0), _xlfn.RANK.EQ(F9,$F$9:$F$67,0), _xlfn.RANK.EQ(I9,$I$9:$I$67,0), _xlfn.RANK.EQ(J9,$J$9:$J$67,0) ) -> 40 | N9: =AVERAGE( _xlfn.RANK.EQ(G9,$G$9:$G$67,1), _xlfn.RANK.EQ(H9,$H$9:$H$67,0) ) -> 28 | O9: =_xlfn.RANK.EQ(K9,$K$9:$K$67,0) -> 39 | P9: =AVERAGE(L9,M9,N9,O9) -> 36.083333
A10: ='Raw Data'!B8 -> KKV Agro Powers Limited | B10: =('Raw Data'!D8+'Raw Data'!E8-'Raw Data'!F8)/'Raw Data'!H8 -> 4.0767499 | C10: ='Raw Data'!C8/'Raw Data'!L8 -> 7.1692773 | D10: ='Raw Data'!C8/'Raw Data'!N8 -> 1.453088 | E10: ='Raw Data'!J8/'Raw Data'!M8 -> 0.42174548 | F10: ='Raw Data'!I8/('Raw Data'!M8+'Raw Data'!E8) -> 0.44295466 | G10: ='Raw Data'!E8/'Raw Data'!M8 -> 0.65580379 | H10: ='Raw Data'!I8/'Raw Data'!Q8 -> -11.843837 | I10: ='Raw Data'!I8/'Raw Data'!O8 -> 0.010947467 | J10: =IFERROR('Raw Data'!J8/'Raw Data'!O8, "") -> 0.0062950028 | K10: ='Raw Data'!R8/'Raw Data'!C8 -> 0.13948407 | L10: =AVERAGE(_xlfn.RANK.EQ(B10,$B$9:$B$67,1), _xlfn.RANK.EQ(C10,$C$9:$C$67,1), _xlfn.RANK.EQ(D10,$D$9:$D$67,1) ) -> 15.333333 | M10: =AVERAGE( _xlfn.RANK.EQ(E10,$E$9:$E$67,0), _xlfn.RANK.EQ(F10,$F$9:$F$67,0), _xlfn.RANK.EQ(I10,$I$9:$I$67,0), _xlfn.RANK.EQ(J10,$J$9:$J$67,0) ) -> 29 | N10: =AVERAGE( _xlfn.RANK.EQ(G10,$G$9:$G$67,1), _xlfn.RANK.EQ(H10,$H$9:$H$67,0) ) -> 39 | O10: =_xlfn.RANK.EQ(K10,$K$9:$K$67,0) -> 4 | P10: =AVERAGE(L10,M10,N10,O10) -> 21.833333
A11: ='Raw Data'!B9 -> SRM Energy Limited | B11: =('Raw Data'!D9+'Raw Data'!E9-'Raw Data'!F9)/'Raw Data'!H9 -> -163.1127 | C11: ='Raw Data'!C9/'Raw Data'!L9 -> -42.394728 | D11: ='Raw Data'!C9/'Raw Data'!N9 -> -0.35827685 | E11: ='Raw Data'!J9/'Raw Data'!M9 -> 0.0069077406 | F11: ='Raw Data'!I9/('Raw Data'!M9+'Raw Data'!E9) -> 0.040423079 | G11: ='Raw Data'!E9/'Raw Data'!M9 -> -0.82915581 | H11: ='Raw Data'!I9/'Raw Data'!Q9 -> 3740.5833 | I11: ='Raw Data'!I9/'Raw Data'!O9 -> -403.53054 | J11: =IFERROR('Raw Data'!J9/'Raw Data'!O9, "") -> -403.62943 | K11: ='Raw Data'!R9/'Raw Data'!C9 -> -0.023587838 | L11: =AVERAGE(_xlfn.RANK.EQ(B11,$B$9:$B$67,1), _xlfn.RANK.EQ(C11,$C$9:$C$67,1), _xlfn.RANK.EQ(D11,$D$9:$D$67,1) ) -> 3 | M11: =AVERAGE( _xlfn.RANK.EQ(E11,$E$9:$E$67,0), _xlfn.RANK.EQ(F11,$F$9:$F$67,0), _xlfn.RANK.EQ(I11,$I$9:$I$67,0), _xlfn.RANK.EQ(J11,$J$9:$J$67,0) ) -> 51.5 | N11: =AVERAGE( _xlfn.RANK.EQ(G11,$G$9:$G$67,1), _xlfn.RANK.EQ(H11,$H$9:$H$67,0) ) -> 5.5 | O11: =_xlfn.RANK.EQ(K11,$K$9:$K$67,0) -> 53 | P11: =AVERAGE(L11,M11,N11,O11) -> 28.25
A12: ='Raw Data'!B10 -> Gita Renewable Energy Limited | B12: =('Raw Data'!D10+'Raw Data'!E10-'Raw Data'!F10)/'Raw Data'!H10 -> 3864.1414 | C12: ='Raw Data'!C10/'Raw Data'!L10 -> -135.35335 | D12: ='Raw Data'!C10/'Raw Data'!N10 -> 2.888147 | E12: ='Raw Data'!J10/'Raw Data'!M10 -> -0.031263912 | F12: ='Raw Data'!I10/('Raw Data'!M10+'Raw Data'!E10) -> -0.045098577 | G12: ='Raw Data'!E10/'Raw Data'!M10 -> 0 | H12: ='Raw Data'!I10/'Raw Data'!Q10 -> 37.150662 | I12: ='Raw Data'!I10/'Raw Data'!O10 -> -28.475888 | J12: =IFERROR('Raw Data'!J10/'Raw Data'!O10, "") -> -19.740482 | K12: ='Raw Data'!R10/'Raw Data'!C10 -> -0.0073880697 | L12: =AVERAGE(_xlfn.RANK.EQ(B12,$B$9:$B$67,1), _xlfn.RANK.EQ(C12,$C$9:$C$67,1), _xlfn.RANK.EQ(D12,$D$9:$D$67,1) ) -> 33 | M12: =AVERAGE( _xlfn.RANK.EQ(E12,$E$9:$E$67,0), _xlfn.RANK.EQ(F12,$F$9:$F$67,0), _xlfn.RANK.EQ(I12,$I$9:$I$67,0), _xlfn.RANK.EQ(J12,$J$9:$J$67,0) ) -> 53.5 | N12: =AVERAGE( _xlfn.RANK.EQ(G12,$G$9:$G$67,1), _xlfn.RANK.EQ(H12,$H$9:$H$67,0) ) -> 10.5 | O12: =_xlfn.RANK.EQ(K12,$K$9:$K$67,0) -> 50 | P12: =AVERAGE(L12,M12,N12,O12) -> 36.75
A13: ='Raw Data'!B11 -> Skyline Ventures India Limited | B13: =('Raw Data'!D11+'Raw Data'!E11-'Raw Data'!F11)/'Raw Data'!H11 -> -25.314774 | C13: ='Raw Data'!C11/'Raw Data'!L11 -> -22.120368 | D13: ='Raw Data'!C11/'Raw Data'!N11 -> 3.7686782 | E13: ='Raw Data'!J11/'Raw Data'!M11 -> -25.178526 | F13: ='Raw Data'!I11/('Raw Data'!M11+'Raw Data'!E11) -> -0.58696805 | G13: ='Raw Data'!E11/'Raw Data'!M11 -> 41.922115 | H13: ='Raw Data'!I11/'Raw Data'!Q11 -> 6550.4167 | I13: ='Raw Data'!I11/'Raw Data'!O11 -> -706.65266 | J13: =IFERROR('Raw Data'!J11/'Raw Data'!O11, "") -> -706.22115 | K13: ='Raw Data'!R11/'Raw Data'!C11 -> -0.045207204 | L13: =AVERAGE(_xlfn.RANK.EQ(B13,$B$9:$B$67,1), _xlfn.RANK.EQ(C13,$C$9:$C$67,1), _xlfn.RANK.EQ(D13,$D$9:$D$67,1) ) -> 19.333333 | M13: =AVERAGE( _xlfn.RANK.EQ(E13,$E$9:$E$67,0), _xlfn.RANK.EQ(F13,$F$9:$F$67,0), _xlfn.RANK.EQ(I13,$I$9:$I$67,0), _xlfn.RANK.EQ(J13,$J$9:$J$67,0) ) -> 59 | N13: =AVERAGE( _xlfn.RANK.EQ(G13,$G$9:$G$67,1), _xlfn.RANK.EQ(H13,$H$9:$H$67,0) ) -> 30 | O13: =_xlfn.RANK.EQ(K13,$K$9:$K$67,0) -> 54 | P13: =AVERAGE(L13,M13,N13,O13) -> 40.583333
A14: ='Raw Data'!B12 -> Waa Solar Limited | B14: =('Raw Data'!D12+'Raw Data'!E12-'Raw Data'!F12)/'Raw Data'!H12 -> 16.115717 | C14: ='Raw Data'!C12/'Raw Data'!L12 -> 33.850152 | D14: ='Raw Data'!C12/'Raw Data'!N12 -> 0.31066989 | E14: ='Raw Data'!J12/'Raw Data'!M12 -> 0.020817616 | F14: ='Raw Data'!I12/('Raw Data'!M12+'Raw Data'!E12) -> 0.0033715969 | G14: ='Raw Data'!E12/'Raw Data'!M12 -> 0.78235414 | H14: ='Raw Data'!I12/'Raw Data'!Q12 -> -0.25079054 | I14: ='Raw Data'!I12/'Raw Data'!O12 -> 0.027328878 | J14: =IFERROR('Raw Data'!J12/'Raw Data'!O12, "") -> 0.094672347 | K14: ='Raw Data'!R12/'Raw Data'!C12 -> 0.029541965 | L14: =AVERAGE(_xlfn.RANK.EQ(B14,$B$9:$B$67,1), _xlfn.RANK.EQ(C14,$C$9:$C$67,1), _xlfn.RANK.EQ(D14,$D$9:$D$67,1) ) -> 29.333333 | M14: =AVERAGE( _xlfn.RANK.EQ(E14,$E$9:$E$67,0), _xlfn.RANK.EQ(F14,$F$9:$F$67,0), _xlfn.RANK.EQ(I14,$I$9:$I$67,0), _xlfn.RANK.EQ(J14,$J$9:$J$67,0) ) -> 41 | N14: =AVERAGE( _xlfn.RANK.EQ(G14,$G$9:$G$67,1), _xlfn.RANK.EQ(H14,$H$9:$H$67,0) ) -> 25.5 | O14: =_xlfn.RANK.EQ(K14,$K$9:$K$67,0) -> 34 | P14: =AVERAGE(L14,M14,N14,O14) -> 32.458333
A15: ='Raw Data'!B13 -> Karma Energy Limited | B15: =('Raw Data'!D13+'Raw Data'!E13-'Raw Data'!F13)/'Raw Data'!H13 -> -2555.1065 | C15: ='Raw Data'!C13/'Raw Data'!L13 -> 112.35649 | D15: ='Raw Data'!C13/'Raw Data'!N13 -> 1.5111702 | E15: ='Raw Data'!J13/'Raw Data'!M13 -> 0.018545856 | F15: ='Raw Data'!I13/('Raw Data'!M13+'Raw Data'!E13) -> -0.057219326 | G15: ='Raw Data'!E13/'Raw Data'!M13 -> 0.057599182 | H15: ='Raw Data'!I13/'Raw Data'!Q13 -> 10.661308 | I15: ='Raw Data'!I13/'Raw Data'!O13 -> -0.19085576 | J15: =IFERROR('Raw Data'!J13/'Raw Data'!O13, "") -> 0.058490901 | K15: ='Raw Data'!R13/'Raw Data'!C13 -> 0.0089002428 | L15: =AVERAGE(_xlfn.RANK.EQ(B15,$B$9:$B$67,1), _xlfn.RANK.EQ(C15,$C$9:$C$67,1), _xlfn.RANK.EQ(D15,$D$9:$D$67,1) ) -> 25.333333 | M15: =AVERAGE( _xlfn.RANK.EQ(E15,$E$9:$E$67,0), _xlfn.RANK.EQ(F15,$F$9:$F$67,0), _xlfn.RANK.EQ(I15,$I$9:$I$67,0), _xlfn.RANK.EQ(J15,$J$9:$J$67,0) ) -> 47.25 | N15: =AVERAGE( _xlfn.RANK.EQ(G15,$G$9:$G$67,1), _xlfn.RANK.EQ(H15,$H$9:$H$67,0) ) -> 16 | O15: =_xlfn.RANK.EQ(K15,$K$9:$K$67,0) -> 44 | P15: =AVERAGE(L15,M15,N15,O15) -> 33.145833
A16: ='Raw Data'!B14 -> Energy Development Company Limited | B16: =('Raw Data'!D14+'Raw Data'!E14-'Raw Data'!F14)/'Raw Data'!H14 -> 9.562673 | C16: ='Raw Data'!C14/'Raw Data'!L14 -> -1.0383327 | D16: ='Raw Data'!C14/'Raw Data'!N14 -> 5.8571448 | E16: ='Raw Data'!J14/'Raw Data'!M14 -> 0.73194078 | F16: ='Raw Data'!I14/('Raw Data'!M14+'Raw Data'!E14) -> 0.68159653 | G16: ='Raw Data'!E14/'Raw Data'!M14 -> -1.1504969 | H16: ='Raw Data'!I14/'Raw Data'!Q14 -> -1.3605597 | I16: ='Raw Data'!I14/'Raw Data'!O14 -> 0.30526867 | J16: =IFERROR('Raw Data'!J14/'Raw Data'!O14, "") -> -2.1782279 | K16: ='Raw Data'!R14/'Raw Data'!C14 -> -0.96308248 | L16: =AVERAGE(_xlfn.RANK.EQ(B16,$B$9:$B$67,1), _xlfn.RANK.EQ(C16,$C$9:$C$67,1), _xlfn.RANK.EQ(D16,$D$9:$D$67,1) ) -> 28.333333 | M16: =AVERAGE( _xlfn.RANK.EQ(E16,$E$9:$E$67,0), _xlfn.RANK.EQ(F16,$F$9:$F$67,0), _xlfn.RANK.EQ(I16,$I$9:$I$67,0), _xlfn.RANK.EQ(J16,$J$9:$J$67,0) ) -> 18.5 | N16: =AVERAGE( _xlfn.RANK.EQ(G16,$G$9:$G$67,1), _xlfn.RANK.EQ(H16,$H$9:$H$67,0) ) -> 12.5 | O16: =_xlfn.RANK.EQ(K16,$K$9:$K$67,0) -> 59 | P16: =AVERAGE(L16,M16,N16,O16) -> 29.583333
A17: ='Raw Data'!B15 -> Indowind Energy Limited | B17: =('Raw Data'!D15+'Raw Data'!E15-'Raw Data'!F15)/'Raw Data'!H15 -> 12.950761 | C17: ='Raw Data'!C15/'Raw Data'!L15 -> 93.191706 | D17: ='Raw Data'!C15/'Raw Data'!N15 -> 0.64552903 | E17: ='Raw Data'!J15/'Raw Data'!M15 -> -0.19500819 | F17: ='Raw Data'!I15/('Raw Data'!M15+'Raw Data'!E15) -> 1.0068013 | G17: ='Raw Data'!E15/'Raw Data'!M15 -> -1.7747911 | H17: ='Raw Data'!I15/'Raw Data'!Q15 -> -2.2453941 | I17: ='Raw Data'!I15/'Raw Data'!O15 -> 0.20083741 | J17: =IFERROR('Raw Data'!J15/'Raw Data'!O15, "") -> 0.050207551 | K17: ='Raw Data'!R15/'Raw Data'!C15 -> 0.010730569 | L17: =AVERAGE(_xlfn.RANK.EQ(B17,$B$9:$B$67,1), _xlfn.RANK.EQ(C17,$C$9:$C$67,1), _xlfn.RANK.EQ(D17,$D$9:$D$67,1) ) -> 31.666667 | M17: =AVERAGE( _xlfn.RANK.EQ(E17,$E$9:$E$67,0), _xlfn.RANK.EQ(F17,$F$9:$F$67,0), _xlfn.RANK.EQ(I17,$I$9:$I$67,0), _xlfn.RANK.EQ(J17,$J$9:$J$67,0) ) -> 29 | N17: =AVERAGE( _xlfn.RANK.EQ(G17,$G$9:$G$67,1), _xlfn.RANK.EQ(H17,$H$9:$H$67,0) ) -> 16 | O17: =_xlfn.RANK.EQ(K17,$K$9:$K$67,0) -> 42 | P17: =AVERAGE(L17,M17,N17,O17) -> 29.666667
A18: ='Raw Data'!B16 -> EKI Energy Services Limited | B18: =('Raw Data'!D16+'Raw Data'!E16-'Raw Data'!F16)/'Raw Data'!H16 -> -22.655434 | C18: ='Raw Data'!C16/'Raw Data'!L16 -> -17.907427 | D18: ='Raw Data'!C16/'Raw Data'!N16 -> 0.42109689 | E18: ='Raw Data'!J16/'Raw Data'!M16 -> -0.025001334 | F18: ='Raw Data'!I16/('Raw Data'!M16+'Raw Data'!E16) -> -0.076650219 | G18: ='Raw Data'!E16/'Raw Data'!M16 -> 0.0022123161 | H18: ='Raw Data'!I16/'Raw Data'!Q16 -> 150.21603 | I18: ='Raw Data'!I16/'Raw Data'!O16 -> -0.20589485 | J18: =IFERROR('Raw Data'!J16/'Raw Data'!O16, "") -> -0.06700937 | K18: ='Raw Data'!R16/'Raw Data'!C16 -> -0.055842752 | L18: =AVERAGE(_xlfn.RANK.EQ(B18,$B$9:$B$67,1), _xlfn.RANK.EQ(C18,$C$9:$C$67,1), _xlfn.RANK.EQ(D18,$D$9:$D$67,1) ) -> 5.6666667 | M18: =AVERAGE( _xlfn.RANK.EQ(E18,$E$9:$E$67,0), _xlfn.RANK.EQ(F18,$F$9:$F$67,0), _xlfn.RANK.EQ(I18,$I$9:$I$67,0), _xlfn.RANK.EQ(J18,$J$9:$J$67,0) ) -> 51.5 | N18: =AVERAGE( _xlfn.RANK.EQ(G18,$G$9:$G$67,1), _xlfn.RANK.EQ(H18,$H$9:$H$67,0) ) -> 10 | O18: =_xlfn.RANK.EQ(K18,$K$9:$K$67,0) -> 55 | P18: =AVERAGE(L18,M18,N18,O18) -> 30.541667
A19: ='Raw Data'!B17 -> Madhav Infra Projects Limited | B19: =('Raw Data'!D17+'Raw Data'!E17-'Raw Data'!F17)/'Raw Data'!H17 -> 5.8003829 | C19: ='Raw Data'!C17/'Raw Data'!L17 -> 8.3031507 | D19: ='Raw Data'!C17/'Raw Data'!N17 -> 1.2452115 | E19: ='Raw Data'!J17/'Raw Data'!M17 -> 0.2420903 | F19: ='Raw Data'!I17/('Raw Data'!M17+'Raw Data'!E17) -> 0.17257668 | G19: ='Raw Data'!E17/'Raw Data'!M17 -> 1.3149924 | H19: ='Raw Data'!I17/'Raw Data'!Q17 -> -2.8690992 | I19: ='Raw Data'!I17/'Raw Data'!O17 -> 0.088566796 | J19: =IFERROR('Raw Data'!J17/'Raw Data'!O17, "") -> 0.053668152 | K19: ='Raw Data'!R17/'Raw Data'!C17 -> 0.12043621 | L19: =AVERAGE(_xlfn.RANK.EQ(B19,$B$9:$B$67,1), _xlfn.RANK.EQ(C19,$C$9:$C$67,1), _xlfn.RANK.EQ(D19,$D$9:$D$67,1) ) -> 14.666667 | M19: =AVERAGE( _xlfn.RANK.EQ(E19,$E$9:$E$67,0), _xlfn.RANK.EQ(F19,$F$9:$F$67,0), _xlfn.RANK.EQ(I19,$I$9:$I$67,0), _xlfn.RANK.EQ(J19,$J$9:$J$67,0) ) -> 28.5 | N19: =AVERAGE( _xlfn.RANK.EQ(G19,$G$9:$G$67,1), _xlfn.RANK.EQ(H19,$H$9:$H$67,0) ) -> 37 | O19: =_xlfn.RANK.EQ(K19,$K$9:$K$67,0) -> 5 | P19: =AVERAGE(L19,M19,N19,O19) -> 21.291667
A20: ='Raw Data'!B18 -> India Power Corporation Limited | B20: =('Raw Data'!D18+'Raw Data'!E18-'Raw Data'!F18)/'Raw Data'!H18 -> 465.61415 | C20: ='Raw Data'!C18/'Raw Data'!L18 -> 137.40559 | D20: ='Raw Data'!C18/'Raw Data'!N18 -> 1.0864976 | E20: ='Raw Data'!J18/'Raw Data'!M18 -> 0.0070645929 | F20: ='Raw Data'!I18/('Raw Data'!M18+'Raw Data'!E18) -> -0.030825758 | G20: ='Raw Data'!E18/'Raw Data'!M18 -> 0.1582608 | H20: ='Raw Data'!I18/'Raw Data'!Q18 -> 1.4855892 | I20: ='Raw Data'!I18/'Raw Data'!O18 -> -0.057615491 | J20: =IFERROR('Raw Data'!J18/'Raw Data'!O18, "") -> 0.011400037 | K20: ='Raw Data'!R18/'Raw Data'!C18 -> 0.0072777241 | L20: =AVERAGE(_xlfn.RANK.EQ(B20,$B$9:$B$67,1), _xlfn.RANK.EQ(C20,$C$9:$C$67,1), _xlfn.RANK.EQ(D20,$D$9:$D$67,1) ) -> 42 | M20: =AVERAGE( _xlfn.RANK.EQ(E20,$E$9:$E$67,0), _xlfn.RANK.EQ(F20,$F$9:$F$67,0), _xlfn.RANK.EQ(I20,$I$9:$I$67,0), _xlfn.RANK.EQ(J20,$J$9:$J$67,0) ) -> 48 | N20: =AVERAGE( _xlfn.RANK.EQ(G20,$G$9:$G$67,1), _xlfn.RANK.EQ(H20,$H$9:$H$67,0) ) -> 20 | O20: =_xlfn.RANK.EQ(K20,$K$9:$K$67,0) -> 47 | P20: =AVERAGE(L20,M20,N20,O20) -> 39.25
... A67: ='Raw Data'!B65 -> GAIL (India) Limited | B67: =('Raw Data'!D65+'Raw Data'!E65-'Raw Data'!F65)/'Raw Data'!H65 -> 8.5797064 | C67: ='Raw Data'!C65/'Raw Data'!L65 -> 9.1066108 | D67: ='Raw Data'!C65/'Raw Data'!N65 -> 1.2454448 | E67: ='Raw Data'!J65/'Raw Data'!M65 -> 0.17360614 | F67: ='Raw Data'!I65/('Raw Data'!M65+'Raw Data'!E65) -> 0.12040907 | G67: ='Raw Data'!E65/'Raw Data'!M65 -> 0.3221956 | H67: ='Raw Data'!I65/'Raw Data'!Q65 -> -14.054769 | I67: ='Raw Data'!I65/'Raw Data'!O65 -> 0.07489507 | J67: =IFERROR('Raw Data'!J65/'Raw Data'!O65, "") -> 0.081670157 | K67: ='Raw Data'!R65/'Raw Data'!C65 -> 0.10981034 | L67: =AVERAGE(_xlfn.RANK.EQ(B67,$B$9:$B$67,1), _xlfn.RANK.EQ(C67,$C$9:$C$67,1), _xlfn.RANK.EQ(D67,$D$9:$D$67,1) ) -> 17.333333 | M67: =AVERAGE( _xlfn.RANK.EQ(E67,$E$9:$E$67,0), _xlfn.RANK.EQ(F67,$F$9:$F$67,0), _xlfn.RANK.EQ(I67,$I$9:$I$67,0), _xlfn.RANK.EQ(J67,$J$9:$J$67,0) ) -> 31.75 | N67: =AVERAGE( _xlfn.RANK.EQ(G67,$G$9:$G$67,1), _xlfn.RANK.EQ(H67,$H$9:$H$67,0) ) -> 38.5 | O67: =_xlfn.RANK.EQ(K67,$K$9:$K$67,0) -> 7 | P67: =AVERAGE(L67,M67,N67,O67) -> 23.645833

Sheet Selecting on the basis of Ratio
A5: Company | B5: Filtering as per Column C to L | C5: EV/EBITDA | D5: P/E | E5: P/B | F5: ROE | G5: ROCE | H5: Debt/Equity | I5: Interest Coverage | J5: Operating Margin | K5: Net Profit Margin | L5: Dividend Yield | M5: Valuation Score | N5: Profitability Score | O5: Risk Score | P5: Income Score | Q5: Total Score | R5: Selection (Rank)
A6: ='Raw Data'!B41 -> Adani Power Limited | B6: =COUNTIF($C$69:$L$98,A6) -> 6 | C6: =('Raw Data'!D41+'Raw Data'!E41-'Raw Data'!F41)/'Raw Data'!H41 -> 14.747371 | D6: ='Raw Data'!C41/'Raw Data'!L41 -> 22.265673 | E6: ='Raw Data'!C41/'Raw Data'!N41 -> 4.5832997 | F6: ='Raw Data'!J41/'Raw Data'!M41 -> 0.36392917 | G6: ='Raw Data'!I41/('Raw Data'!M41+'Raw Data'!E41) -> 0.19976001 | H6: ='Raw Data'!E41/'Raw Data'!M41 -> 1.4658921 | I6: ='Raw Data'!I41/'Raw Data'!Q41 -> -5.1653446 | J6: ='Raw Data'!I41/'Raw Data'!O41 -> 0.29356424 | K6: =IFERROR('Raw Data'!J41/'Raw Data'!O41, "") -> 0.21688893 | L6: ='Raw Data'!R41/'Raw Data'!C41 -> 0.044912184 | M6: =AVERAGE(_xlfn.RANK.EQ(C6,$C$6:$C$64,1), _xlfn.RANK.EQ(D6,$D$6:$D$64,1), _xlfn.RANK.EQ(E6,$E$6:$E$64,1) ) -> 42 | N6: =AVERAGE( _xlfn.RANK.EQ(F6,$F$6:$F$64,0), _xlfn.RANK.EQ(G6,$G$6:$G$64,0), _xlfn.RANK.EQ(J6,$J$6:$J$64,0), _xlfn.RANK.EQ(K6,$K$6:$K$64,0) ) -> 12.75 | O6: =AVERAGE( _xlfn.RANK.EQ(H6,$H$6:$H$64,1), _xlfn.RANK.EQ(I6,$I$6:$I$64,0) ) -> 41.5 | P6: =_xlfn.RANK.EQ(L6,$L$6:$L$64,0) -> 26 | Q6: =AVERAGE(M6,N6,O6,P6) -> 30.5625 | R6: =IF(Q6<=20,"Excellent",IF(Q6<=25,"Very Good",IF(Q6<=30,"Decent",IF(Q6<=35,"Average","Weak/Avoid")))) -> Average
A7: ='Raw Data'!B47 -> K.P. Energy Limited | B7: =COUNTIF($C$69:$L$98,A7) -> 6 | C7: =('Raw Data'!D47+'Raw Data'!E47-'Raw Data'!F47)/'Raw Data'!H47 -> 11.766423 | D7: ='Raw Data'!C47/'Raw Data'!L47 -> 16.99577 | E7: ='Raw Data'!C47/'Raw Data'!N47 -> 6.0149248 | F7: ='Raw Data'!J47/'Raw Data'!M47 -> 0.39651643 | G7: ='Raw Data'!I47/('Raw Data'!M47+'Raw Data'!E47) -> 0.26428625 | H7: ='Raw Data'!E47/'Raw Data'!M47 -> 1.3621101 | I7: ='Raw Data'!I47/'Raw Data'!Q47 -> -581.32448 | J7: ='Raw Data'!I47/'Raw Data'!O47 -> 0.18554535 | K7: =IFERROR('Raw Data'!J47/'Raw Data'!O47, "") -> 0.11785189 | L7: ='Raw Data'!R47/'Raw Data'!C47 -> 0.05883817 | M7: =AVERAGE(_xlfn.RANK.EQ(C7,$C$6:$C$64,1), _xlfn.RANK.EQ(D7,$D$6:$D$64,1), _xlfn.RANK.EQ(E7,$E$6:$E$64,1) ) -> 38.666667 | N7: =AVERAGE( _xlfn.RANK.EQ(F7,$F$6:$F$64,0), _xlfn.RANK.EQ(G7,$G$6:$G$64,0), _xlfn.RANK.EQ(J7,$J$6:$J$64,0), _xlfn.RANK.EQ(K7,$K$6:$K$64,0) ) -> 17 | O7: =AVERAGE( _xlfn.RANK.EQ(H7,$H$6:$H$64,1), _xlfn.RANK.EQ(I7,$I$6:$I$64,0) ) -> 50 | P7: =_xlfn.RANK.EQ(L7,$L$6:$L$64,0) -> 20 | Q7: =AVERAGE(M7,N7,O7,P7) -> 31.416667 | R7: =IF(Q7<=20,"Excellent",IF(Q7<=25,"Very Good",IF(Q7<=30,"Decent",IF(Q7<=35,"Average","Weak/Avoid")))) -> Average
A8: ='Raw Data'!B34 -> Torrent Power Limited | B8: =COUNTIF($C$69:$L$98,A8) -> 6 | C8: =('Raw Data'!D34+'Raw Data'!E34-'Raw Data'!F34)/'Raw Data'!H34 -> 13.996731 | D8: ='Raw Data'!C34/'Raw Data'!L34 -> 22.416167 | E8: ='Raw Data'!C34/'Raw Data'!N34 -> 3.4976448 | F8: ='Raw Data'!J34/'Raw Data'!M34 -> 0.20058306 | G8: ='Raw Data'!I34/('Raw Data'!M34+'Raw Data'!E34) -> 0.15575351 | H8: ='Raw Data'!E34/'Raw Data'!M34 -> 0.6453041 | I8: ='Raw Data'!I34/'Raw Data'!Q34 -> -3.6408347 | J8: ='Raw Data'!I34/'Raw Data'!O34 -> 0.12520267 | K8: =IFERROR('Raw Data'!J34/'Raw Data'!O34, "") -> 0.097999494 | L8: ='Raw Data'!R34/'Raw Data'!C34 -> 0.044610659 | M8: =AVERAGE(_xlfn.RANK.EQ(C8,$C$6:$C$64,1), _xlfn.RANK.EQ(D8,$D$6:$D$64,1), _xlfn.RANK.EQ(E8,$E$6:$E$64,1) ) -> 39.666667 | N8: =AVERAGE( _xlfn.RANK.EQ(F8,$F$6:$F$64,0), _xlfn.RANK.EQ(G8,$G$6:$G$64,0), _xlfn.RANK.EQ(J8,$J$6:$J$64,0), _xlfn.RANK.EQ(K8,$K$6:$K$64,0) ) -> 25.75 | O8: =AVERAGE( _xlfn.RANK.EQ(H8,$H$6:$H$64,1), _xlfn.RANK.EQ(I8,$I$6:$I$64,0) ) -> 35 | P8: =_xlfn.RANK.EQ(L8,$L$6:$L$64,0) -> 27 | Q8: =AVERAGE(M8,N8,O8,P8) -> 31.854167 | R8: =IF(Q8<=20,"Excellent",IF(Q8<=25,"Very Good",IF(Q8<=30,"Decent",IF(Q8<=35,"Average","Weak/Avoid")))) -> Average
A9: ='Raw Data'!B51 -> Waaree Renewable Technologies Limited | B9: =COUNTIF($C$69:$L$98,A9) -> 5 | C9: =('Raw Data'!D51+'Raw Data'!E51-'Raw Data'!F51)/'Raw Data'!H51 -> 29.577114 | D9: ='Raw Data'!C51/'Raw Data'!L51 -> 40.848806 | E9: ='Raw Data'!C51/'Raw Data'!N51 -> 20.55474 | F9: ='Raw Data'!J51/'Raw Data'!M51 -> 1.1167919 | G9: ='Raw Data'!I51/('Raw Data'!M51+'Raw Data'!E51) -> 1.3094245 | H9: ='Raw Data'!E51/'Raw Data'!M51 -> 0.13339702 | I9: ='Raw Data'!I51/'Raw Data'!Q51 -> -19.692367 | J9: ='Raw Data'!I51/'Raw Data'!O51 -> 0.19059985 | K9: =IFERROR('Raw Data'!J51/'Raw Data'!O51, "") -> 0.14342745 | L9: ='Raw Data'!R51/'Raw Data'!C51 -> 0.02448052 | M9: =AVERAGE(_xlfn.RANK.EQ(C9,$C$6:$C$64,1), _xlfn.RANK.EQ(D9,$D$6:$D$64,1), _xlfn.RANK.EQ(E9,$E$6:$E$64,1) ) -> 51.333333 | N9: =AVERAGE( _xlfn.RANK.EQ(F9,$F$6:$F$64,0), _xlfn.RANK.EQ(G9,$G$6:$G$64,0), _xlfn.RANK.EQ(J9,$J$6:$J$64,0), _xlfn.RANK.EQ(K9,$K$6:$K$64,0) ) -> 9.75 | O9: =AVERAGE( _xlfn.RANK.EQ(H9,$H$6:$H$64,1), _xlfn.RANK.EQ(I9,$I$6:$I$64,0) ) -> 36.5 | P9: =_xlfn.RANK.EQ(L9,$L$6:$L$64,0) -> 37 | Q9: =AVERAGE(M9,N9,O9,P9) -> 33.645833 | R9: =IF(Q9<=20,"Excellent",IF(Q9<=25,"Very Good",IF(Q9<=30,"Decent",IF(Q9<=35,"Average","Weak/Avoid")))) -> Average
A10: ='Raw Data'!B55 -> Apex Ecotech Limited | B10: =COUNTIF($C$69:$L$98,A10) -> 6 | C10: =('Raw Data'!D55+'Raw Data'!E55-'Raw Data'!F55)/'Raw Data'!H55 -> 12.887644 | D10: ='Raw Data'!C55/'Raw Data'!L55 -> 18.667193 | E10: ='Raw Data'!C55/'Raw Data'!N55 -> 3.6659147 | F10: ='Raw Data'!J55/'Raw Data'!M55 -> 0.7210143 | G10: ='Raw Data'!I55/('Raw Data'!M55+'Raw Data'!E55) -> 0.91387203 | H10: ='Raw Data'!E55/'Raw Data'!M55 -> 0.0060171447 | I10: ='Raw Data'!I55/'Raw Data'!Q55 -> -174.21338 | J10: ='Raw Data'!I55/'Raw Data'!O55 -> 0.14937874 | K10: =IFERROR('Raw Data'!J55/'Raw Data'!O55, "") -> 0.1171499 | L10: ='Raw Data'!R55/'Raw Data'!C55 -> 0.053569917 | M10: =AVERAGE(_xlfn.RANK.EQ(C10,$C$6:$C$64,1), _xlfn.RANK.EQ(D10,$D$6:$D$64,1), _xlfn.RANK.EQ(E10,$E$6:$E$64,1) ) -> 38.333333 | N10: =AVERAGE( _xlfn.RANK.EQ(F10,$F$6:$F$64,0), _xlfn.RANK.EQ(G10,$G$6:$G$64,0), _xlfn.RANK.EQ(J10,$J$6:$J$64,0), _xlfn.RANK.EQ(K10,$K$6:$K$64,0) ) -> 15.25 | O10: =AVERAGE( _xlfn.RANK.EQ(H10,$H$6:$H$64,1), _xlfn.RANK.EQ(I10,$I$6:$I$64,0) ) -> 35 | P10: =_xlfn.RANK.EQ(L10,$L$6:$L$64,0) -> 23 | Q10: =AVERAGE(M10,N10,O10,P10) -> 27.895833 | R10: =IF(Q10<=20,"Excellent",IF(Q10<=25,"Very Good",IF(Q10<=30,"Decent",IF(Q10<=35,"Average","Weak/Avoid")))) -> Decent
A11: ='Raw Data'!B61 -> Indraprastha Gas Limited | B11: =COUNTIF($C$69:$L$98,A11) -> 7 | C11: =('Raw Data'!D61+'Raw Data'!E61-'Raw Data'!F61)/'Raw Data'!H61 -> 12.748116 | D11: ='Raw Data'!C61/'Raw Data'!L61 -> 14.756108 | E11: ='Raw Data'!C61/'Raw Data'!N61 -> 2.3152273 | F11: ='Raw Data'!J61/'Raw Data'!M61 -> 0.16059533 | G11: ='Raw Data'!I61/('Raw Data'!M61+'Raw Data'!E61) -> 0.1358562 | H11: ='Raw Data'!E61/'Raw Data'!M61 -> 0.00901415 | I11: ='Raw Data'!I61/'Raw Data'!Q61 -> -181.31095 | J11: ='Raw Data'!I61/'Raw Data'!O61 -> 0.092771033 | K11: =IFERROR('Raw Data'!J61/'Raw Data'!O61, "") -> 0.10868474 | L11: ='Raw Data'!R61/'Raw Data'!C61 -> 0.067768549 | M11: =AVERAGE(_xlfn.RANK.EQ(C11,$C$6:$C$64,1), _xlfn.RANK.EQ(D11,$D$6:$D$64,1), _xlfn.RANK.EQ(E11,$E$6:$E$64,1) ) -> 30.333333 | N11: =AVERAGE( _xlfn.RANK.EQ(F11,$F$6:$F$64,0), _xlfn.RANK.EQ(G11,$G$6:$G$64,0), _xlfn.RANK.EQ(J11,$J$6:$J$64,0), _xlfn.RANK.EQ(K11,$K$6:$K$64,0) ) -> 29.25 | O11: =AVERAGE( _xlfn.RANK.EQ(H11,$H$6:$H$64,1), _xlfn.RANK.EQ(I11,$I$6:$I$64,0) ) -> 36 | P11: =_xlfn.RANK.EQ(L11,$L$6:$L$64,0) -> 14 | Q11: =AVERAGE(M11,N11,O11,P11) -> 27.395833 | R11: =IF(Q11<=20,"Excellent",IF(Q11<=25,"Very Good",IF(Q11<=30,"Decent",IF(Q11<=35,"Average","Weak/Avoid")))) -> Decent
A12: ='Raw Data'!B50 -> KPI Green Energy Limited | B12: =COUNTIF($C$69:$L$98,A12) -> 6 | C12: =('Raw Data'!D50+'Raw Data'!E50-'Raw Data'!F50)/'Raw Data'!H50 -> 14.083948 | D12: ='Raw Data'!C50/'Raw Data'!L50 -> 22.050734 | E12: ='Raw Data'!C50/'Raw Data'!N50 -> 2.8761563 | F12: ='Raw Data'!J50/'Raw Data'!M50 -> 0.55499477 | G12: ='Raw Data'!I50/('Raw Data'!M50+'Raw Data'!E50) -> 0.2635707 | H12: ='Raw Data'!E50/'Raw Data'!M50 -> 2.2439262 | I12: ='Raw Data'!I50/'Raw Data'!Q50 -> -6.1756095 | J12: ='Raw Data'!I50/'Raw Data'!O50 -> 0.28234295 | K12: =IFERROR('Raw Data'!J50/'Raw Data'!O50, "") -> 0.18327269 | L12: ='Raw Data'!R50/'Raw Data'!C50 -> 0.045349964 | M12: =AVERAGE(_xlfn.RANK.EQ(C12,$C$6:$C$64,1), _xlfn.RANK.EQ(D12,$D$6:$D$64,1), _xlfn.RANK.EQ(E12,$E$6:$E$64,1) ) -> 37.666667 | N12: =AVERAGE( _xlfn.RANK.EQ(F12,$F$6:$F$64,0), _xlfn.RANK.EQ(G12,$G$6:$G$64,0), _xlfn.RANK.EQ(J12,$J$6:$J$64,0), _xlfn.RANK.EQ(K12,$K$6:$K$64,0) ) -> 11.75 | O12: =AVERAGE( _xlfn.RANK.EQ(H12,$H$6:$H$64,1), _xlfn.RANK.EQ(I12,$I$6:$I$64,0) ) -> 45.5 | P12: =_xlfn.RANK.EQ(L12,$L$6:$L$64,0) -> 25 | Q12: =AVERAGE(M12,N12,O12,P12) -> 29.979167 | R12: =IF(Q12<=20,"Excellent",IF(Q12<=25,"Very Good",IF(Q12<=30,"Decent",IF(Q12<=35,"Average","Weak/Avoid")))) -> Decent
A13: ='Raw Data'!B30 -> Nava Limited | B13: =COUNTIF($C$69:$L$98,A13) -> 6 | C13: =('Raw Data'!D30+'Raw Data'!E30-'Raw Data'!F30)/'Raw Data'!H30 -> 9.0896363 | D13: ='Raw Data'!C30/'Raw Data'!L30 -> 17.218832 | E13: ='Raw Data'!C30/'Raw Data'!N30 -> 1.9600105 | F13: ='Raw Data'!J30/'Raw Data'!M30 -> 0.13094144 | G13: ='Raw Data'!I30/('Raw Data'!M30+'Raw Data'!E30) -> 0.15830571 | H13: ='Raw Data'!E30/'Raw Data'!M30 -> 0.22656686 | I13: ='Raw Data'!I30/'Raw Data'!Q30 -> -242.69039 | J13: ='Raw Data'!I30/'Raw Data'!O30 -> 0.34040571 | K13: =IFERROR('Raw Data'!J30/'Raw Data'!O30, "") -> 0.22955467 | L13: ='Raw Data'!R30/'Raw Data'!C30 -> 0.058075947 | M13: =AVERAGE(_xlfn.RANK.EQ(C13,$C$6:$C$64,1), _xlfn.RANK.EQ(D13,$D$6:$D$64,1), _xlfn.RANK.EQ(E13,$E$6:$E$64,1) ) -> 28 | N13: =AVERAGE( _xlfn.RANK.EQ(F13,$F$6:$F$64,0), _xlfn.RANK.EQ(G13,$G$6:$G$64,0), _xlfn.RANK.EQ(J13,$J$6:$J$64,0), _xlfn.RANK.EQ(K13,$K$6:$K$64,0) ) -> 18 | O13: =AVERAGE( _xlfn.RANK.EQ(H13,$H$6:$H$64,1), _xlfn.RANK.EQ(I13,$I$6:$I$64,0) ) -> 43.5 | P13: =_xlfn.RANK.EQ(L13,$L$6:$L$64,0) -> 21 | Q13: =AVERAGE(M13,N13,O13,P13) -> 27.625 | R13: =IF(Q13<=20,"Excellent",IF(Q13<=25,"Very Good",IF(Q13<=30,"Decent",IF(Q13<=35,"Average","Weak/Avoid")))) -> Decent
A14: ='Raw Data'!B42 -> NTPC Limited | B14: =COUNTIF($C$69:$L$98,A14) -> 5 | C14: =('Raw Data'!D42+'Raw Data'!E42-'Raw Data'!F42)/'Raw Data'!H42 -> 10.228818 | D14: ='Raw Data'!C42/'Raw Data'!L42 -> 13.002939 | E14: ='Raw Data'!C42/'Raw Data'!N42 -> 1.60822 | F14: ='Raw Data'!J42/'Raw Data'!M42 -> 0.13762299 | G14: ='Raw Data'!I42/('Raw Data'!M42+'Raw Data'!E42) -> 0.085176052 | H14: ='Raw Data'!E42/'Raw Data'!M42 -> 1.4768489 | I14: ='Raw Data'!I42/'Raw Data'!Q42 -> -2.7176365 | J14: ='Raw Data'!I42/'Raw Data'!O42 -> 0.19495721 | K14: =IFERROR('Raw Data'!J42/'Raw Data'!O42, "") -> 0.12717838 | L14: ='Raw Data'!R42/'Raw Data'!C42 -> 0.076905689 | M14: =AVERAGE(_xlfn.RANK.EQ(C14,$C$6:$C$64,1), _xlfn.RANK.EQ(D14,$D$6:$D$64,1), _xlfn.RANK.EQ(E14,$E$6:$E$64,1) ) -> 23.666667 | N14: =AVERAGE( _xlfn.RANK.EQ(F14,$F$6:$F$64,0), _xlfn.RANK.EQ(G14,$G$6:$G$64,0), _xlfn.RANK.EQ(J14,$J$6:$J$64,0), _xlfn.RANK.EQ(K14,$K$6:$K$64,0) ) -> 25.75 | O14: =AVERAGE( _xlfn.RANK.EQ(H14,$H$6:$H$64,1), _xlfn.RANK.EQ(I14,$I$6:$I$64,0) ) -> 39 | P14: =_xlfn.RANK.EQ(L14,$L$6:$L$64,0) -> 12 | Q14: =AVERAGE(M14,N14,O14,P14) -> 25.104167 | R14: =IF(Q14<=20,"Excellent",IF(Q14<=25,"Very Good",IF(Q14<=30,"Decent",IF(Q14<=35,"Average","Weak/Avoid")))) -> Decent
A15: ='Raw Data'!B54 -> Power Grid Corporation of India Limited | B15: =COUNTIF($C$69:$L$98,A15) -> 5 | C15: =('Raw Data'!D54+'Raw Data'!E54-'Raw Data'!F54)/'Raw Data'!H54 -> 9.7057577 | D15: ='Raw Data'!C54/'Raw Data'!L54 -> 15.985706 | E15: ='Raw Data'!C54/'Raw Data'!N54 -> 2.4562542 | F15: ='Raw Data'!J54/'Raw Data'!M54 -> 0.19570228 | G15: ='Raw Data'!I54/('Raw Data'!M54+'Raw Data'!E54) -> 0.1188326 | H15: ='Raw Data'!E54/'Raw Data'!M54 -> 1.7982344 | I15: ='Raw Data'!I54/'Raw Data'!Q54 -> -3.2455377 | J15: ='Raw Data'!I54/'Raw Data'!O54 -> 0.55929563 | K15: =IFERROR('Raw Data'!J54/'Raw Data'!O54, "") -> 0.32916802 | L15: ='Raw Data'!R54/'Raw Data'!C54 -> 0.062555884 | M15: =AVERAGE(_xlfn.RANK.EQ(C15,$C$6:$C$64,1), _xlfn.RANK.EQ(D15,$D$6:$D$64,1), _xlfn.RANK.EQ(E15,$E$6:$E$64,1) ) -> 28.666667 | N15: =AVERAGE( _xlfn.RANK.EQ(F15,$F$6:$F$64,0), _xlfn.RANK.EQ(G15,$G$6:$G$64,0), _xlfn.RANK.EQ(J15,$J$6:$J$64,0), _xlfn.RANK.EQ(K15,$K$6:$K$64,0) ) -> 14.75 | O15: =AVERAGE( _xlfn.RANK.EQ(H15,$H$6:$H$64,1), _xlfn.RANK.EQ(I15,$I$6:$I$64,0) ) -> 41.5 | P15: =_xlfn.RANK.EQ(L15,$L$6:$L$64,0) -> 19 | Q15: =AVERAGE(M15,N15,O15,P15) -> 25.979167 | R15: =IF(Q15<=20,"Excellent",IF(Q15<=25,"Very Good",IF(Q15<=30,"Decent",IF(Q15<=35,"Average","Weak/Avoid")))) -> Decent
A16: ='Raw Data'!B57 -> Rudra Gas Enterprise Limited | B16: =COUNTIF($C$69:$L$98,A16) -> 5 | C16: =('Raw Data'!D57+'Raw Data'!E57-'Raw Data'!F57)/'Raw Data'!H57 -> 10.471657 | D16: ='Raw Data'!C57/'Raw Data'!L57 -> 18.287456 | E16: ='Raw Data'!C57/'Raw Data'!N57 -> 2.983093 | F16: ='Raw Data'!J57/'Raw Data'!M57 -> 0.61161086 | G16: ='Raw Data'!I57/('Raw Data'!M57+'Raw Data'!E57) -> 0.3148247 | H16: ='Raw Data'!E57/'Raw Data'!M57 -> 2.6922056 | I16: ='Raw Data'!I57/'Raw Data'!Q57 -> -2.6497038 | J16: ='Raw Data'!I57/'Raw Data'!O57 -> 0.12351956 | K16: =IFERROR('Raw Data'!J57/'Raw Data'!O57, "") -> 0.064991455 | L16: ='Raw Data'!R57/'Raw Data'!C57 -> 0.054682293 | M16: =AVERAGE(_xlfn.RANK.EQ(C16,$C$6:$C$64,1), _xlfn.RANK.EQ(D16,$D$6:$D$64,1), _xlfn.RANK.EQ(E16,$E$6:$E$64,1) ) -> 33.333333 | N16: =AVERAGE( _xlfn.RANK.EQ(F16,$F$6:$F$64,0), _xlfn.RANK.EQ(G16,$G$6:$G$64,0), _xlfn.RANK.EQ(J16,$J$6:$J$64,0), _xlfn.RANK.EQ(K16,$K$6:$K$64,0) ) -> 22 | O16: =AVERAGE( _xlfn.RANK.EQ(H16,$H$6:$H$64,1), _xlfn.RANK.EQ(I16,$I$6:$I$64,0) ) -> 42.5 | P16: =_xlfn.RANK.EQ(L16,$L$6:$L$64,0) -> 22 | Q16: =AVERAGE(M16,N16,O16,P16) -> 29.958333 | R16: =IF(Q16<=20,"Excellent",IF(Q16<=25,"Very Good",IF(Q16<=30,"Decent",IF(Q16<=35,"Average","Weak/Avoid")))) -> Decent
A17: ='Raw Data'!B45 -> Sugs Lloyd Limited | B17: =COUNTIF($C$69:$L$98,A17) -> 7 | C17: =('Raw Data'!D45+'Raw Data'!E45-'Raw Data'!F45)/'Raw Data'!H45 -> 8.5746239 | D17: ='Raw Data'!C45/'Raw Data'!L45 -> 15.441734 | E17: ='Raw Data'!C45/'Raw Data'!N45 -> 2.7615935 | F17: ='Raw Data'!J45/'Raw Data'!M45 -> 0.22074519 | G17: ='Raw Data'!I45/('Raw Data'!M45+'Raw Data'!E45) -> 0.1887728 | H17: ='Raw Data'!E45/'Raw Data'!M45 -> 0.84008365 | I17: ='Raw Data'!I45/'Raw Data'!Q45 -> -590.24996 | J17: ='Raw Data'!I45/'Raw Data'!O45 -> 0.1458978 | K17: =IFERROR('Raw Data'!J45/'Raw Data'!O45, "") -> 0.092717778 | L17: ='Raw Data'!R45/'Raw Data'!C45 -> 0.064759568 | M17: =AVERAGE(_xlfn.RANK.EQ(C17,$C$6:$C$64,1), _xlfn.RANK.EQ(D17,$D$6:$D$64,1), _xlfn.RANK.EQ(E17,$E$6:$E$64,1) ) -> 27.333333 | N17: =AVERAGE( _xlfn.RANK.EQ(F17,$F$6:$F$64,0), _xlfn.RANK.EQ(G17,$G$6:$G$64,0), _xlfn.RANK.EQ(J17,$J$6:$J$64,0), _xlfn.RANK.EQ(K17,$K$6:$K$64,0) ) -> 23.75 | O17: =AVERAGE( _xlfn.RANK.EQ(H17,$H$6:$H$64,1), _xlfn.RANK.EQ(I17,$I$6:$I$64,0) ) -> 48.5 | P17: =_xlfn.RANK.EQ(L17,$L$6:$L$64,0) -> 17 | Q17: =AVERAGE(M17,N17,O17,P17) -> 29.145833 | R17: =IF(Q17<=20,"Excellent",IF(Q17<=25,"Very Good",IF(Q17<=30,"Decent",IF(Q17<=35,"Average","Weak/Avoid")))) -> Decent
A18: ='Raw Data'!B65 -> GAIL (India) Limited | B18: =COUNTIF($C$69:$L$98,A18) -> 6 | C18: =('Raw Data'!D65+'Raw Data'!E65-'Raw Data'!F65)/'Raw Data'!H65 -> 8.5797064 | D18: ='Raw Data'!C65/'Raw Data'!L65 -> 9.1066108 | E18: ='Raw Data'!C65/'Raw Data'!N65 -> 1.2454448 | F18: ='Raw Data'!J65/'Raw Data'!M65 -> 0.17360614 | G18: ='Raw Data'!I65/('Raw Data'!M65+'Raw Data'!E65) -> 0.12040907 | H18: ='Raw Data'!E65/'Raw Data'!M65 -> 0.3221956 | I18: ='Raw Data'!I65/'Raw Data'!Q65 -> -14.054769 | J18: ='Raw Data'!I65/'Raw Data'!O65 -> 0.07489507 | K18: =IFERROR('Raw Data'!J65/'Raw Data'!O65, "") -> 0.081670157 | L18: ='Raw Data'!R65/'Raw Data'!C65 -> 0.10981034 | M18: =AVERAGE(_xlfn.RANK.EQ(C18,$C$6:$C$64,1), _xlfn.RANK.EQ(D18,$D$6:$D$64,1), _xlfn.RANK.EQ(E18,$E$6:$E$64,1) ) -> 17.333333 | N18: =AVERAGE( _xlfn.RANK.EQ(F18,$F$6:$F$64,0), _xlfn.RANK.EQ(G18,$G$6:$G$64,0), _xlfn.RANK.EQ(J18,$J$6:$J$64,0), _xlfn.RANK.EQ(K18,$K$6:$K$64,0) ) -> 31.75 | O18: =AVERAGE( _xlfn.RANK.EQ(H18,$H$6:$H$64,1), _xlfn.RANK.EQ(I18,$I$6:$I$64,0) ) -> 38.5 | P18: =_xlfn.RANK.EQ(L18,$L$6:$L$64,0) -> 7 | Q18: =AVERAGE(M18,N18,O18,P18) -> 23.645833 | R18: =IF(Q18<=20,"Excellent",IF(Q18<=25,"Very Good",IF(Q18<=30,"Decent",IF(Q18<=35,"Average","Weak/Avoid")))) -> Very Good
A19: ='Raw Data'!B28 -> Jaiprakash Power Ventures Limited | B19: =COUNTIF($C$69:$L$98,A19) -> 5 | C19: =('Raw Data'!D28+'Raw Data'!E28-'Raw Data'!F28)/'Raw Data'!H28 -> 8.7317299 | D19: ='Raw Data'!C28/'Raw Data'!L28 -> 21.056783 | E19: ='Raw Data'!C28/'Raw Data'!N28 -> 1.4103026 | F19: ='Raw Data'!J28/'Raw Data'!M28 -> -0.50892103 | G19: ='Raw Data'!I28/('Raw Data'!M28+'Raw Data'!E28) -> 0.53086176 | H19: ='Raw Data'!E28/'Raw Data'!M28 -> -2.5874409 | I19: ='Raw Data'!I28/'Raw Data'!Q28 -> -3.1933308 | J19: ='Raw Data'!I28/'Raw Data'!O28 -> 0.23258957 | K19: =IFERROR('Raw Data'!J28/'Raw Data'!O28, "") -> 0.14046289 | L19: ='Raw Data'!R28/'Raw Data'!C28 -> 0.047490635 | M19: =AVERAGE(_xlfn.RANK.EQ(C19,$C$6:$C$64,1), _xlfn.RANK.EQ(D19,$D$6:$D$64,1), _xlfn.RANK.EQ(E19,$E$6:$E$64,1) ) -> 24.333333 | N19: =AVERAGE( _xlfn.RANK.EQ(F19,$F$6:$F$64,0), _xlfn.RANK.EQ(G19,$G$6:$G$64,0), _xlfn.RANK.EQ(J19,$J$6:$J$64,0), _xlfn.RANK.EQ(K19,$K$6:$K$64,0) ) -> 23.5 | O19: =AVERAGE( _xlfn.RANK.EQ(H19,$H$6:$H$64,1), _xlfn.RANK.EQ(I19,$I$6:$I$64,0) ) -> 18 | P19: =_xlfn.RANK.EQ(L19,$L$6:$L$64,0) -> 24 | Q19: =AVERAGE(M19,N19,O19,P19) -> 22.458333 | R19: =IF(Q19<=20,"Excellent",IF(Q19<=25,"Very Good",IF(Q19<=30,"Decent",IF(Q19<=35,"Average","Weak/Avoid")))) -> Very Good
A20: ='Raw Data'!B59 -> Mahanagar Gas Limited | B20: =COUNTIF($C$69:$L$98,A20) -> 6 | C20: =('Raw Data'!D59+'Raw Data'!E59-'Raw Data'!F59)/'Raw Data'!H59 -> 7.2078981 | D20: ='Raw Data'!C59/'Raw Data'!L59 -> 11.25037 | E20: ='Raw Data'!C59/'Raw Data'!N59 -> 1.7660404 | F20: ='Raw Data'!J59/'Raw Data'!M59 -> 0.15951393 | G20: ='Raw Data'!I59/('Raw Data'!M59+'Raw Data'!E59) -> 0.18592331 | H20: ='Raw Data'!E59/'Raw Data'!M59 -> 0.036109816 | I20: ='Raw Data'!I59/'Raw Data'!Q59 -> -67.209496 | J20: ='Raw Data'!I59/'Raw Data'!O59 -> 0.14814731 | K20: =IFERROR('Raw Data'!J59/'Raw Data'!O59, "") -> 0.12267407 | L20: ='Raw Data'!R59/'Raw Data'!C59 -> 0.088885967 | M20: =AVERAGE(_xlfn.RANK.EQ(C20,$C$6:$C$64,1), _xlfn.RANK.EQ(D20,$D$6:$D$64,1), _xlfn.RANK.EQ(E20,$E$6:$E$64,1) ) -> 20.666667 | N20: =AVERAGE( _xlfn.RANK.EQ(F20,$F$6:$F$64,0), _xlfn.RANK.EQ(G20,$G$6:$G$64,0), _xlfn.RANK.EQ(J20,$J$6:$J$64,0), _xlfn.RANK.EQ(K20,$K$6:$K$64,0) ) -> 24.25 | O20: =AVERAGE( _xlfn.RANK.EQ(H20,$H$6:$H$64,1), _xlfn.RANK.EQ(I20,$I$6:$I$64,0) ) -> 36.5 | P20: =_xlfn.RANK.EQ(L20,$L$6:$L$64,0) -> 10 | Q20: =AVERAGE(M20,N20,O20,P20) -> 22.854167 | R20: =IF(Q20<=20,"Excellent",IF(Q20<=25,"Very Good",IF(Q20<=30,"Decent",IF(Q20<=35,"Average","Weak/Avoid")))) -> Very Good
A21: ='Raw Data'!B33 -> NLC India Limited | B21: =COUNTIF($C$69:$L$98,A21) -> 6 | C21: =('Raw Data'!D33+'Raw Data'!E33-'Raw Data'!F33)/'Raw Data'!H33 -> 11.608896 | D21: ='Raw Data'!C33/'Raw Data'!L33 -> 10.915305 | E21: ='Raw Data'!C33/'Raw Data'!N33 -> 1.7142982 | F21: ='Raw Data'!J33/'Raw Data'!M33 -> 0.17009693 | G21: ='Raw Data'!I33/('Raw Data'!M33+'Raw Data'!E33) -> 0.068871727 | H21: ='Raw Data'!E33/'Raw Data'!M33 -> 1.3341467 | I21: ='Raw Data'!I33/'Raw Data'!Q33 -> -2.5959215 | J21: ='Raw Data'!I33/'Raw Data'!O33 -> 0.17180173 | K21: =IFERROR('Raw Data'!J33/'Raw Data'!O33, "") -> 0.18178368 | L21: ='Raw Data'!R33/'Raw Data'!C33 -> 0.091614479 | M21: =AVERAGE(_xlfn.RANK.EQ(C21,$C$6:$C$64,1), _xlfn.RANK.EQ(D21,$D$6:$D$64,1), _xlfn.RANK.EQ(E21,$E$6:$E$64,1) ) -> 24.666667 | N21: =AVERAGE( _xlfn.RANK.EQ(F21,$F$6:$F$64,0), _xlfn.RANK.EQ(G21,$G$6:$G$64,0), _xlfn.RANK.EQ(J21,$J$6:$J$64,0), _xlfn.RANK.EQ(K21,$K$6:$K$64,0) ) -> 25.25 | O21: =AVERAGE( _xlfn.RANK.EQ(H21,$H$6:$H$64,1), _xlfn.RANK.EQ(I21,$I$6:$I$64,0) ) -> 36 | P21: =_xlfn.RANK.EQ(L21,$L$6:$L$64,0) -> 9 | Q21: =AVERAGE(M21,N21,O21,P21) -> 23.729167 | R21: =IF(Q21<=20,"Excellent",IF(Q21<=25,"Very Good",IF(Q21<=30,"Decent",IF(Q21<=35,"Average","Weak/Avoid")))) -> Very Good
A22: ='Raw Data'!B24 -> Pace Digitek Limited | B22: =COUNTIF($C$69:$L$98,A22) -> 7 | C22: =('Raw Data'!D24+'Raw Data'!E24-'Raw Data'!F24)/'Raw Data'!H24 -> 11.405448 | D22: ='Raw Data'!C24/'Raw Data'!L24 -> 14.341665 | E22: ='Raw Data'!C24/'Raw Data'!N24 -> 2.7339329 | F22: ='Raw Data'!J24/'Raw Data'!M24 -> 0.30279491 | G22: ='Raw Data'!I24/('Raw Data'!M24+'Raw Data'!E24) -> 0.38550875 | H22: ='Raw Data'!E24/'Raw Data'!M24 -> 0.18594467 | I22: ='Raw Data'!I24/'Raw Data'!Q24 -> -11.412597 | J22: ='Raw Data'!I24/'Raw Data'!O24 -> 0.17243435 | K22: =IFERROR('Raw Data'!J24/'Raw Data'!O24, "") -> 0.11420199 | L22: ='Raw Data'!R24/'Raw Data'!C24 -> 0.069726913 | M22: =AVERAGE(_xlfn.RANK.EQ(C22,$C$6:$C$64,1), _xlfn.RANK.EQ(D22,$D$6:$D$64,1), _xlfn.RANK.EQ(E22,$E$6:$E$64,1) ) -> 29.333333 | N22: =AVERAGE( _xlfn.RANK.EQ(F22,$F$6:$F$64,0), _xlfn.RANK.EQ(G22,$G$6:$G$64,0), _xlfn.RANK.EQ(J22,$J$6:$J$64,0), _xlfn.RANK.EQ(K22,$K$6:$K$64,0) ) -> 19 | O22: =AVERAGE( _xlfn.RANK.EQ(H22,$H$6:$H$64,1), _xlfn.RANK.EQ(I22,$I$6:$I$64,0) ) -> 35.5 | P22: =_xlfn.RANK.EQ(L22,$L$6:$L$64,0) -> 13 | Q22: =AVERAGE(M22,N22,O22,P22) -> 24.208333 | R22: =IF(Q22<=20,"Excellent",IF(Q22<=25,"Very Good",IF(Q22<=30,"Decent",IF(Q22<=35,"Average","Weak/Avoid")))) -> Very Good
A23: ='Raw Data'!B63 -> Petronet LNG Limited | B23: =COUNTIF($C$69:$L$98,A23) -> 5 | C23: =('Raw Data'!D63+'Raw Data'!E63-'Raw Data'!F63)/'Raw Data'!H63 -> 7.8157436 | D23: ='Raw Data'!C63/'Raw Data'!L63 -> 10.455675 | E23: ='Raw Data'!C63/'Raw Data'!N63 -> 1.9499402 | F23: ='Raw Data'!J63/'Raw Data'!M63 -> 0.2011327 | G23: ='Raw Data'!I63/('Raw Data'!M63+'Raw Data'!E63) -> 0.20392187 | H23: ='Raw Data'!E63/'Raw Data'!M63 -> 0.14405827 | I23: ='Raw Data'!I63/'Raw Data'!Q63 -> -17.025419 | J23: ='Raw Data'!I63/'Raw Data'!O63 -> 0.087007925 | K23: =IFERROR('Raw Data'!J63/'Raw Data'!O63, "") -> 0.07501179 | L23: ='Raw Data'!R63/'Raw Data'!C63 -> 0.095641843 | M23: =AVERAGE(_xlfn.RANK.EQ(C23,$C$6:$C$64,1), _xlfn.RANK.EQ(D23,$D$6:$D$64,1), _xlfn.RANK.EQ(E23,$E$6:$E$64,1) ) -> 22 | N23: =AVERAGE( _xlfn.RANK.EQ(F23,$F$6:$F$64,0), _xlfn.RANK.EQ(G23,$G$6:$G$64,0), _xlfn.RANK.EQ(J23,$J$6:$J$64,0), _xlfn.RANK.EQ(K23,$K$6:$K$64,0) ) -> 26.5 | O23: =AVERAGE( _xlfn.RANK.EQ(H23,$H$6:$H$64,1), _xlfn.RANK.EQ(I23,$I$6:$I$64,0) ) -> 36.5 | P23: =_xlfn.RANK.EQ(L23,$L$6:$L$64,0) -> 8 | Q23: =AVERAGE(M23,N23,O23,P23) -> 23.25 | R23: =IF(Q23<=20,"Excellent",IF(Q23<=25,"Very Good",IF(Q23<=30,"Decent",IF(Q23<=35,"Average","Weak/Avoid")))) -> Very Good
A24: ='Raw Data'!B64 -> Adani Total Gas Limited | B24: =COUNTIF($C$69:$L$98,A24) -> 5 | C24: =('Raw Data'!D64+'Raw Data'!E64-'Raw Data'!F64)/'Raw Data'!H64 -> 56.463022 | D24: ='Raw Data'!C64/'Raw Data'!L64 -> 95.170686 | E24: ='Raw Data'!C64/'Raw Data'!N64 -> 14.630762 | F24: ='Raw Data'!J64/'Raw Data'!M64 -> 0.16366048 | G24: ='Raw Data'!I64/('Raw Data'!M64+'Raw Data'!E64) -> 0.15903375 | H24: ='Raw Data'!E64/'Raw Data'!M64 -> 0.46336068 | I24: ='Raw Data'!I64/'Raw Data'!Q64 -> -10.369143 | J24: ='Raw Data'!I64/'Raw Data'!O64 -> 0.17603455 | K24: =IFERROR('Raw Data'!J64/'Raw Data'!O64, "") -> 0.12379442 | L24: ='Raw Data'!R64/'Raw Data'!C64 -> 0.010507437 | M24: =AVERAGE(_xlfn.RANK.EQ(C24,$C$6:$C$64,1), _xlfn.RANK.EQ(D24,$D$6:$D$64,1), _xlfn.RANK.EQ(E24,$E$6:$E$64,1) ) -> 54 | N24: =AVERAGE( _xlfn.RANK.EQ(F24,$F$6:$F$64,0), _xlfn.RANK.EQ(G24,$G$6:$G$64,0), _xlfn.RANK.EQ(J24,$J$6:$J$64,0), _xlfn.RANK.EQ(K24,$K$6:$K$64,0) ) -> 23 | O24: =AVERAGE( _xlfn.RANK.EQ(H24,$H$6:$H$64,1), _xlfn.RANK.EQ(I24,$I$6:$I$64,0) ) -> 37 | P24: =_xlfn.RANK.EQ(L24,$L$6:$L$64,0) -> 43 | Q24: =AVERAGE(M24,N24,O24,P24) -> 39.25 | R24: =IF(Q24<=20,"Excellent",IF(Q24<=25,"Very Good",IF(Q24<=30,"Decent",IF(Q24<=35,"Average","Weak/Avoid")))) -> Weak/Avoid
A25: ='Raw Data'!B37 -> Siemens Energy India Limited | B25: =COUNTIF($C$69:$L$98,A25) -> 5 | C25: =('Raw Data'!D37+'Raw Data'!E37-'Raw Data'!F37)/'Raw Data'!H37 -> 56.254216 | D25: ='Raw Data'!C37/'Raw Data'!L37 -> 77.451448 | E25: ='Raw Data'!C37/'Raw Data'!N37 -> 26.386016 | F25: ='Raw Data'!J37/'Raw Data'!M37 -> 0.39635843 | G25: ='Raw Data'!I37/('Raw Data'!M37+'Raw Data'!E37) -> 0.50598916 | H25: ='Raw Data'!E37/'Raw Data'!M37 -> 0.040233005 | I25: ='Raw Data'!I37/'Raw Data'!Q37 -> -52.566263 | J25: ='Raw Data'!I37/'Raw Data'!O37 -> 0.18104486 | K25: =IFERROR('Raw Data'!J37/'Raw Data'!O37, "") -> 0.13633346 | L25: ='Raw Data'!R37/'Raw Data'!C37 -> 0.012911314 | M25: =AVERAGE(_xlfn.RANK.EQ(C25,$C$6:$C$64,1), _xlfn.RANK.EQ(D25,$D$6:$D$64,1), _xlfn.RANK.EQ(E25,$E$6:$E$64,1) ) -> 53.666667 | N25: =AVERAGE( _xlfn.RANK.EQ(F25,$F$6:$F$64,0), _xlfn.RANK.EQ(G25,$G$6:$G$64,0), _xlfn.RANK.EQ(J25,$J$6:$J$64,0), _xlfn.RANK.EQ(K25,$K$6:$K$64,0) ) -> 15.25 | O25: =AVERAGE( _xlfn.RANK.EQ(H25,$H$6:$H$64,1), _xlfn.RANK.EQ(I25,$I$6:$I$64,0) ) -> 36.5 | P25: =_xlfn.RANK.EQ(L25,$L$6:$L$64,0) -> 40 | Q25: =AVERAGE(M25,N25,O25,P25) -> 36.354167 | R25: =IF(Q25<=20,"Excellent",IF(Q25<=25,"Very Good",IF(Q25<=30,"Decent",IF(Q25<=35,"Average","Weak/Avoid")))) -> Weak/Avoid
A26: ='Raw Data'!B62 -> Gujarat Gas Limited | B26: =COUNTIF($C$69:$L$98,A26) -> 4 | C26: =('Raw Data'!D62+'Raw Data'!E62-'Raw Data'!F62)/'Raw Data'!H62 -> 14.050529 | D26: ='Raw Data'!C62/'Raw Data'!L62 -> 23.893367 | E26: ='Raw Data'!C62/'Raw Data'!N62 -> 3.0663779 | F26: ='Raw Data'!J62/'Raw Data'!M62 -> 0.14141878 | G26: ='Raw Data'!I62/('Raw Data'!M62+'Raw Data'!E62) -> 0.17148234 | H26: ='Raw Data'!E62/'Raw Data'!M62 -> 0.019160805 | I26: ='Raw Data'!I62/'Raw Data'!Q62 -> -41.655638 | J26: ='Raw Data'!I62/'Raw Data'!O62 -> 0.086396999 | K26: =IFERROR('Raw Data'!J62/'Raw Data'!O62, "") -> 0.069910695 | L26: ='Raw Data'!R62/'Raw Data'!C62 -> 0.04185262 | M26: =AVERAGE(_xlfn.RANK.EQ(C26,$C$6:$C$64,1), _xlfn.RANK.EQ(D26,$D$6:$D$64,1), _xlfn.RANK.EQ(E26,$E$6:$E$64,1) ) -> 40 | N26: =AVERAGE( _xlfn.RANK.EQ(F26,$F$6:$F$64,0), _xlfn.RANK.EQ(G26,$G$6:$G$64,0), _xlfn.RANK.EQ(J26,$J$6:$J$64,0), _xlfn.RANK.EQ(K26,$K$6:$K$64,0) ) -> 31.5 | O26: =AVERAGE( _xlfn.RANK.EQ(H26,$H$6:$H$64,1), _xlfn.RANK.EQ(I26,$I$6:$I$64,0) ) -> 34 | P26: =_xlfn.RANK.EQ(L26,$L$6:$L$64,0) -> 29 | Q26: =AVERAGE(M26,N26,O26,P26) -> 33.625 | R26: =IF(Q26<=20,"Excellent",IF(Q26<=25,"Very Good",IF(Q26<=30,"Decent",IF(Q26<=35,"Average","Weak/Avoid")))) -> Average
A27: ='Raw Data'!B36 -> JSW Energy Limited | B27: =COUNTIF($C$69:$L$98,A27) -> 4 | C27: =('Raw Data'!D36+'Raw Data'!E36-'Raw Data'!F36)/'Raw Data'!H36 -> 19.747703 | D27: ='Raw Data'!C36/'Raw Data'!L36 -> 35.057274 | E27: ='Raw Data'!C36/'Raw Data'!N36 -> 2.784564 | F27: ='Raw Data'!J36/'Raw Data'!M36 -> 0.1889974 | G27: ='Raw Data'!I36/('Raw Data'!M36+'Raw Data'!E36) -> 0.07478608 | H27: ='Raw Data'!E36/'Raw Data'!M36 -> 4.3663798 | I27: ='Raw Data'!I36/'Raw Data'!Q36 -> -1.5398284 | J27: ='Raw Data'!I36/'Raw Data'!O36 -> 0.32926056 | K27: =IFERROR('Raw Data'!J36/'Raw Data'!O36, "") -> 0.15505771 | L27: ='Raw Data'!R36/'Raw Data'!C36 -> 0.028524751 | M27: =AVERAGE(_xlfn.RANK.EQ(C27,$C$6:$C$64,1), _xlfn.RANK.EQ(D27,$D$6:$D$64,1), _xlfn.RANK.EQ(E27,$E$6:$E$64,1) ) -> 42.666667 | N27: =AVERAGE( _xlfn.RANK.EQ(F27,$F$6:$F$64,0), _xlfn.RANK.EQ(G27,$G$6:$G$64,0), _xlfn.RANK.EQ(J27,$J$6:$J$64,0), _xlfn.RANK.EQ(K27,$K$6:$K$64,0) ) -> 21 | O27: =AVERAGE( _xlfn.RANK.EQ(H27,$H$6:$H$64,1), _xlfn.RANK.EQ(I27,$I$6:$I$64,0) ) -> 38.5 | P27: =_xlfn.RANK.EQ(L27,$L$6:$L$64,0) -> 36 | Q27: =AVERAGE(M27,N27,O27,P27) -> 34.541667 | R27: =IF(Q27<=20,"Excellent",IF(Q27<=25,"Very Good",IF(Q27<=30,"Decent",IF(Q27<=35,"Average","Weak/Avoid")))) -> Average
A28: ='Raw Data'!B35 -> NHPC Limited | B28: =COUNTIF($C$69:$L$98,A28) -> 3 | C28: =('Raw Data'!D35+'Raw Data'!E35-'Raw Data'!F35)/'Raw Data'!H35 -> 20.186682 | D28: ='Raw Data'!C35/'Raw Data'!L35 -> 24.091564 | E28: ='Raw Data'!C35/'Raw Data'!N35 -> 1.8518719 | F28: ='Raw Data'!J35/'Raw Data'!M35 -> 0.11540999 | G28: ='Raw Data'!I35/('Raw Data'!M35+'Raw Data'!E35) -> 0.066596119 | H28: ='Raw Data'!E35/'Raw Data'!M35 -> 1.5731732 | I28: ='Raw Data'!I35/'Raw Data'!Q35 -> -12.171993 | J28: ='Raw Data'!I35/'Raw Data'!O35 -> 0.4154887 | K28: =IFERROR('Raw Data'!J35/'Raw Data'!O35, "") -> 0.27982381 | L28: ='Raw Data'!R35/'Raw Data'!C35 -> 0.041508305 | M28: =AVERAGE(_xlfn.RANK.EQ(C28,$C$6:$C$64,1), _xlfn.RANK.EQ(D28,$D$6:$D$64,1), _xlfn.RANK.EQ(E28,$E$6:$E$64,1) ) -> 37.666667 | N28: =AVERAGE( _xlfn.RANK.EQ(F28,$F$6:$F$64,0), _xlfn.RANK.EQ(G28,$G$6:$G$64,0), _xlfn.RANK.EQ(J28,$J$6:$J$64,0), _xlfn.RANK.EQ(K28,$K$6:$K$64,0) ) -> 20.75 | O28: =AVERAGE( _xlfn.RANK.EQ(H28,$H$6:$H$64,1), _xlfn.RANK.EQ(I28,$I$6:$I$64,0) ) -> 45.5 | P28: =_xlfn.RANK.EQ(L28,$L$6:$L$64,0) -> 30 | Q28: =AVERAGE(M28,N28,O28,P28) -> 33.479167 | R28: =IF(Q28<=20,"Excellent",IF(Q28<=25,"Very Good",IF(Q28<=30,"Decent",IF(Q28<=35,"Average","Weak/Avoid")))) -> Average
A29: ='Raw Data'!B12 -> Waa Solar Limited | B29: =COUNTIF($C$69:$L$98,A29) -> 3 | C29: =('Raw Data'!D12+'Raw Data'!E12-'Raw Data'!F12)/'Raw Data'!H12 -> 16.115717 | D29: ='Raw Data'!C12/'Raw Data'!L12 -> 33.850152 | E29: ='Raw Data'!C12/'Raw Data'!N12 -> 0.31066989 | F29: ='Raw Data'!J12/'Raw Data'!M12 -> 0.020817616 | G29: ='Raw Data'!I12/('Raw Data'!M12+'Raw Data'!E12) -> 0.0033715969 | H29: ='Raw Data'!E12/'Raw Data'!M12 -> 0.78235414 | I29: ='Raw Data'!I12/'Raw Data'!Q12 -> -0.25079054 | J29: ='Raw Data'!I12/'Raw Data'!O12 -> 0.027328878 | K29: =IFERROR('Raw Data'!J12/'Raw Data'!O12, "") -> 0.094672347 | L29: ='Raw Data'!R12/'Raw Data'!C12 -> 0.029541965 | M29: =AVERAGE(_xlfn.RANK.EQ(C29,$C$6:$C$64,1), _xlfn.RANK.EQ(D29,$D$6:$D$64,1), _xlfn.RANK.EQ(E29,$E$6:$E$64,1) ) -> 29.333333 | N29: =AVERAGE( _xlfn.RANK.EQ(F29,$F$6:$F$64,0), _xlfn.RANK.EQ(G29,$G$6:$G$64,0), _xlfn.RANK.EQ(J29,$J$6:$J$64,0), _xlfn.RANK.EQ(K29,$K$6:$K$64,0) ) -> 41 | O29: =AVERAGE( _xlfn.RANK.EQ(H29,$H$6:$H$64,1), _xlfn.RANK.EQ(I29,$I$6:$I$64,0) ) -> 25.5 | P29: =_xlfn.RANK.EQ(L29,$L$6:$L$64,0) -> 34 | Q29: =AVERAGE(M29,N29,O29,P29) -> 32.458333 | R29: =IF(Q29<=20,"Excellent",IF(Q29<=25,"Very Good",IF(Q29<=30,"Decent",IF(Q29<=35,"Average","Weak/Avoid")))) -> Average
A30: ='Raw Data'!B31 -> CESC Limited | B30: =COUNTIF($C$69:$L$98,A30) -> 4 | C30: =('Raw Data'!D31+'Raw Data'!E31-'Raw Data'!F31)/'Raw Data'!H31 -> 11.094946 | D30: ='Raw Data'!C31/'Raw Data'!L31 -> 15.531983 | E30: ='Raw Data'!C31/'Raw Data'!N31 -> 1.7850224 | F30: ='Raw Data'!J31/'Raw Data'!M31 -> 0.10828869 | G30: ='Raw Data'!I31/('Raw Data'!M31+'Raw Data'!E31) -> 0.069504056 | H30: ='Raw Data'!E31/'Raw Data'!M31 -> 1.4127823 | I30: ='Raw Data'!I31/'Raw Data'!Q31 -> -1.3993443 | J30: ='Raw Data'!I31/'Raw Data'!O31 -> 0.12306805 | K30: =IFERROR('Raw Data'!J31/'Raw Data'!O31, "") -> 0.079469435 | L30: ='Raw Data'!R31/'Raw Data'!C31 -> 0.064383279 | M30: =AVERAGE(_xlfn.RANK.EQ(C30,$C$6:$C$64,1), _xlfn.RANK.EQ(D30,$D$6:$D$64,1), _xlfn.RANK.EQ(E30,$E$6:$E$64,1) ) -> 27.333333 | N30: =AVERAGE( _xlfn.RANK.EQ(F30,$F$6:$F$64,0), _xlfn.RANK.EQ(G30,$G$6:$G$64,0), _xlfn.RANK.EQ(J30,$J$6:$J$64,0), _xlfn.RANK.EQ(K30,$K$6:$K$64,0) ) -> 34.5 | O30: =AVERAGE( _xlfn.RANK.EQ(H30,$H$6:$H$64,1), _xlfn.RANK.EQ(I30,$I$6:$I$64,0) ) -> 32 | P30: =_xlfn.RANK.EQ(L30,$L$6:$L$64,0) -> 18 | Q30: =AVERAGE(M30,N30,O30,P30) -> 27.958333 | R30: =IF(Q30<=20,"Excellent",IF(Q30<=25,"Very Good",IF(Q30<=30,"Decent",IF(Q30<=35,"Average","Weak/Avoid")))) -> Decent
A31: ='Raw Data'!B14 -> Energy Development Company Limited | B31: =COUNTIF($C$69:$L$98,A31) -> 3 | C31: =('Raw Data'!D14+'Raw Data'!E14-'Raw Data'!F14)/'Raw Data'!H14 -> 9.562673 | D31: ='Raw Data'!C14/'Raw Data'!L14 -> -1.0383327 | E31: ='Raw Data'!C14/'Raw Data'!N14 -> 5.8571448 | F31: ='Raw Data'!J14/'Raw Data'!M14 -> 0.73194078 | G31: ='Raw Data'!I14/('Raw Data'!M14+'Raw Data'!E14) -> 0.68159653 | H31: ='Raw Data'!E14/'Raw Data'!M14 -> -1.1504969 | I31: ='Raw Data'!I14/'Raw Data'!Q14 -> -1.3605597 | J31: ='Raw Data'!I14/'Raw Data'!O14 -> 0.30526867 | K31: =IFERROR('Raw Data'!J14/'Raw Data'!O14, "") -> -2.1782279 | L31: ='Raw Data'!R14/'Raw Data'!C14 -> -0.96308248 | M31: =AVERAGE(_xlfn.RANK.EQ(C31,$C$6:$C$64,1), _xlfn.RANK.EQ(D31,$D$6:$D$64,1), _xlfn.RANK.EQ(E31,$E$6:$E$64,1) ) -> 28.333333 | N31: =AVERAGE( _xlfn.RANK.EQ(F31,$F$6:$F$64,0), _xlfn.RANK.EQ(G31,$G$6:$G$64,0), _xlfn.RANK.EQ(J31,$J$6:$J$64,0), _xlfn.RANK.EQ(K31,$K$6:$K$64,0) ) -> 18.5 | O31: =AVERAGE( _xlfn.RANK.EQ(H31,$H$6:$H$64,1), _xlfn.RANK.EQ(I31,$I$6:$I$64,0) ) -> 12.5 | P31: =_xlfn.RANK.EQ(L31,$L$6:$L$64,0) -> 59 | Q31: =AVERAGE(M31,N31,O31,P31) -> 29.583333 | R31: =IF(Q31<=20,"Excellent",IF(Q31<=25,"Very Good",IF(Q31<=30,"Decent",IF(Q31<=35,"Average","Weak/Avoid")))) -> Decent
A32: ='Raw Data'!B60 -> Gujarat State Petronet Limited | B32: =COUNTIF($C$69:$L$98,A32) -> 4 | C32: =('Raw Data'!D60+'Raw Data'!E60-'Raw Data'!F60)/'Raw Data'!H60 -> 5.4409235 | D32: ='Raw Data'!C60/'Raw Data'!L60 -> 15.288421 | E32: ='Raw Data'!C60/'Raw Data'!N60 -> 1.3186268 | F32: ='Raw Data'!J60/'Raw Data'!M60 -> 0.071624322 | G32: ='Raw Data'!I60/('Raw Data'!M60+'Raw Data'!E60) -> 0.1218519 | H32: ='Raw Data'!E60/'Raw Data'!M60 -> 0.009716264 | I32: ='Raw Data'!I60/'Raw Data'!Q60 -> -47.42943 | J32: ='Raw Data'!I60/'Raw Data'!O60 -> 0.10552066 | K32: =IFERROR('Raw Data'!J60/'Raw Data'!O60, "") -> 0.061428001 | L32: ='Raw Data'!R60/'Raw Data'!C60 -> 0.065408978 | M32: =AVERAGE(_xlfn.RANK.EQ(C32,$C$6:$C$64,1), _xlfn.RANK.EQ(D32,$D$6:$D$64,1), _xlfn.RANK.EQ(E32,$E$6:$E$64,1) ) -> 18.333333 | N32: =AVERAGE( _xlfn.RANK.EQ(F32,$F$6:$F$64,0), _xlfn.RANK.EQ(G32,$G$6:$G$64,0), _xlfn.RANK.EQ(J32,$J$6:$J$64,0), _xlfn.RANK.EQ(K32,$K$6:$K$64,0) ) -> 34.75 | O32: =AVERAGE( _xlfn.RANK.EQ(H32,$H$6:$H$64,1), _xlfn.RANK.EQ(I32,$I$6:$I$64,0) ) -> 34 | P32: =_xlfn.RANK.EQ(L32,$L$6:$L$64,0) -> 15 | Q32: =AVERAGE(M32,N32,O32,P32) -> 25.520833 | R32: =IF(Q32<=20,"Excellent",IF(Q32<=25,"Very Good",IF(Q32<=30,"Decent",IF(Q32<=35,"Average","Weak/Avoid")))) -> Decent
A33: ='Raw Data'!B15 -> Indowind Energy Limited | B33: =COUNTIF($C$69:$L$98,A33) -> 3 | C33: =('Raw Data'!D15+'Raw Data'!E15-'Raw Data'!F15)/'Raw Data'!H15 -> 12.950761 | D33: ='Raw Data'!C15/'Raw Data'!L15 -> 93.191706 | E33: ='Raw Data'!C15/'Raw Data'!N15 -> 0.64552903 | F33: ='Raw Data'!J15/'Raw Data'!M15 -> -0.19500819 | G33: ='Raw Data'!I15/('Raw Data'!M15+'Raw Data'!E15) -> 1.0068013 | H33: ='Raw Data'!E15/'Raw Data'!M15 -> -1.7747911 | I33: ='Raw Data'!I15/'Raw Data'!Q15 -> -2.2453941 | J33: ='Raw Data'!I15/'Raw Data'!O15 -> 0.20083741 | K33: =IFERROR('Raw Data'!J15/'Raw Data'!O15, "") -> 0.050207551 | L33: ='Raw Data'!R15/'Raw Data'!C15 -> 0.010730569 | M33: =AVERAGE(_xlfn.RANK.EQ(C33,$C$6:$C$64,1), _xlfn.RANK.EQ(D33,$D$6:$D$64,1), _xlfn.RANK.EQ(E33,$E$6:$E$64,1) ) -> 31.666667 | N33: =AVERAGE( _xlfn.RANK.EQ(F33,$F$6:$F$64,0), _xlfn.RANK.EQ(G33,$G$6:$G$64,0), _xlfn.RANK.EQ(J33,$J$6:$J$64,0), _xlfn.RANK.EQ(K33,$K$6:$K$64,0) ) -> 29 | O33: =AVERAGE( _xlfn.RANK.EQ(H33,$H$6:$H$64,1), _xlfn.RANK.EQ(I33,$I$6:$I$64,0) ) -> 16 | P33: =_xlfn.RANK.EQ(L33,$L$6:$L$64,0) -> 42 | Q33: =AVERAGE(M33,N33,O33,P33) -> 29.666667 | R33: =IF(Q33<=20,"Excellent",IF(Q33<=25,"Very Good",IF(Q33<=30,"Decent",IF(Q33<=35,"Average","Weak/Avoid")))) -> Decent
A34: ='Raw Data'!B21 -> Orient Green Power Company Limited | B34: =COUNTIF($C$69:$L$98,A34) -> 4 | C34: =('Raw Data'!D21+'Raw Data'!E21-'Raw Data'!F21)/'Raw Data'!H21 -> 9.9137992 | D34: ='Raw Data'!C21/'Raw Data'!L21 -> 23.219944 | E34: ='Raw Data'!C21/'Raw Data'!N21 -> 1.2189949 | F34: ='Raw Data'!J21/'Raw Data'!M21 -> -0.051012894 | G34: ='Raw Data'!I21/('Raw Data'!M21+'Raw Data'!E21) -> -0.19430763 | H34: ='Raw Data'!E21/'Raw Data'!M21 -> -0.5063516 | I34: ='Raw Data'!I21/'Raw Data'!Q21 -> -1.5353684 | J34: ='Raw Data'!I21/'Raw Data'!O21 -> 0.36293624 | K34: =IFERROR('Raw Data'!J21/'Raw Data'!O21, "") -> 0.19302018 | L34: ='Raw Data'!R21/'Raw Data'!C21 -> 0.043066426 | M34: =AVERAGE(_xlfn.RANK.EQ(C34,$C$6:$C$64,1), _xlfn.RANK.EQ(D34,$D$6:$D$64,1), _xlfn.RANK.EQ(E34,$E$6:$E$64,1) ) -> 25.333333 | N34: =AVERAGE( _xlfn.RANK.EQ(F34,$F$6:$F$64,0), _xlfn.RANK.EQ(G34,$G$6:$G$64,0), _xlfn.RANK.EQ(J34,$J$6:$J$64,0), _xlfn.RANK.EQ(K34,$K$6:$K$64,0) ) -> 31.5 | O34: =AVERAGE( _xlfn.RANK.EQ(H34,$H$6:$H$64,1), _xlfn.RANK.EQ(I34,$I$6:$I$64,0) ) -> 15.5 | P34: =_xlfn.RANK.EQ(L34,$L$6:$L$64,0) -> 28 | Q34: =AVERAGE(M34,N34,O34,P34) -> 25.083333 | R34: =IF(Q34<=20,"Excellent",IF(Q34<=25,"Very Good",IF(Q34<=30,"Decent",IF(Q34<=35,"Average","Weak/Avoid")))) -> Decent
A35: ='Raw Data'!B25 -> PTC India Limited | B35: =COUNTIF($C$69:$L$98,A35) -> 3 | C35: =('Raw Data'!D25+'Raw Data'!E25-'Raw Data'!F25)/'Raw Data'!H25 -> 4.6146281 | D35: ='Raw Data'!C25/'Raw Data'!L25 -> 4.7479577 | E35: ='Raw Data'!C25/'Raw Data'!N25 -> 0.75368171 | F35: ='Raw Data'!J25/'Raw Data'!M25 -> 0.22544771 | G35: ='Raw Data'!I25/('Raw Data'!M25+'Raw Data'!E25) -> 0.17233502 | H35: ='Raw Data'!E25/'Raw Data'!M25 -> 0.72484596 | I35: ='Raw Data'!I25/'Raw Data'!Q25 -> -4.539157 | J35: ='Raw Data'!I25/'Raw Data'!O25 -> 0.077378435 | K35: =IFERROR('Raw Data'!J25/'Raw Data'!O25, "") -> 0.058687001 | L35: ='Raw Data'!R25/'Raw Data'!C25 -> 0.21061687 | M35: =AVERAGE(_xlfn.RANK.EQ(C35,$C$6:$C$64,1), _xlfn.RANK.EQ(D35,$D$6:$D$64,1), _xlfn.RANK.EQ(E35,$E$6:$E$64,1) ) -> 11 | N35: =AVERAGE( _xlfn.RANK.EQ(F35,$F$6:$F$64,0), _xlfn.RANK.EQ(G35,$G$6:$G$64,0), _xlfn.RANK.EQ(J35,$J$6:$J$64,0), _xlfn.RANK.EQ(K35,$K$6:$K$64,0) ) -> 29.25 | O35: =AVERAGE( _xlfn.RANK.EQ(H35,$H$6:$H$64,1), _xlfn.RANK.EQ(I35,$I$6:$I$64,0) ) -> 36.5 | P35: =_xlfn.RANK.EQ(L35,$L$6:$L$64,0) -> 3 | Q35: =AVERAGE(M35,N35,O35,P35) -> 19.9375 | R35: =IF(Q35<=20,"Excellent",IF(Q35<=25,"Very Good",IF(Q35<=30,"Decent",IF(Q35<=35,"Average","Weak/Avoid")))) -> Excellent
A36: ='Raw Data'!B26 -> RattanIndia Power Limited | B36: =COUNTIF($C$69:$L$98,A36) -> 4 | C36: =('Raw Data'!D26+'Raw Data'!E26-'Raw Data'!F26)/'Raw Data'!H26 -> 11.693339 | D36: ='Raw Data'!C26/'Raw Data'!L26 -> 0.45132434 | E36: ='Raw Data'!C26/'Raw Data'!N26 -> 1.1024099 | F36: ='Raw Data'!J26/'Raw Data'!M26 -> -3.3596548 | G36: ='Raw Data'!I26/('Raw Data'!M26+'Raw Data'!E26) -> 1.3361084 | H36: ='Raw Data'!E26/'Raw Data'!M26 -> -1.0811234 | I36: ='Raw Data'!I26/'Raw Data'!Q26 -> -0.63777301 | J36: ='Raw Data'!I26/'Raw Data'!O26 -> 0.10645182 | K36: =IFERROR('Raw Data'!J26/'Raw Data'!O26, "") -> 3.2995885 | L36: ='Raw Data'!R26/'Raw Data'!C26 -> 2.2157014 | M36: =AVERAGE(_xlfn.RANK.EQ(C36,$C$6:$C$64,1), _xlfn.RANK.EQ(D36,$D$6:$D$64,1), _xlfn.RANK.EQ(E36,$E$6:$E$64,1) ) -> 18.333333 | N36: =AVERAGE( _xlfn.RANK.EQ(F36,$F$6:$F$64,0), _xlfn.RANK.EQ(G36,$G$6:$G$64,0), _xlfn.RANK.EQ(J36,$J$6:$J$64,0), _xlfn.RANK.EQ(K36,$K$6:$K$64,0) ) -> 23 | O36: =AVERAGE( _xlfn.RANK.EQ(H36,$H$6:$H$64,1), _xlfn.RANK.EQ(I36,$I$6:$I$64,0) ) -> 11.5 | P36: =_xlfn.RANK.EQ(L36,$L$6:$L$64,0) -> 1 | Q36: =AVERAGE(M36,N36,O36,P36) -> 13.458333 | R36: =IF(Q36<=20,"Excellent",IF(Q36<=25,"Very Good",IF(Q36<=30,"Decent",IF(Q36<=35,"Average","Weak/Avoid")))) -> Excellent
A37: ='Raw Data'!B22 -> Gujarat Industries Power Company Limited | B37: =COUNTIF($C$69:$L$98,A37) -> 4 | C37: =('Raw Data'!D22+'Raw Data'!E22-'Raw Data'!F22)/'Raw Data'!H22 -> 11.302585 | D37: ='Raw Data'!C22/'Raw Data'!L22 -> 11.935321 | E37: ='Raw Data'!C22/'Raw Data'!N22 -> 0.63352477 | F37: ='Raw Data'!J22/'Raw Data'!M22 -> 0.063547997 | G37: ='Raw Data'!I22/('Raw Data'!M22+'Raw Data'!E22) -> 0.040667921 | H37: ='Raw Data'!E22/'Raw Data'!M22 -> 0.94897524 | I37: ='Raw Data'!I22/'Raw Data'!Q22 -> -5.8850241 | J37: ='Raw Data'!I22/'Raw Data'!O22 -> 0.17300322 | K37: =IFERROR('Raw Data'!J22/'Raw Data'!O22, "") -> 0.13870681 | L37: ='Raw Data'!R22/'Raw Data'!C22 -> 0.083784924 | M37: =AVERAGE(_xlfn.RANK.EQ(C37,$C$6:$C$64,1), _xlfn.RANK.EQ(D37,$D$6:$D$64,1), _xlfn.RANK.EQ(E37,$E$6:$E$64,1) ) -> 18.333333 | N37: =AVERAGE( _xlfn.RANK.EQ(F37,$F$6:$F$64,0), _xlfn.RANK.EQ(G37,$G$6:$G$64,0), _xlfn.RANK.EQ(J37,$J$6:$J$64,0), _xlfn.RANK.EQ(K37,$K$6:$K$64,0) ) -> 30.5 | O37: =AVERAGE( _xlfn.RANK.EQ(H37,$H$6:$H$64,1), _xlfn.RANK.EQ(I37,$I$6:$I$64,0) ) -> 39.5 | P37: =_xlfn.RANK.EQ(L37,$L$6:$L$64,0) -> 11 | Q37: =AVERAGE(M37,N37,O37,P37) -> 24.833333 | R37: =IF(Q37<=20,"Excellent",IF(Q37<=25,"Very Good",IF(Q37<=30,"Decent",IF(Q37<=35,"Average","Weak/Avoid")))) -> Very Good
A38: ='Raw Data'!B8 -> KKV Agro Powers Limited | B38: =COUNTIF($C$69:$L$98,A38) -> 4 | C38: =('Raw Data'!D8+'Raw Data'!E8-'Raw Data'!F8)/'Raw Data'!H8 -> 4.0767499 | D38: ='Raw Data'!C8/'Raw Data'!L8 -> 7.1692773 | E38: ='Raw Data'!C8/'Raw Data'!N8 -> 1.453088 | F38: ='Raw Data'!J8/'Raw Data'!M8 -> 0.42174548 | G38: ='Raw Data'!I8/('Raw Data'!M8+'Raw Data'!E8) -> 0.44295466 | H38: ='Raw Data'!E8/'Raw Data'!M8 -> 0.65580379 | I38: ='Raw Data'!I8/'Raw Data'!Q8 -> -11.843837 | J38: ='Raw Data'!I8/'Raw Data'!O8 -> 0.010947467 | K38: =IFERROR('Raw Data'!J8/'Raw Data'!O8, "") -> 0.0062950028 | L38: ='Raw Data'!R8/'Raw Data'!C8 -> 0.13948407 | M38: =AVERAGE(_xlfn.RANK.EQ(C38,$C$6:$C$64,1), _xlfn.RANK.EQ(D38,$D$6:$D$64,1), _xlfn.RANK.EQ(E38,$E$6:$E$64,1) ) -> 15.333333 | N38: =AVERAGE( _xlfn.RANK.EQ(F38,$F$6:$F$64,0), _xlfn.RANK.EQ(G38,$G$6:$G$64,0), _xlfn.RANK.EQ(J38,$J$6:$J$64,0), _xlfn.RANK.EQ(K38,$K$6:$K$64,0) ) -> 29 | O38: =AVERAGE( _xlfn.RANK.EQ(H38,$H$6:$H$64,1), _xlfn.RANK.EQ(I38,$I$6:$I$64,0) ) -> 39 | P38: =_xlfn.RANK.EQ(L38,$L$6:$L$64,0) -> 4 | Q38: =AVERAGE(M38,N38,O38,P38) -> 21.833333 | R38: =IF(Q38<=20,"Excellent",IF(Q38<=25,"Very Good",IF(Q38<=30,"Decent",IF(Q38<=35,"Average","Weak/Avoid")))) -> Very Good
A39: ='Raw Data'!B17 -> Madhav Infra Projects Limited | B39: =COUNTIF($C$69:$L$98,A39) -> 4 | C39: =('Raw Data'!D17+'Raw Data'!E17-'Raw Data'!F17)/'Raw Data'!H17 -> 5.8003829 | D39: ='Raw Data'!C17/'Raw Data'!L17 -> 8.3031507 | E39: ='Raw Data'!C17/'Raw Data'!N17 -> 1.2452115 | F39: ='Raw Data'!J17/'Raw Data'!M17 -> 0.2420903 | G39: ='Raw Data'!I17/('Raw Data'!M17+'Raw Data'!E17) -> 0.17257668 | H39: ='Raw Data'!E17/'Raw Data'!M17 -> 1.3149924 | I39: ='Raw Data'!I17/'Raw Data'!Q17 -> -2.8690992 | J39: ='Raw Data'!I17/'Raw Data'!O17 -> 0.088566796 | K39: =IFERROR('Raw Data'!J17/'Raw Data'!O17, "") -> 0.053668152 | L39: ='Raw Data'!R17/'Raw Data'!C17 -> 0.12043621 | M39: =AVERAGE(_xlfn.RANK.EQ(C39,$C$6:$C$64,1), _xlfn.RANK.EQ(D39,$D$6:$D$64,1), _xlfn.RANK.EQ(E39,$E$6:$E$64,1) ) -> 14.666667 | N39: =AVERAGE( _xlfn.RANK.EQ(F39,$F$6:$F$64,0), _xlfn.RANK.EQ(G39,$G$6:$G$64,0), _xlfn.RANK.EQ(J39,$J$6:$J$64,0), _xlfn.RANK.EQ(K39,$K$6:$K$64,0) ) -> 28.5 | O39: =AVERAGE( _xlfn.RANK.EQ(H39,$H$6:$H$64,1), _xlfn.RANK.EQ(I39,$I$6:$I$64,0) ) -> 37 | P39: =_xlfn.RANK.EQ(L39,$L$6:$L$64,0) -> 5 | Q39: =AVERAGE(M39,N39,O39,P39) -> 21.291667 | R39: =IF(Q39<=20,"Excellent",IF(Q39<=25,"Very Good",IF(Q39<=30,"Decent",IF(Q39<=35,"Average","Weak/Avoid")))) -> Very Good
A40: ='Raw Data'!B58 -> Positron Energy Limited | B40: =COUNTIF($C$69:$L$98,A40) -> 4 | C40: =('Raw Data'!D58+'Raw Data'!E58-'Raw Data'!F58)/'Raw Data'!H58 -> 6.210786 | D40: ='Raw Data'!C58/'Raw Data'!L58 -> 8.8038215 | E40: ='Raw Data'!C58/'Raw Data'!N58 -> 1.8991523 | F40: ='Raw Data'!J58/'Raw Data'!M58 -> 0.63920053 | G40: ='Raw Data'!I58/('Raw Data'!M58+'Raw Data'!E58) -> 0.51347805 | H40: ='Raw Data'!E58/'Raw Data'!M58 -> 0.19290602 | I40: ='Raw Data'!I58/'Raw Data'!Q58 -> -51.004377 | J40: ='Raw Data'!I58/'Raw Data'!O58 -> 0.040780628 | K40: =IFERROR('Raw Data'!J58/'Raw Data'!O58, "") -> 0.042556208 | L40: ='Raw Data'!R58/'Raw Data'!C58 -> 0.11358704 | M40: =AVERAGE(_xlfn.RANK.EQ(C40,$C$6:$C$64,1), _xlfn.RANK.EQ(D40,$D$6:$D$64,1), _xlfn.RANK.EQ(E40,$E$6:$E$64,1) ) -> 20.333333 | N40: =AVERAGE( _xlfn.RANK.EQ(F40,$F$6:$F$64,0), _xlfn.RANK.EQ(G40,$G$6:$G$64,0), _xlfn.RANK.EQ(J40,$J$6:$J$64,0), _xlfn.RANK.EQ(K40,$K$6:$K$64,0) ) -> 25.25 | O40: =AVERAGE( _xlfn.RANK.EQ(H40,$H$6:$H$64,1), _xlfn.RANK.EQ(I40,$I$6:$I$64,0) ) -> 40 | P40: =_xlfn.RANK.EQ(L40,$L$6:$L$64,0) -> 6 | Q40: =AVERAGE(M40,N40,O40,P40) -> 22.895833 | R40: =IF(Q40<=20,"Excellent",IF(Q40<=25,"Very Good",IF(Q40<=30,"Decent",IF(Q40<=35,"Average","Weak/Avoid")))) -> Very Good
A41: ='Raw Data'!B38 -> Adani Energy Solutions Limited | B41: =COUNTIF($C$69:$L$98,A41) -> 4 | C41: =('Raw Data'!D38+'Raw Data'!E38-'Raw Data'!F38)/'Raw Data'!H38 -> 17.906468 | D41: ='Raw Data'!C38/'Raw Data'!L38 -> 47.733036 | E41: ='Raw Data'!C38/'Raw Data'!N38 -> 5.1880264 | F41: ='Raw Data'!J38/'Raw Data'!M38 -> 0.34819314 | G41: ='Raw Data'!I38/('Raw Data'!M38+'Raw Data'!E38) -> 0.14101408 | H41: ='Raw Data'!E38/'Raw Data'!M38 -> 5.8542818 | I41: ='Raw Data'!I38/'Raw Data'!Q38 -> -2.066977 | J41: ='Raw Data'!I38/'Raw Data'!O38 -> 0.26388994 | K41: =IFERROR('Raw Data'!J38/'Raw Data'!O38, "") -> 0.095064547 | L41: ='Raw Data'!R38/'Raw Data'!C38 -> 0.020949851 | M41: =AVERAGE(_xlfn.RANK.EQ(C41,$C$6:$C$64,1), _xlfn.RANK.EQ(D41,$D$6:$D$64,1), _xlfn.RANK.EQ(E41,$E$6:$E$64,1) ) -> 47.333333 | N41: =AVERAGE( _xlfn.RANK.EQ(F41,$F$6:$F$64,0), _xlfn.RANK.EQ(G41,$G$6:$G$64,0), _xlfn.RANK.EQ(J41,$J$6:$J$64,0), _xlfn.RANK.EQ(K41,$K$6:$K$64,0) ) -> 20.75 | O41: =AVERAGE( _xlfn.RANK.EQ(H41,$H$6:$H$64,1), _xlfn.RANK.EQ(I41,$I$6:$I$64,0) ) -> 40 | P41: =_xlfn.RANK.EQ(L41,$L$6:$L$64,0) -> 38 | Q41: =AVERAGE(M41,N41,O41,P41) -> 36.520833 | R41: =IF(Q41<=20,"Excellent",IF(Q41<=25,"Very Good",IF(Q41<=30,"Decent",IF(Q41<=35,"Average","Weak/Avoid")))) -> Weak/Avoid
A42: ='Raw Data'!B40 -> Adani Green Energy Limited | B42: =COUNTIF($C$69:$L$98,A42) -> 3 | C42: =('Raw Data'!D40+'Raw Data'!E40-'Raw Data'!F40)/'Raw Data'!H40 -> 24.115198 | D42: ='Raw Data'!C40/'Raw Data'!L40 -> 82.174779 | E42: ='Raw Data'!C40/'Raw Data'!N40 -> 8.7977455 | F42: ='Raw Data'!J40/'Raw Data'!M40 -> 0.63775481 | G42: ='Raw Data'!I40/('Raw Data'!M40+'Raw Data'!E40) -> 0.078966482 | H42: ='Raw Data'!E40/'Raw Data'!M40 -> 27.859266 | I42: ='Raw Data'!I40/'Raw Data'!Q40 -> -1.2193101 | J42: ='Raw Data'!I40/'Raw Data'!O40 -> 0.59882079 | K42: =IFERROR('Raw Data'!J40/'Raw Data'!O40, "") -> 0.16758014 | L42: ='Raw Data'!R40/'Raw Data'!C40 -> 0.012169184 | M42: =AVERAGE(_xlfn.RANK.EQ(C42,$C$6:$C$64,1), _xlfn.RANK.EQ(D42,$D$6:$D$64,1), _xlfn.RANK.EQ(E42,$E$6:$E$64,1) ) -> 51.333333 | N42: =AVERAGE( _xlfn.RANK.EQ(F42,$F$6:$F$64,0), _xlfn.RANK.EQ(G42,$G$6:$G$64,0), _xlfn.RANK.EQ(J42,$J$6:$J$64,0), _xlfn.RANK.EQ(K42,$K$6:$K$64,0) ) -> 14.5 | O42: =AVERAGE( _xlfn.RANK.EQ(H42,$H$6:$H$64,1), _xlfn.RANK.EQ(I42,$I$6:$I$64,0) ) -> 37.5 | P42: =_xlfn.RANK.EQ(L42,$L$6:$L$64,0) -> 41 | Q42: =AVERAGE(M42,N42,O42,P42) -> 36.083333 | R42: =IF(Q42<=20,"Excellent",IF(Q42<=25,"Very Good",IF(Q42<=30,"Decent",IF(Q42<=35,"Average","Weak/Avoid")))) -> Weak/Avoid
A43: ='Raw Data'!B7 -> Agni Green Power Limited | B43: =COUNTIF($C$69:$L$98,A43) -> 3 | C43: =('Raw Data'!D7+'Raw Data'!E7-'Raw Data'!F7)/'Raw Data'!H7 -> 18.87023 | D43: ='Raw Data'!C7/'Raw Data'!L7 -> 71.116232 | E43: ='Raw Data'!C7/'Raw Data'!N7 -> 1.4163724 | F43: ='Raw Data'!J7/'Raw Data'!M7 -> 0.052522561 | G43: ='Raw Data'!I7/('Raw Data'!M7+'Raw Data'!E7) -> 0.11353708 | H43: ='Raw Data'!E7/'Raw Data'!M7 -> 0.82146539 | I43: ='Raw Data'!I7/'Raw Data'!Q7 -> -1.2603327 | J43: ='Raw Data'!I7/'Raw Data'!O7 -> 0.060055236 | K43: =IFERROR('Raw Data'!J7/'Raw Data'!O7, "") -> 0.015252397 | L43: ='Raw Data'!R7/'Raw Data'!C7 -> 0.014061487 | M43: =AVERAGE(_xlfn.RANK.EQ(C43,$C$6:$C$64,1), _xlfn.RANK.EQ(D43,$D$6:$D$64,1), _xlfn.RANK.EQ(E43,$E$6:$E$64,1) ) -> 37.333333 | N43: =AVERAGE( _xlfn.RANK.EQ(F43,$F$6:$F$64,0), _xlfn.RANK.EQ(G43,$G$6:$G$64,0), _xlfn.RANK.EQ(J43,$J$6:$J$64,0), _xlfn.RANK.EQ(K43,$K$6:$K$64,0) ) -> 40 | O43: =AVERAGE( _xlfn.RANK.EQ(H43,$H$6:$H$64,1), _xlfn.RANK.EQ(I43,$I$6:$I$64,0) ) -> 28 | P43: =_xlfn.RANK.EQ(L43,$L$6:$L$64,0) -> 39 | Q43: =AVERAGE(M43,N43,O43,P43) -> 36.083333 | R43: =IF(Q43<=20,"Excellent",IF(Q43<=25,"Very Good",IF(Q43<=30,"Decent",IF(Q43<=35,"Average","Weak/Avoid")))) -> Weak/Avoid
A44: ='Raw Data'!B23 -> SG Mart Limited | B44: =COUNTIF($C$69:$L$98,A44) -> 4 | C44: =('Raw Data'!D23+'Raw Data'!E23-'Raw Data'!F23)/'Raw Data'!H23 -> 31.718831 | D44: ='Raw Data'!C23/'Raw Data'!L23 -> 34.267884 | E44: ='Raw Data'!C23/'Raw Data'!N23 -> 2.9336815 | F44: ='Raw Data'!J23/'Raw Data'!M23 -> 1.5162952 | G44: ='Raw Data'!I23/('Raw Data'!M23+'Raw Data'!E23) -> 0.1278345 | H44: ='Raw Data'!E23/'Raw Data'!M23 -> 10.583866 | I44: ='Raw Data'!I23/'Raw Data'!Q23 -> -2.3014356 | J44: ='Raw Data'!I23/'Raw Data'!O23 -> 0.017248475 | K44: =IFERROR('Raw Data'!J23/'Raw Data'!O23, "") -> 0.017661715 | L44: ='Raw Data'!R23/'Raw Data'!C23 -> 0.029181843 | M44: =AVERAGE(_xlfn.RANK.EQ(C44,$C$6:$C$64,1), _xlfn.RANK.EQ(D44,$D$6:$D$64,1), _xlfn.RANK.EQ(E44,$E$6:$E$64,1) ) -> 45.333333 | N44: =AVERAGE( _xlfn.RANK.EQ(F44,$F$6:$F$64,0), _xlfn.RANK.EQ(G44,$G$6:$G$64,0), _xlfn.RANK.EQ(J44,$J$6:$J$64,0), _xlfn.RANK.EQ(K44,$K$6:$K$64,0) ) -> 30 | O44: =AVERAGE( _xlfn.RANK.EQ(H44,$H$6:$H$64,1), _xlfn.RANK.EQ(I44,$I$6:$I$64,0) ) -> 42.5 | P44: =_xlfn.RANK.EQ(L44,$L$6:$L$64,0) -> 35 | Q44: =AVERAGE(M44,N44,O44,P44) -> 38.208333 | R44: =IF(Q44<=20,"Excellent",IF(Q44<=25,"Very Good",IF(Q44<=30,"Decent",IF(Q44<=35,"Average","Weak/Avoid")))) -> Weak/Avoid
A45: ='Raw Data'!B10 -> Gita Renewable Energy Limited | B45: =COUNTIF($C$69:$L$98,A45) -> 1 | C45: =('Raw Data'!D10+'Raw Data'!E10-'Raw Data'!F10)/'Raw Data'!H10 -> 3864.1414 | D45: ='Raw Data'!C10/'Raw Data'!L10 -> -135.35335 | E45: ='Raw Data'!C10/'Raw Data'!N10 -> 2.888147 | F45: ='Raw Data'!J10/'Raw Data'!M10 -> -0.031263912 | G45: ='Raw Data'!I10/('Raw Data'!M10+'Raw Data'!E10) -> -0.045098577 | H45: ='Raw Data'!E10/'Raw Data'!M10 -> 0 | I45: ='Raw Data'!I10/'Raw Data'!Q10 -> 37.150662 | J45: ='Raw Data'!I10/'Raw Data'!O10 -> -28.475888 | K45: =IFERROR('Raw Data'!J10/'Raw Data'!O10, "") -> -19.740482 | L45: ='Raw Data'!R10/'Raw Data'!C10 -> -0.0073880697 | M45: =AVERAGE(_xlfn.RANK.EQ(C45,$C$6:$C$64,1), _xlfn.RANK.EQ(D45,$D$6:$D$64,1), _xlfn.RANK.EQ(E45,$E$6:$E$64,1) ) -> 33 | N45: =AVERAGE( _xlfn.RANK.EQ(F45,$F$6:$F$64,0), _xlfn.RANK.EQ(G45,$G$6:$G$64,0), _xlfn.RANK.EQ(J45,$J$6:$J$64,0), _xlfn.RANK.EQ(K45,$K$6:$K$64,0) ) -> 53.5 | O45: =AVERAGE( _xlfn.RANK.EQ(H45,$H$6:$H$64,1), _xlfn.RANK.EQ(I45,$I$6:$I$64,0) ) -> 10.5 | P45: =_xlfn.RANK.EQ(L45,$L$6:$L$64,0) -> 50 | Q45: =AVERAGE(M45,N45,O45,P45) -> 36.75 | R45: =IF(Q45<=20,"Excellent",IF(Q45<=25,"Very Good",IF(Q45<=30,"Decent",IF(Q45<=35,"Average","Weak/Avoid")))) -> Weak/Avoid
A46: ='Raw Data'!B16 -> EKI Energy Services Limited | B46: =COUNTIF($C$69:$L$98,A46) -> 0 | C46: =('Raw Data'!D16+'Raw Data'!E16-'Raw Data'!F16)/'Raw Data'!H16 -> -22.655434 | D46: ='Raw Data'!C16/'Raw Data'!L16 -> -17.907427 | E46: ='Raw Data'!C16/'Raw Data'!N16 -> 0.42109689 | F46: ='Raw Data'!J16/'Raw Data'!M16 -> -0.025001334 | G46: ='Raw Data'!I16/('Raw Data'!M16+'Raw Data'!E16) -> -0.076650219 | H46: ='Raw Data'!E16/'Raw Data'!M16 -> 0.0022123161 | I46: ='Raw Data'!I16/'Raw Data'!Q16 -> 150.21603 | J46: ='Raw Data'!I16/'Raw Data'!O16 -> -0.20589485 | K46: =IFERROR('Raw Data'!J16/'Raw Data'!O16, "") -> -0.06700937 | L46: ='Raw Data'!R16/'Raw Data'!C16 -> -0.055842752 | M46: =AVERAGE(_xlfn.RANK.EQ(C46,$C$6:$C$64,1), _xlfn.RANK.EQ(D46,$D$6:$D$64,1), _xlfn.RANK.EQ(E46,$E$6:$E$64,1) ) -> 5.6666667 | N46: =AVERAGE( _xlfn.RANK.EQ(F46,$F$6:$F$64,0), _xlfn.RANK.EQ(G46,$G$6:$G$64,0), _xlfn.RANK.EQ(J46,$J$6:$J$64,0), _xlfn.RANK.EQ(K46,$K$6:$K$64,0) ) -> 51.5 | O46: =AVERAGE( _xlfn.RANK.EQ(H46,$H$6:$H$64,1), _xlfn.RANK.EQ(I46,$I$6:$I$64,0) ) -> 10 | P46: =_xlfn.RANK.EQ(L46,$L$6:$L$64,0) -> 55 | Q46: =AVERAGE(M46,N46,O46,P46) -> 30.541667 | R46: =IF(Q46<=20,"Excellent",IF(Q46<=25,"Very Good",IF(Q46<=30,"Decent",IF(Q46<=35,"Average","Weak/Avoid")))) -> Average
A47: ='Raw Data'!B13 -> Karma Energy Limited | B47: =COUNTIF($C$69:$L$98,A47) -> 0 | C47: =('Raw Data'!D13+'Raw Data'!E13-'Raw Data'!F13)/'Raw Data'!H13 -> -2555.1065 | D47: ='Raw Data'!C13/'Raw Data'!L13 -> 112.35649 | E47: ='Raw Data'!C13/'Raw Data'!N13 -> 1.5111702 | F47: ='Raw Data'!J13/'Raw Data'!M13 -> 0.018545856 | G47: ='Raw Data'!I13/('Raw Data'!M13+'Raw Data'!E13) -> -0.057219326 | H47: ='Raw Data'!E13/'Raw Data'!M13 -> 0.057599182 | I47: ='Raw Data'!I13/'Raw Data'!Q13 -> 10.661308 | J47: ='Raw Data'!I13/'Raw Data'!O13 -> -0.19085576 | K47: =IFERROR('Raw Data'!J13/'Raw Data'!O13, "") -> 0.058490901 | L47: ='Raw Data'!R13/'Raw Data'!C13 -> 0.0089002428 | M47: =AVERAGE(_xlfn.RANK.EQ(C47,$C$6:$C$64,1), _xlfn.RANK.EQ(D47,$D$6:$D$64,1), _xlfn.RANK.EQ(E47,$E$6:$E$64,1) ) -> 25.333333 | N47: =AVERAGE( _xlfn.RANK.EQ(F47,$F$6:$F$64,0), _xlfn.RANK.EQ(G47,$G$6:$G$64,0), _xlfn.RANK.EQ(J47,$J$6:$J$64,0), _xlfn.RANK.EQ(K47,$K$6:$K$64,0) ) -> 47.25 | O47: =AVERAGE( _xlfn.RANK.EQ(H47,$H$6:$H$64,1), _xlfn.RANK.EQ(I47,$I$6:$I$64,0) ) -> 16 | P47: =_xlfn.RANK.EQ(L47,$L$6:$L$64,0) -> 44 | Q47: =AVERAGE(M47,N47,O47,P47) -> 33.145833 | R47: =IF(Q47<=20,"Excellent",IF(Q47<=25,"Very Good",IF(Q47<=30,"Decent",IF(Q47<=35,"Average","Weak/Avoid")))) -> Average
A48: ='Raw Data'!B56 -> Rajasthan Cylinders and Containers Limited | B48: =COUNTIF($C$69:$L$98,A48) -> 0 | C48: =('Raw Data'!D56+'Raw Data'!E56-'Raw Data'!F56)/'Raw Data'!H56 -> -4.9189496 | D48: ='Raw Data'!C56/'Raw Data'!L56 -> -9.5000861 | E48: ='Raw Data'!C56/'Raw Data'!N56 -> 0.79487937 | F48: ='Raw Data'!J56/'Raw Data'!M56 -> -0.12011116 | G48: ='Raw Data'!I56/('Raw Data'!M56+'Raw Data'!E56) -> -0.22915947 | H48: ='Raw Data'!E56/'Raw Data'!M56 -> 0.042055938 | I48: ='Raw Data'!I56/'Raw Data'!Q56 -> 65.856333 | J48: ='Raw Data'!I56/'Raw Data'!O56 -> -28.633188 | K48: =IFERROR('Raw Data'!J56/'Raw Data'!O56, "") -> -14.402047 | L48: ='Raw Data'!R56/'Raw Data'!C56 -> -0.1052622 | M48: =AVERAGE(_xlfn.RANK.EQ(C48,$C$6:$C$64,1), _xlfn.RANK.EQ(D48,$D$6:$D$64,1), _xlfn.RANK.EQ(E48,$E$6:$E$64,1) ) -> 8 | N48: =AVERAGE( _xlfn.RANK.EQ(F48,$F$6:$F$64,0), _xlfn.RANK.EQ(G48,$G$6:$G$64,0), _xlfn.RANK.EQ(J48,$J$6:$J$64,0), _xlfn.RANK.EQ(K48,$K$6:$K$64,0) ) -> 55.75 | O48: =AVERAGE( _xlfn.RANK.EQ(H48,$H$6:$H$64,1), _xlfn.RANK.EQ(I48,$I$6:$I$64,0) ) -> 14 | P48: =_xlfn.RANK.EQ(L48,$L$6:$L$64,0) -> 56 | Q48: =AVERAGE(M48,N48,O48,P48) -> 33.4375 | R48: =IF(Q48<=20,"Excellent",IF(Q48<=25,"Very Good",IF(Q48<=30,"Decent",IF(Q48<=35,"Average","Weak/Avoid")))) -> Average
A49: ='Raw Data'!B52 -> Reliance Power Limited | B49: =COUNTIF($C$69:$L$98,A49) -> 2 | C49: =('Raw Data'!D52+'Raw Data'!E52-'Raw Data'!F52)/'Raw Data'!H52 -> 21.94477 | D49: ='Raw Data'!C52/'Raw Data'!L52 -> -6.6845361 | E49: ='Raw Data'!C52/'Raw Data'!N52 -> 1.0762589 | F49: ='Raw Data'!J52/'Raw Data'!M52 -> 1.3822372 | G49: ='Raw Data'!I52/('Raw Data'!M52+'Raw Data'!E52) -> 0.0089260855 | H49: ='Raw Data'!E52/'Raw Data'!M52 -> -13.871624 | I49: ='Raw Data'!I52/'Raw Data'!Q52 -> -0.11663733 | J49: ='Raw Data'!I52/'Raw Data'!O52 -> 0.019500659 | K49: =IFERROR('Raw Data'!J52/'Raw Data'!O52, "") -> -0.23460511 | L49: ='Raw Data'!R52/'Raw Data'!C52 -> -0.14959901 | M49: =AVERAGE(_xlfn.RANK.EQ(C49,$C$6:$C$64,1), _xlfn.RANK.EQ(D49,$D$6:$D$64,1), _xlfn.RANK.EQ(E49,$E$6:$E$64,1) ) -> 21.666667 | N49: =AVERAGE( _xlfn.RANK.EQ(F49,$F$6:$F$64,0), _xlfn.RANK.EQ(G49,$G$6:$G$64,0), _xlfn.RANK.EQ(J49,$J$6:$J$64,0), _xlfn.RANK.EQ(K49,$K$6:$K$64,0) ) -> 36.25 | O49: =AVERAGE( _xlfn.RANK.EQ(H49,$H$6:$H$64,1), _xlfn.RANK.EQ(I49,$I$6:$I$64,0) ) -> 7 | P49: =_xlfn.RANK.EQ(L49,$L$6:$L$64,0) -> 57 | Q49: =AVERAGE(M49,N49,O49,P49) -> 30.479167 | R49: =IF(Q49<=20,"Excellent",IF(Q49<=25,"Very Good",IF(Q49<=30,"Decent",IF(Q49<=35,"Average","Weak/Avoid")))) -> Average
A50: ='Raw Data'!B32 -> SJVN Limited | B50: =COUNTIF($C$69:$L$98,A50) -> 2 | C50: =('Raw Data'!D32+'Raw Data'!E32-'Raw Data'!F32)/'Raw Data'!H32 -> 22.769177 | D50: ='Raw Data'!C32/'Raw Data'!L32 -> 32.840987 | E50: ='Raw Data'!C32/'Raw Data'!N32 -> 1.8985195 | F50: ='Raw Data'!J32/'Raw Data'!M32 -> 0.080473841 | G50: ='Raw Data'!I32/('Raw Data'!M32+'Raw Data'!E32) -> 0.04151692 | H50: ='Raw Data'!E32/'Raw Data'!M32 -> 2.6533207 | I50: ='Raw Data'!I32/'Raw Data'!Q32 -> -2.0781979 | J50: ='Raw Data'!I32/'Raw Data'!O32 -> 0.50288573 | K50: =IFERROR('Raw Data'!J32/'Raw Data'!O32, "") -> 0.26681554 | L50: ='Raw Data'!R32/'Raw Data'!C32 -> 0.030449754 | M50: =AVERAGE(_xlfn.RANK.EQ(C50,$C$6:$C$64,1), _xlfn.RANK.EQ(D50,$D$6:$D$64,1), _xlfn.RANK.EQ(E50,$E$6:$E$64,1) ) -> 39.666667 | N50: =AVERAGE( _xlfn.RANK.EQ(F50,$F$6:$F$64,0), _xlfn.RANK.EQ(G50,$G$6:$G$64,0), _xlfn.RANK.EQ(J50,$J$6:$J$64,0), _xlfn.RANK.EQ(K50,$K$6:$K$64,0) ) -> 22 | O50: =AVERAGE( _xlfn.RANK.EQ(H50,$H$6:$H$64,1), _xlfn.RANK.EQ(I50,$I$6:$I$64,0) ) -> 39 | P50: =_xlfn.RANK.EQ(L50,$L$6:$L$64,0) -> 33 | Q50: =AVERAGE(M50,N50,O50,P50) -> 33.416667 | R50: =IF(Q50<=20,"Excellent",IF(Q50<=25,"Very Good",IF(Q50<=30,"Decent",IF(Q50<=35,"Average","Weak/Avoid")))) -> Average
A51: ='Raw Data'!B20 -> Texmaco Infrastructure & Holdings Limited | B51: =COUNTIF($C$69:$L$98,A51) -> 0 | C51: =('Raw Data'!D20+'Raw Data'!E20-'Raw Data'!F20)/'Raw Data'!H20 -> -636.06393 | D51: ='Raw Data'!C20/'Raw Data'!L20 -> 220.35427 | E51: ='Raw Data'!C20/'Raw Data'!N20 -> 0.8312482 | F51: ='Raw Data'!J20/'Raw Data'!M20 -> 0.012398546 | G51: ='Raw Data'!I20/('Raw Data'!M20+'Raw Data'!E20) -> -0.009826794 | H51: ='Raw Data'!E20/'Raw Data'!M20 -> 0.073042332 | I51: ='Raw Data'!I20/'Raw Data'!Q20 -> 1.8197874 | J51: ='Raw Data'!I20/'Raw Data'!O20 -> -1.9392899 | K51: =IFERROR('Raw Data'!J20/'Raw Data'!O20, "") -> 2.2802622 | L51: ='Raw Data'!R20/'Raw Data'!C20 -> 0.0045381467 | M51: =AVERAGE(_xlfn.RANK.EQ(C51,$C$6:$C$64,1), _xlfn.RANK.EQ(D51,$D$6:$D$64,1), _xlfn.RANK.EQ(E51,$E$6:$E$64,1) ) -> 23.333333 | N51: =AVERAGE( _xlfn.RANK.EQ(F51,$F$6:$F$64,0), _xlfn.RANK.EQ(G51,$G$6:$G$64,0), _xlfn.RANK.EQ(J51,$J$6:$J$64,0), _xlfn.RANK.EQ(K51,$K$6:$K$64,0) ) -> 37.5 | O51: =AVERAGE( _xlfn.RANK.EQ(H51,$H$6:$H$64,1), _xlfn.RANK.EQ(I51,$I$6:$I$64,0) ) -> 18 | P51: =_xlfn.RANK.EQ(L51,$L$6:$L$64,0) -> 48 | Q51: =AVERAGE(M51,N51,O51,P51) -> 31.708333 | R51: =IF(Q51<=20,"Excellent",IF(Q51<=25,"Very Good",IF(Q51<=30,"Decent",IF(Q51<=35,"Average","Weak/Avoid")))) -> Average
A52: ='Raw Data'!B46 -> Ujaas Energy Limited | B52: =COUNTIF($C$69:$L$98,A52) -> 1 | C52: =('Raw Data'!D46+'Raw Data'!E46-'Raw Data'!F46)/'Raw Data'!H46 -> -1306.1289 | D52: ='Raw Data'!C46/'Raw Data'!L46 -> 222.14315 | E52: ='Raw Data'!C46/'Raw Data'!N46 -> 29.878085 | F52: ='Raw Data'!J46/'Raw Data'!M46 -> -0.7745911 | G52: ='Raw Data'!I46/('Raw Data'!M46+'Raw Data'!E46) -> 0.010112111 | H52: ='Raw Data'!E46/'Raw Data'!M46 -> -2.4716713 | I52: ='Raw Data'!I46/'Raw Data'!Q46 -> -0.41402757 | J52: ='Raw Data'!I46/'Raw Data'!O46 -> 0.0062029904 | K52: =IFERROR('Raw Data'!J46/'Raw Data'!O46, "") -> 0.32286499 | L52: ='Raw Data'!R46/'Raw Data'!C46 -> 0.0045016018 | M52: =AVERAGE(_xlfn.RANK.EQ(C52,$C$6:$C$64,1), _xlfn.RANK.EQ(D52,$D$6:$D$64,1), _xlfn.RANK.EQ(E52,$E$6:$E$64,1) ) -> 40 | N52: =AVERAGE( _xlfn.RANK.EQ(F52,$F$6:$F$64,0), _xlfn.RANK.EQ(G52,$G$6:$G$64,0), _xlfn.RANK.EQ(J52,$J$6:$J$64,0), _xlfn.RANK.EQ(K52,$K$6:$K$64,0) ) -> 38.25 | O52: =AVERAGE( _xlfn.RANK.EQ(H52,$H$6:$H$64,1), _xlfn.RANK.EQ(I52,$I$6:$I$64,0) ) -> 9 | P52: =_xlfn.RANK.EQ(L52,$L$6:$L$64,0) -> 49 | Q52: =AVERAGE(M52,N52,O52,P52) -> 34.0625 | R52: =IF(Q52<=20,"Excellent",IF(Q52<=25,"Very Good",IF(Q52<=30,"Decent",IF(Q52<=35,"Average","Weak/Avoid")))) -> Average
A53: ='Raw Data'!B44 -> Venlon Enterprises Limited | B53: =COUNTIF($C$69:$L$98,A53) -> 0 | C53: =('Raw Data'!D44+'Raw Data'!E44-'Raw Data'!F44)/'Raw Data'!H44 -> -4.5721247 | D53: ='Raw Data'!C44/'Raw Data'!L44 -> -2.6462983 | E53: ='Raw Data'!C44/'Raw Data'!N44 -> 4.6572795 | F53: ='Raw Data'!J44/'Raw Data'!M44 -> 0.11219228 | G53: ='Raw Data'!I44/('Raw Data'!M44+'Raw Data'!E44) -> 0.14522416 | H53: ='Raw Data'!E44/'Raw Data'!M44 -> -0.18758405 | I53: ='Raw Data'!I44/'Raw Data'!Q44 -> 186.98215 | J53: ='Raw Data'!I44/'Raw Data'!O44 -> -1.2290083 | K53: =IFERROR('Raw Data'!J44/'Raw Data'!O44, "") -> -1.168693 | L53: ='Raw Data'!R44/'Raw Data'!C44 -> -0.37788634 | M53: =AVERAGE(_xlfn.RANK.EQ(C53,$C$6:$C$64,1), _xlfn.RANK.EQ(D53,$D$6:$D$64,1), _xlfn.RANK.EQ(E53,$E$6:$E$64,1) ) -> 23 | N53: =AVERAGE( _xlfn.RANK.EQ(F53,$F$6:$F$64,0), _xlfn.RANK.EQ(G53,$G$6:$G$64,0), _xlfn.RANK.EQ(J53,$J$6:$J$64,0), _xlfn.RANK.EQ(K53,$K$6:$K$64,0) ) -> 42 | O53: =AVERAGE( _xlfn.RANK.EQ(H53,$H$6:$H$64,1), _xlfn.RANK.EQ(I53,$I$6:$I$64,0) ) -> 8 | P53: =_xlfn.RANK.EQ(L53,$L$6:$L$64,0) -> 58 | Q53: =AVERAGE(M53,N53,O53,P53) -> 32.75 | R53: =IF(Q53<=20,"Excellent",IF(Q53<=25,"Very Good",IF(Q53<=30,"Decent",IF(Q53<=35,"Average","Weak/Avoid")))) -> Average
A54: ='Raw Data'!B43 -> Jayshree Chemicals Limited | B54: =COUNTIF($C$69:$L$98,A54) -> 0 | C54: =('Raw Data'!D43+'Raw Data'!E43-'Raw Data'!F43)/'Raw Data'!H43 -> -19.841737 | D54: ='Raw Data'!C43/'Raw Data'!L43 -> -76.032732 | E54: ='Raw Data'!C43/'Raw Data'!N43 -> 1.5463055 | F54: ='Raw Data'!J43/'Raw Data'!M43 -> 0.0063428083 | G54: ='Raw Data'!I43/('Raw Data'!M43+'Raw Data'!E43) -> 0.023196372 | H54: ='Raw Data'!E43/'Raw Data'!M43 -> -0.022619715 | I54: ='Raw Data'!I43/'Raw Data'!Q43 -> 14.393986 | J54: ='Raw Data'!I43/'Raw Data'!O43 -> -0.04016936 | K54: =IFERROR('Raw Data'!J43/'Raw Data'!O43, "") -> -0.011238099 | L54: ='Raw Data'!R43/'Raw Data'!C43 -> -0.01315223 | M54: =AVERAGE(_xlfn.RANK.EQ(C54,$C$6:$C$64,1), _xlfn.RANK.EQ(D54,$D$6:$D$64,1), _xlfn.RANK.EQ(E54,$E$6:$E$64,1) ) -> 10.666667 | N54: =AVERAGE( _xlfn.RANK.EQ(F54,$F$6:$F$64,0), _xlfn.RANK.EQ(G54,$G$6:$G$64,0), _xlfn.RANK.EQ(J54,$J$6:$J$64,0), _xlfn.RANK.EQ(K54,$K$6:$K$64,0) ) -> 47.5 | O54: =AVERAGE( _xlfn.RANK.EQ(H54,$H$6:$H$64,1), _xlfn.RANK.EQ(I54,$I$6:$I$64,0) ) -> 10.5 | P54: =_xlfn.RANK.EQ(L54,$L$6:$L$64,0) -> 51 | Q54: =AVERAGE(M54,N54,O54,P54) -> 29.916667 | R54: =IF(Q54<=20,"Excellent",IF(Q54<=25,"Very Good",IF(Q54<=30,"Decent",IF(Q54<=35,"Average","Weak/Avoid")))) -> Decent
A55: ='Raw Data'!B9 -> SRM Energy Limited | B55: =COUNTIF($C$69:$L$98,A55) -> 0 | C55: =('Raw Data'!D9+'Raw Data'!E9-'Raw Data'!F9)/'Raw Data'!H9 -> -163.1127 | D55: ='Raw Data'!C9/'Raw Data'!L9 -> -42.394728 | E55: ='Raw Data'!C9/'Raw Data'!N9 -> -0.35827685 | F55: ='Raw Data'!J9/'Raw Data'!M9 -> 0.0069077406 | G55: ='Raw Data'!I9/('Raw Data'!M9+'Raw Data'!E9) -> 0.040423079 | H55: ='Raw Data'!E9/'Raw Data'!M9 -> -0.82915581 | I55: ='Raw Data'!I9/'Raw Data'!Q9 -> 3740.5833 | J55: ='Raw Data'!I9/'Raw Data'!O9 -> -403.53054 | K55: =IFERROR('Raw Data'!J9/'Raw Data'!O9, "") -> -403.62943 | L55: ='Raw Data'!R9/'Raw Data'!C9 -> -0.023587838 | M55: =AVERAGE(_xlfn.RANK.EQ(C55,$C$6:$C$64,1), _xlfn.RANK.EQ(D55,$D$6:$D$64,1), _xlfn.RANK.EQ(E55,$E$6:$E$64,1) ) -> 3 | N55: =AVERAGE( _xlfn.RANK.EQ(F55,$F$6:$F$64,0), _xlfn.RANK.EQ(G55,$G$6:$G$64,0), _xlfn.RANK.EQ(J55,$J$6:$J$64,0), _xlfn.RANK.EQ(K55,$K$6:$K$64,0) ) -> 51.5 | O55: =AVERAGE( _xlfn.RANK.EQ(H55,$H$6:$H$64,1), _xlfn.RANK.EQ(I55,$I$6:$I$64,0) ) -> 5.5 | P55: =_xlfn.RANK.EQ(L55,$L$6:$L$64,0) -> 53 | Q55: =AVERAGE(M55,N55,O55,P55) -> 28.25 | R55: =IF(Q55<=20,"Excellent",IF(Q55<=25,"Very Good",IF(Q55<=30,"Decent",IF(Q55<=35,"Average","Weak/Avoid")))) -> Decent
A56: ='Raw Data'!B27 -> Reliance Infrastructure Limited | B56: =COUNTIF($C$69:$L$98,A56) -> 2 | C56: =('Raw Data'!D27+'Raw Data'!E27-'Raw Data'!F27)/'Raw Data'!H27 -> 1.9981267 | D56: ='Raw Data'!C27/'Raw Data'!L27 -> 0.64106731 | E56: ='Raw Data'!C27/'Raw Data'!N27 -> 0.33806546 | F56: ='Raw Data'!J27/'Raw Data'!M27 -> -1.6204777 | G56: ='Raw Data'!I27/('Raw Data'!M27+'Raw Data'!E27) -> 0.99709924 | H56: ='Raw Data'!E27/'Raw Data'!M27 -> -1.9705016 | I56: ='Raw Data'!I27/'Raw Data'!Q27 -> -2.184284 | J56: ='Raw Data'!I27/'Raw Data'!O27 -> 0.14003802 | K56: =IFERROR('Raw Data'!J27/'Raw Data'!O27, "") -> 0.23450623 | L56: ='Raw Data'!R27/'Raw Data'!C27 -> 1.5598986 | M56: =AVERAGE(_xlfn.RANK.EQ(C56,$C$6:$C$64,1), _xlfn.RANK.EQ(D56,$D$6:$D$64,1), _xlfn.RANK.EQ(E56,$E$6:$E$64,1) ) -> 8.6666667 | N56: =AVERAGE( _xlfn.RANK.EQ(F56,$F$6:$F$64,0), _xlfn.RANK.EQ(G56,$G$6:$G$64,0), _xlfn.RANK.EQ(J56,$J$6:$J$64,0), _xlfn.RANK.EQ(K56,$K$6:$K$64,0) ) -> 24.25 | O56: =AVERAGE( _xlfn.RANK.EQ(H56,$H$6:$H$64,1), _xlfn.RANK.EQ(I56,$I$6:$I$64,0) ) -> 15 | P56: =_xlfn.RANK.EQ(L56,$L$6:$L$64,0) -> 2 | Q56: =AVERAGE(M56,N56,O56,P56) -> 12.479167 | R56: =IF(Q56<=20,"Excellent",IF(Q56<=25,"Very Good",IF(Q56<=30,"Decent",IF(Q56<=35,"Average","Weak/Avoid")))) -> Excellent
A57: ='Raw Data'!B29 -> Swan Corp Limited | B57: =COUNTIF($C$69:$L$98,A57) -> 0 | C57: =('Raw Data'!D29+'Raw Data'!E29-'Raw Data'!F29)/'Raw Data'!H29 -> -33.642668 | D57: ='Raw Data'!C29/'Raw Data'!L29 -> 15.389204 | E57: ='Raw Data'!C29/'Raw Data'!N29 -> 1.3824708 | F57: ='Raw Data'!J29/'Raw Data'!M29 -> 0.49887255 | G57: ='Raw Data'!I29/('Raw Data'!M29+'Raw Data'!E29) -> -0.15214029 | H57: ='Raw Data'!E29/'Raw Data'!M29 -> 2.3300697 | I57: ='Raw Data'!I29/'Raw Data'!Q29 -> 4.1550742 | J57: ='Raw Data'!I29/'Raw Data'!O29 -> -0.12883678 | K57: =IFERROR('Raw Data'!J29/'Raw Data'!O29, "") -> 0.1268621 | L57: ='Raw Data'!R29/'Raw Data'!C29 -> 0.064980621 | M57: =AVERAGE(_xlfn.RANK.EQ(C57,$C$6:$C$64,1), _xlfn.RANK.EQ(D57,$D$6:$D$64,1), _xlfn.RANK.EQ(E57,$E$6:$E$64,1) ) -> 16 | N57: =AVERAGE( _xlfn.RANK.EQ(F57,$F$6:$F$64,0), _xlfn.RANK.EQ(G57,$G$6:$G$64,0), _xlfn.RANK.EQ(J57,$J$6:$J$64,0), _xlfn.RANK.EQ(K57,$K$6:$K$64,0) ) -> 34.75 | O57: =AVERAGE( _xlfn.RANK.EQ(H57,$H$6:$H$64,1), _xlfn.RANK.EQ(I57,$I$6:$I$64,0) ) -> 30.5 | P57: =_xlfn.RANK.EQ(L57,$L$6:$L$64,0) -> 16 | Q57: =AVERAGE(M57,N57,O57,P57) -> 24.3125 | R57: =IF(Q57<=20,"Excellent",IF(Q57<=25,"Very Good",IF(Q57<=30,"Decent",IF(Q57<=35,"Average","Weak/Avoid")))) -> Very Good
A58: ='Raw Data'!B18 -> India Power Corporation Limited | B58: =COUNTIF($C$69:$L$98,A58) -> 0 | C58: =('Raw Data'!D18+'Raw Data'!E18-'Raw Data'!F18)/'Raw Data'!H18 -> 465.61415 | D58: ='Raw Data'!C18/'Raw Data'!L18 -> 137.40559 | E58: ='Raw Data'!C18/'Raw Data'!N18 -> 1.0864976 | F58: ='Raw Data'!J18/'Raw Data'!M18 -> 0.0070645929 | G58: ='Raw Data'!I18/('Raw Data'!M18+'Raw Data'!E18) -> -0.030825758 | H58: ='Raw Data'!E18/'Raw Data'!M18 -> 0.1582608 | I58: ='Raw Data'!I18/'Raw Data'!Q18 -> 1.4855892 | J58: ='Raw Data'!I18/'Raw Data'!O18 -> -0.057615491 | K58: =IFERROR('Raw Data'!J18/'Raw Data'!O18, "") -> 0.011400037 | L58: ='Raw Data'!R18/'Raw Data'!C18 -> 0.0072777241 | M58: =AVERAGE(_xlfn.RANK.EQ(C58,$C$6:$C$64,1), _xlfn.RANK.EQ(D58,$D$6:$D$64,1), _xlfn.RANK.EQ(E58,$E$6:$E$64,1) ) -> 42 | N58: =AVERAGE( _xlfn.RANK.EQ(F58,$F$6:$F$64,0), _xlfn.RANK.EQ(G58,$G$6:$G$64,0), _xlfn.RANK.EQ(J58,$J$6:$J$64,0), _xlfn.RANK.EQ(K58,$K$6:$K$64,0) ) -> 48 | O58: =AVERAGE( _xlfn.RANK.EQ(H58,$H$6:$H$64,1), _xlfn.RANK.EQ(I58,$I$6:$I$64,0) ) -> 20 | P58: =_xlfn.RANK.EQ(L58,$L$6:$L$64,0) -> 47 | Q58: =AVERAGE(M58,N58,O58,P58) -> 39.25 | R58: =IF(Q58<=20,"Excellent",IF(Q58<=25,"Very Good",IF(Q58<=30,"Decent",IF(Q58<=35,"Average","Weak/Avoid")))) -> Weak/Avoid
A59: ='Raw Data'!B49 -> Inox Green Energy Services Limited | B59: =COUNTIF($C$69:$L$98,A59) -> 0 | C59: =('Raw Data'!D49+'Raw Data'!E49-'Raw Data'!F49)/'Raw Data'!H49 -> 230.55055 | D59: ='Raw Data'!C49/'Raw Data'!L49 -> 120.81319 | E59: ='Raw Data'!C49/'Raw Data'!N49 -> 3.5646291 | F59: ='Raw Data'!J49/'Raw Data'!M49 -> -0.17007539 | G59: ='Raw Data'!I49/('Raw Data'!M49+'Raw Data'!E49) -> 0.064808026 | H59: ='Raw Data'!E49/'Raw Data'!M49 -> -0.27165922 | I59: ='Raw Data'!I49/'Raw Data'!Q49 -> 1.8358941 | J59: ='Raw Data'!I49/'Raw Data'!O49 -> -0.060902673 | K59: =IFERROR('Raw Data'!J49/'Raw Data'!O49, "") -> 0.21943929 | L59: ='Raw Data'!R49/'Raw Data'!C49 -> 0.0082772418 | M59: =AVERAGE(_xlfn.RANK.EQ(C59,$C$6:$C$64,1), _xlfn.RANK.EQ(D59,$D$6:$D$64,1), _xlfn.RANK.EQ(E59,$E$6:$E$64,1) ) -> 52.333333 | N59: =AVERAGE( _xlfn.RANK.EQ(F59,$F$6:$F$64,0), _xlfn.RANK.EQ(G59,$G$6:$G$64,0), _xlfn.RANK.EQ(J59,$J$6:$J$64,0), _xlfn.RANK.EQ(K59,$K$6:$K$64,0) ) -> 38.25 | O59: =AVERAGE( _xlfn.RANK.EQ(H59,$H$6:$H$64,1), _xlfn.RANK.EQ(I59,$I$6:$I$64,0) ) -> 11 | P59: =_xlfn.RANK.EQ(L59,$L$6:$L$64,0) -> 45 | Q59: =AVERAGE(M59,N59,O59,P59) -> 36.645833 | R59: =IF(Q59<=20,"Excellent",IF(Q59<=25,"Very Good",IF(Q59<=30,"Decent",IF(Q59<=35,"Average","Weak/Avoid")))) -> Weak/Avoid
A60: ='Raw Data'!B19 -> Jyoti Structures Limited | B60: =COUNTIF($C$69:$L$98,A60) -> 1 | C60: =('Raw Data'!D19+'Raw Data'!E19-'Raw Data'!F19)/'Raw Data'!H19 -> 74.352676 | D60: ='Raw Data'!C19/'Raw Data'!L19 -> 28.794468 | E60: ='Raw Data'!C19/'Raw Data'!N19 -> 2.5129842 | F60: ='Raw Data'!J19/'Raw Data'!M19 -> -0.01935706 | G60: ='Raw Data'!I19/('Raw Data'!M19+'Raw Data'!E19) -> -0.086063946 | H60: ='Raw Data'!E19/'Raw Data'!M19 -> -0.85487566 | I60: ='Raw Data'!I19/'Raw Data'!Q19 -> -220.07373 | J60: ='Raw Data'!I19/'Raw Data'!O19 -> 0.046994081 | K60: =IFERROR('Raw Data'!J19/'Raw Data'!O19, "") -> 0.072831802 | L60: ='Raw Data'!R19/'Raw Data'!C19 -> 0.034728893 | M60: =AVERAGE(_xlfn.RANK.EQ(C60,$C$6:$C$64,1), _xlfn.RANK.EQ(D60,$D$6:$D$64,1), _xlfn.RANK.EQ(E60,$E$6:$E$64,1) ) -> 43.666667 | N60: =AVERAGE( _xlfn.RANK.EQ(F60,$F$6:$F$64,0), _xlfn.RANK.EQ(G60,$G$6:$G$64,0), _xlfn.RANK.EQ(J60,$J$6:$J$64,0), _xlfn.RANK.EQ(K60,$K$6:$K$64,0) ) -> 44.75 | O60: =AVERAGE( _xlfn.RANK.EQ(H60,$H$6:$H$64,1), _xlfn.RANK.EQ(I60,$I$6:$I$64,0) ) -> 31.5 | P60: =_xlfn.RANK.EQ(L60,$L$6:$L$64,0) -> 32 | Q60: =AVERAGE(M60,N60,O60,P60) -> 37.979167 | R60: =IF(Q60<=20,"Excellent",IF(Q60<=25,"Very Good",IF(Q60<=30,"Decent",IF(Q60<=35,"Average","Weak/Avoid")))) -> Weak/Avoid
A61: ='Raw Data'!B53 -> NTPC Green Energy Limited | B61: =COUNTIF($C$69:$L$98,A61) -> 1 | C61: =('Raw Data'!D53+'Raw Data'!E53-'Raw Data'!F53)/'Raw Data'!H53 -> 46.826773 | D61: ='Raw Data'!C53/'Raw Data'!L53 -> 131.74038 | E61: ='Raw Data'!C53/'Raw Data'!N53 -> 3.9110188 | F61: ='Raw Data'!J53/'Raw Data'!M53 -> 0.055465435 | G61: ='Raw Data'!I53/('Raw Data'!M53+'Raw Data'!E53) -> 0.040729301 | H61: ='Raw Data'!E53/'Raw Data'!M53 -> 1.9346953 | I61: ='Raw Data'!I53/'Raw Data'!Q53 -> -1.545134 | J61: ='Raw Data'!I53/'Raw Data'!O53 -> 0.51963745 | K61: =IFERROR('Raw Data'!J53/'Raw Data'!O53, "") -> 0.24113092 | L61: ='Raw Data'!R53/'Raw Data'!C53 -> 0.0075906871 | M61: =AVERAGE(_xlfn.RANK.EQ(C61,$C$6:$C$64,1), _xlfn.RANK.EQ(D61,$D$6:$D$64,1), _xlfn.RANK.EQ(E61,$E$6:$E$64,1) ) -> 52 | N61: =AVERAGE( _xlfn.RANK.EQ(F61,$F$6:$F$64,0), _xlfn.RANK.EQ(G61,$G$6:$G$64,0), _xlfn.RANK.EQ(J61,$J$6:$J$64,0), _xlfn.RANK.EQ(K61,$K$6:$K$64,0) ) -> 23 | O61: =AVERAGE( _xlfn.RANK.EQ(H61,$H$6:$H$64,1), _xlfn.RANK.EQ(I61,$I$6:$I$64,0) ) -> 36 | P61: =_xlfn.RANK.EQ(L61,$L$6:$L$64,0) -> 46 | Q61: =AVERAGE(M61,N61,O61,P61) -> 39.25 | R61: =IF(Q61<=20,"Excellent",IF(Q61<=25,"Very Good",IF(Q61<=30,"Decent",IF(Q61<=35,"Average","Weak/Avoid")))) -> Weak/Avoid
A62: ='Raw Data'!B48 -> Ravindra Energy Limited | B62: =COUNTIF($C$69:$L$98,A62) -> 1 | C62: =('Raw Data'!D48+'Raw Data'!E48-'Raw Data'!F48)/'Raw Data'!H48 -> 80.933962 | D62: ='Raw Data'!C48/'Raw Data'!L48 -> -42.952805 | E62: ='Raw Data'!C48/'Raw Data'!N48 -> 15.725191 | F62: ='Raw Data'!J48/'Raw Data'!M48 -> 0.19751422 | G62: ='Raw Data'!I48/('Raw Data'!M48+'Raw Data'!E48) -> -0.1220584 | H62: ='Raw Data'!E48/'Raw Data'!M48 -> -0.36631685 | I62: ='Raw Data'!I48/'Raw Data'!Q48 -> -620.77669 | J62: ='Raw Data'!I48/'Raw Data'!O48 -> 0.25937921 | K62: =IFERROR('Raw Data'!J48/'Raw Data'!O48, "") -> -0.66235942 | L62: ='Raw Data'!R48/'Raw Data'!C48 -> -0.023281367 | M62: =AVERAGE(_xlfn.RANK.EQ(C62,$C$6:$C$64,1), _xlfn.RANK.EQ(D62,$D$6:$D$64,1), _xlfn.RANK.EQ(E62,$E$6:$E$64,1) ) -> 38.333333 | N62: =AVERAGE( _xlfn.RANK.EQ(F62,$F$6:$F$64,0), _xlfn.RANK.EQ(G62,$G$6:$G$64,0), _xlfn.RANK.EQ(J62,$J$6:$J$64,0), _xlfn.RANK.EQ(K62,$K$6:$K$64,0) ) -> 35.75 | O62: =AVERAGE( _xlfn.RANK.EQ(H62,$H$6:$H$64,1), _xlfn.RANK.EQ(I62,$I$6:$I$64,0) ) -> 35 | P62: =_xlfn.RANK.EQ(L62,$L$6:$L$64,0) -> 52 | Q62: =AVERAGE(M62,N62,O62,P62) -> 40.270833 | R62: =IF(Q62<=20,"Excellent",IF(Q62<=25,"Very Good",IF(Q62<=30,"Decent",IF(Q62<=35,"Average","Weak/Avoid")))) -> Weak/Avoid
A63: ='Raw Data'!B11 -> Skyline Ventures India Limited | B63: =COUNTIF($C$69:$L$98,A63) -> 0 | C63: =('Raw Data'!D11+'Raw Data'!E11-'Raw Data'!F11)/'Raw Data'!H11 -> -25.314774 | D63: ='Raw Data'!C11/'Raw Data'!L11 -> -22.120368 | E63: ='Raw Data'!C11/'Raw Data'!N11 -> 3.7686782 | F63: ='Raw Data'!J11/'Raw Data'!M11 -> -25.178526 | G63: ='Raw Data'!I11/('Raw Data'!M11+'Raw Data'!E11) -> -0.58696805 | H63: ='Raw Data'!E11/'Raw Data'!M11 -> 41.922115 | I63: ='Raw Data'!I11/'Raw Data'!Q11 -> 6550.4167 | J63: ='Raw Data'!I11/'Raw Data'!O11 -> -706.65266 | K63: =IFERROR('Raw Data'!J11/'Raw Data'!O11, "") -> -706.22115 | L63: ='Raw Data'!R11/'Raw Data'!C11 -> -0.045207204 | M63: =AVERAGE(_xlfn.RANK.EQ(C63,$C$6:$C$64,1), _xlfn.RANK.EQ(D63,$D$6:$D$64,1), _xlfn.RANK.EQ(E63,$E$6:$E$64,1) ) -> 19.333333 | N63: =AVERAGE( _xlfn.RANK.EQ(F63,$F$6:$F$64,0), _xlfn.RANK.EQ(G63,$G$6:$G$64,0), _xlfn.RANK.EQ(J63,$J$6:$J$64,0), _xlfn.RANK.EQ(K63,$K$6:$K$64,0) ) -> 59 | O63: =AVERAGE( _xlfn.RANK.EQ(H63,$H$6:$H$64,1), _xlfn.RANK.EQ(I63,$I$6:$I$64,0) ) -> 30 | P63: =_xlfn.RANK.EQ(L63,$L$6:$L$64,0) -> 54 | Q63: =AVERAGE(M63,N63,O63,P63) -> 40.583333 | R63: =IF(Q63<=20,"Excellent",IF(Q63<=25,"Very Good",IF(Q63<=30,"Decent",IF(Q63<=35,"Average","Weak/Avoid")))) -> Weak/Avoid
A64: ='Raw Data'!B39 -> Tata Power Company Limited | B64: =COUNTIF($C$69:$L$98,A64) -> 1 | C64: =('Raw Data'!D39+'Raw Data'!E39-'Raw Data'!F39)/'Raw Data'!H39 -> 12.223123 | D64: ='Raw Data'!C39/'Raw Data'!L39 -> 28.590229 | E64: ='Raw Data'!C39/'Raw Data'!N39 -> 3.2194433 | F64: ='Raw Data'!J39/'Raw Data'!M39 -> 0.14299554 | G64: ='Raw Data'!I39/('Raw Data'!M39+'Raw Data'!E39) -> 0.11259838 | H64: ='Raw Data'!E39/'Raw Data'!M39 -> 2.2308047 | I64: ='Raw Data'!I39/'Raw Data'!Q39 -> -2.3129906 | J64: ='Raw Data'!I39/'Raw Data'!O39 -> 0.15597461 | K64: =IFERROR('Raw Data'!J39/'Raw Data'!O39, "") -> 0.061310314 | L64: ='Raw Data'!R39/'Raw Data'!C39 -> 0.034976985 | M64: =AVERAGE(_xlfn.RANK.EQ(C64,$C$6:$C$64,1), _xlfn.RANK.EQ(D64,$D$6:$D$64,1), _xlfn.RANK.EQ(E64,$E$6:$E$64,1) ) -> 39.333333 | N64: =AVERAGE( _xlfn.RANK.EQ(F64,$F$6:$F$64,0), _xlfn.RANK.EQ(G64,$G$6:$G$64,0), _xlfn.RANK.EQ(J64,$J$6:$J$64,0), _xlfn.RANK.EQ(K64,$K$6:$K$64,0) ) -> 31.75 | O64: =AVERAGE( _xlfn.RANK.EQ(H64,$H$6:$H$64,1), _xlfn.RANK.EQ(I64,$I$6:$I$64,0) ) -> 39.5 | P64: =_xlfn.RANK.EQ(L64,$L$6:$L$64,0) -> 31 | Q64: =AVERAGE(M64,N64,O64,P64) -> 35.395833 | R64: =IF(Q64<=20,"Excellent",IF(Q64<=25,"Very Good",IF(Q64<=30,"Decent",IF(Q64<=35,"Average","Weak/Avoid")))) -> Weak/Avoid
C68: A | D68: B | E68: C | F68: D | G68: E | H68: F | I68: G | J68: H | K68: I | L68: J
C69: Adani Power Limited | D69: Adani Power Limited | E69: Agni Green Power Limited | F69: Adani Energy Solutions Limited | G69: Adani Energy Solutions Limited | H69: Adani Power Limited | I69: Gita Renewable Energy Limited | K69: Adani Energy Solutions Limited | L69: Adani Energy Solutions Limited
C70: Apex Ecotech Limited | D70: Apex Ecotech Limited | E70: CESC Limited | F70: Adani Green Energy Limited | G70: Adani Power Limited | H70: Adani Total Gas Limited | K70: Adani Green Energy Limited | L70: Adani Green Energy Limited
C71: CESC Limited | D71: CESC Limited | E71: GAIL (India) Limited | F71: Adani Power Limited | G71: Adani Total Gas Limited | H71: Agni Green Power Limited | K71: Adani Power Limited | L71: Adani Total Gas Limited
C72: Energy Development Company Limited | D72: Gujarat Gas Limited | F72: Adani Total Gas Limited | G72: Apex Ecotech Limited | H72: Apex Ecotech Limited | K72: Adani Total Gas Limited | L72: Agni Green Power Limited
C73: GAIL (India) Limited | D73: Gujarat Industries Power Company Limited | E73: Gujarat State Petronet Limited | F73: Apex Ecotech Limited | G73: Energy Development Company Limited | H73: CESC Limited | K73: Apex Ecotech Limited | L73: Indowind Energy Limited
C74: Gujarat Gas Limited | D74: Gujarat State Petronet Limited | F74: Energy Development Company Limited | G74: GAIL (India) Limited | H74: GAIL (India) Limited | K74: GAIL (India) Limited | L74: JSW Energy Limited
C75: Gujarat Industries Power Company Limited | D75: Indraprastha Gas Limited | E75: Indraprastha Gas Limited | F75: GAIL (India) Limited | G75: Gujarat Gas Limited | K75: Gujarat Industries Power Company Limited | L75: SG Mart Limited
C76: Indowind Energy Limited | D76: Jaiprakash Power Ventures Limited | E76: Jaiprakash Power Ventures Limited | F76: Indraprastha Gas Limited | G76: Gujarat State Petronet Limited | H76: Gujarat Gas Limited | K76: Indraprastha Gas Limited | L76: Siemens Energy India Limited
C77: Indraprastha Gas Limited | D77: K.P. Energy Limited | E77: JSW Energy Limited | F77: JSW Energy Limited | G77: Indowind Energy Limited | H77: Gujarat Industries Power Company Limited | K77: Jaiprakash Power Ventures Limited | L77: Waa Solar Limited
C78: Jaiprakash Power Ventures Limited | D78: KPI Green Energy Limited | E78: Jyoti Structures Limited | F78: K.P. Energy Limited | G78: Indraprastha Gas Limited | H78: Gujarat State Petronet Limited | K78: JSW Energy Limited | L78: Waaree Renewable Technologies Limited
C79: K.P. Energy Limited | D79: Mahanagar Gas Limited | E79: KKV Agro Powers Limited | F79: KKV Agro Powers Limited | G79: Jaiprakash Power Ventures Limited | H79: Indraprastha Gas Limited | K79: K.P. Energy Limited
C80: KPI Green Energy Limited | D80: Nava Limited | E80: KPI Green Energy Limited | F80: KPI Green Energy Limited | G80: K.P. Energy Limited | H80: K.P. Energy Limited | K80: KPI Green Energy Limited
C81: Nava Limited | D81: NHPC Limited | E81: Madhav Infra Projects Limited | F81: Madhav Infra Projects Limited | G81: KKV Agro Powers Limited | H81: KKV Agro Powers Limited | K81: Mahanagar Gas Limited
C82: NLC India Limited | D82: NLC India Limited | E82: Mahanagar Gas Limited | F82: Mahanagar Gas Limited | G82: KPI Green Energy Limited | H82: Madhav Infra Projects Limited | K82: Nava Limited
C83: NTPC Limited | D83: NTPC Limited | E83: Nava Limited | F83: NLC India Limited | G83: Madhav Infra Projects Limited | H83: Mahanagar Gas Limited | K83: NHPC Limited
C84: Orient Green Power Company Limited | D84: Orient Green Power Company Limited | E84: NHPC Limited | F84: Pace Digitek Limited | G84: Mahanagar Gas Limited | H84: Nava Limited | K84: NLC India Limited
C85: Pace Digitek Limited | D85: Pace Digitek Limited | E85: NLC India Limited | F85: Petronet LNG Limited | G85: Nava Limited | H85: NLC India Limited | K85: NTPC Green Energy Limited
C86: Power Grid Corporation of India Limited | D86: Petronet LNG Limited | E86: NTPC Limited | F86: Positron Energy Limited | G86: Pace Digitek Limited | H86: NTPC Limited | K86: NTPC Limited
C87: RattanIndia Power Limited | D87: Power Grid Corporation of India Limited | E87: Orient Green Power Company Limited | F87: Power Grid Corporation of India Limited | G87: Petronet LNG Limited | H87: Petronet LNG Limited | K87: Orient Green Power Company Limited
C88: Rudra Gas Enterprise Limited | D88: Rudra Gas Enterprise Limited | E88: Petronet LNG Limited | F88: PTC India Limited | G88: Positron Energy Limited | H88: Pace Digitek Limited | K88: Pace Digitek Limited
C89: Sugs Lloyd Limited | D89: Sugs Lloyd Limited | E89: Pace Digitek Limited | F89: Ravindra Energy Limited | G89: PTC India Limited | H89: Positron Energy Limited | K89: RattanIndia Power Limited
C90: Torrent Power Limited | D90: Torrent Power Limited | E90: Positron Energy Limited | F90: Rudra Gas Enterprise Limited | G90: Reliance Infrastructure Limited | H90: PTC India Limited | K90: Power Grid Corporation of India Limited
C91: Tata Power Company Limited | E91: Power Grid Corporation of India Limited | F91: Reliance Power Limited | G91: RattanIndia Power Limited | H91: Siemens Energy India Limited | K91: Reliance Infrastructure Limited
E92: RattanIndia Power Limited | F92: SG Mart Limited | G92: Rudra Gas Enterprise Limited | H92: Sugs Lloyd Limited | K92: Siemens Energy India Limited
E93: Reliance Power Limited | F93: Siemens Energy India Limited | G93: SG Mart Limited | H93: Torrent Power Limited | K93: SJVN Limited
E94: Rudra Gas Enterprise Limited | F94: Sugs Lloyd Limited | G94: Siemens Energy India Limited | H94: Waa Solar Limited | K94: Sugs Lloyd Limited
E95: SG Mart Limited | F95: Torrent Power Limited | G95: Sugs Lloyd Limited | H95: Waaree Renewable Technologies Limited | K95: Torrent Power Limited
E96: SJVN Limited | F96: Waaree Renewable Technologies Limited | G96: Torrent Power Limited | K96: Ujaas Energy Limited
E97: Sugs Lloyd Limited | G97: Waaree Renewable Technologies Limited | K97: Waa Solar Limited
K98: Waaree Renewable Technologies Limited

Sheet Sector details–Investor Summary
A1: Parameter | B1: Utilities Sector - Key Insights
A2: Sector Nature | B2: Regulated, capital-intensive sector with long asset life
A3: Revenue Model | B3: Revenues largely secured through long-term Power Purchase Agreements (PPAs)
A4: Demand Visibility | B4: Electricity demand is non-discretionary and grows with GDP
A5: Cost Structure | B5: Fuel cost is the largest variable expense
A6: Key Fuel Sources | B6: Coal, Gas, Hydro, Renewables
A7: Fuel Risk | B7: Imported fuel exposes companies to price volatility
A8: Role of PPAs | B8: PPAs provide tariff certainty and reduce demand risk
A9: Counterparty Risk | B9: State Electricity Boards (SEBs) are key buyers of power
A10: SEB Financial Health | B10: Weak SEB finances can lead to payment delays
A11: Regulatory Environment | B11: Returns influenced by government policies and tariff regulations
A12: Key Growth Drivers | B12: Power demand growth, renewable energy transition
... A14: Investor Suitability | B14: Suitable for long-term, defensive investors
A16: Investment Interpretation: Utilities offer stable cash flows with moderate returns. Companies with strong PPAs, low fuel risk, and sound balance sheets are better positioned for long-term investment.
A20: Fuel Source Analysis
A22: Company Name | B22: Primary Fuel Source | C22: Domestic / Imported | D22: Fuel Risk Level | E22: Key Comment
A23: NTPC Limited | B23: Coal | C23: Domestic | D23: Low | E23: Assured domestic coal linkage and long-term PPAs
A24: Power Grid Corporation of India Limited | B24: NA (Transmission) | C24: NA | D24: Low | E24: No fuel risk due to transmission business
A25: GAIL (India) Limited | B25: Natural Gas | C25: Mixed | D25: Medium | E25: Earnings sensitive to domestic and LNG prices
A26: Petronet LNG Limited | B26: LNG | C26: Imported | D26: Medium | E26: Long-term LNG contracts mitigate price volatility
A27: Indraprastha Gas Limited | B27: Natural Gas | C27: Mixed | D27: Low | E27: Cost pass-through allowed under regulatory framework
A28: Gujarat Gas Limited | B28: Natural Gas | C28: Mixed | D28: Medium | E28: Industrial demand sensitive to gas prices
A29: Gujarat State Petronet Limited | B29: Natural Gas | C29: Domestic | D29: Low | E29: Regulated gas transmission business
A30: NHPC Limited | B30: Hydropower | C30: Domestic | D30: Low | E30: No fuel cost; dependent on hydrology
A31: SJVN Limited | B31: Hydropower / Renewable | C31: Domestic | D31: Low | E31: Renewable-heavy portfolio with minimal fuel risk
A32: CESC Limited | B32: Coal | C32: Mixed | D32: Medium | E32: Partial exposure to imported coal
A35: Project Pipeline & Visibility
A37: Company Name | B37: Installed Capacity (Approx.) | C37: Projects Under Construction | D37: PPA Secured for New Projects | E37: Approval / Clearance Status | F37: Visibility Comment
A38: NTPC Limited | B38: ~75 GW | C38: Yes | D38: Yes | E38: Approved | F38: Strong long-term capacity addition with secured PPAs
A39: Power Grid Corporation of India Limited | B39: Transmission Network (Pan-India) | C39: Yes | D39: NA | E39: Approved | F39: Continuous capex backed by regulated returns
A40: GAIL (India) Limited | B40: Gas Transmission Network | C40: Yes | D40: NA | E40: Approved | F40: Expansion aligned with gas infrastructure growth
A41: Petronet LNG Limited | B41: LNG Terminals | C41: Yes | D41: Yes | E41: Approved | F41: Capacity expansion supported by long-term contracts
A42: Indraprastha Gas Limited | B42: CG Distribution Network | C42: Limited | D42: NA | E42: Approved | F42: Growth driven by city gas network expansion
A43: Gujarat Gas Limited | B43: CG Distribution Network | C43: Yes | D43: NA | E43: Approved | F43: Expansion in industrial and residential segments
A44: Gujarat State Petronet Limited | B44: Gas Pipeline Network | C44: Yes | D44: NA | E44: Approved | F44: Steady pipeline expansion within regulated framework
A45: NHPC Limited | B45: ~7 GW | C45: Yes | D45: Yes | E45: Partially Approved | F45: Execution dependent on project clearances
A46: SJVN Limited | B46: ~2 GW | C46: Yes | D46: Yes | E46: Partially Approved | F46: Aggressive expansion with execution risk
A47: CESC Limited | B47: ~3 GW | C47: Limited | D47: Yes | E47: Approved | F47: Limited growth outside core geography
A50: SEB Financial Health Summary
A52: Parameter | B52: Current Status | C52: Impact on Utilities Sector
A53: Overall SEB Financial Position | B53: Weak | C53: High accumulated losses impact timely payments
A54: Payment Delay Trend | B54: Common | C54: Causes cash flow timing issues for generators
A55: Government Support | B55: Ongoing | C55: State and central support reduces default risk
A56: Tariff Recovery | B56: Partial | C56: Not all costs are fully passed through
A57: Impact on Regulated Utilities | B57: Manageable | C57: Regulated returns provide some protection
A58: Impact on Merchant Power | B58: High Risk | C58: Higher exposure to delayed receivables
A59: Recent Reforms (UDAY, RDSS) | B59: In Progress | C59: Aimed at improving operational efficiency
A60: Overall Risk Assessment | B60: Medium | C60: SEB risk remains a structural concern
A63: Company Risk Profile
A65: Company Name | B65: Fuel Risk | C65: PPA Strength | D65: SEB Exposure | E65: Balance Sheet Risk | F65: Overall Risk Profile
A66: NTPC Limited | B66: Low | C66: High | D66: Medium | E66: Low | F66: Low
A67: Power Grid Corporation of India Limited | B67: Low | C67: High | D67: Low | E67: Low | F67: Very Low
A68: GAIL (India) Limited | B68: Medium | C68: Medium | D68: Low | E68: Low | F68: Medium
A69: Petronet LNG Limited | B69: Medium | C69: High | D69: Low | E69: Low | F69: Medium
A70: Indraprastha Gas Limited | B70: Low | C70: High | D70: Low | E70: Low | F70: Low
A71: Gujarat Gas Limited | B71: Medium | C71: Medium | D71: Low | E71: Low | F71: Medium
A72: Gujarat State Petronet Limited | B72: Low | C72: High | D72: Low | E72: Low | F72: Low
A73: NHPC Limited | B73: Low | C73: High | D73: Medium | E73: Medium | F73: Medium
A74: SJVN Limited | B74: Low | C74: Medium | D74: Medium | E74: Medium | F74: Medium–High
A75: CESC Limited | B75: Medium | C75: Medium | D75: Medium | E75: Medium | F75: Medium
A78: Investment Recommendation Summary
A80: Company Name | B80: Investment Category | C80: Key Investment Rationale
A81: NTPC Limited | B81: BUY | C81: Stable long-term PPAs, domestic fuel security, predictable cash flows
A82: Power Grid Corporation of India Limited | B82: BUY | C82: Regulated monopoly transmission business with very low risk
A83: Indraprastha Gas Limited | B83: BUY | C83: High ROE, low leverage, monopoly city gas distribution model
A84: GAIL (India) Limited | B84: HOLD | C84: Diversified gas business with exposure to LNG price volatility
A85: Petronet LNG Limited | B85: HOLD | C85: Strong margins supported by long-term contracts, demand-linked risk
A86: Gujarat Gas Limited | B86: HOLD | C86: Growth potential offset by industrial demand cyclicality
A87: Gujarat State Petronet Limited | B87: HOLD | C87: Stable regulated returns with limited expansion upside
A88: NHPC Limited | B88: AVOID | C88: Execution delays and capped regulated returns limit upside
A89: SJVN Limited | B89: AVOID | C89: Aggressive expansion increases leverage and execution risk
A90: CESC Limited | B90: AVOID | C90: Regional concentration and limited growth visibility
